Workbook
Name UPDATE: 'Data Sheet'!$E$1

Sheet DCF>

Sheet DCF
B2: ='Data Sheet'!B1 -> ITC LTD
B3: DCF
B5: Calculation of PV of FCFF
B7: Particulars | D7: ='Historicals FS'!L3 -> 46112 | E7: =D7+365 -> 46477 | F7: =E7+365 -> 46842 | G7: =F7+365 -> 47207 | H7: =G7+365 -> 47572 | I7: =H7+365 -> 47937
B8: EBIT | D8: ='Historicals FS'!L23 -> 25595.47 | E8: =D8*(1+E$9) -> 28546.858 | F8: =E8*(1+F$9) -> 31194.058 | G8: =F8*(1+G$9) -> 33382.461 | H8: =G8*(1+H$9) -> 34970.707 | I8: =H8*(1+I$9) -> 35844.975
B9: Faded Growth Rate | E9: =$D$21-(($D$21-$D$22)/5) -> 0.115309 | F9: =E9-(($D$21-$D$22)/5) -> 0.092731748 | G9: =F9-(($D$21-$D$22)/5) -> 0.070154498 | H9: =G9-(($D$21-$D$22)/5) -> 0.047577249 | I9: =H9-(($D$21-$D$22)/5) -> 0.025
B10: Tax Rate | D10: ='Master Input Center'!$C$4 -> 0.2517 | E10: ='Master Input Center'!$C$4 -> 0.2517 | F10: ='Master Input Center'!$C$4 -> 0.2517 | G10: ='Master Input Center'!$C$4 -> 0.2517 | H10: ='Master Input Center'!$C$4 -> 0.2517 | I10: ='Master Input Center'!$C$4 -> 0.2517
B11: NOPAT | D11: =D8*(1-D10) -> 19153.09 | E11: =E8*(1-E10) -> 21361.614 | F11: =F8*(1-F10) -> 23342.514 | G11: =G8*(1-G10) -> 24980.096 | H11: =H8*(1-H10) -> 26168.58 | I11: =I8*(1-I10) -> 26822.795
B12: Reinvestment rate | D12: ='Master Input Center'!C30 -> 0.1818709 | E12: =D12+(($I$12-$D$12)/5) -> 0.16549672 | F12: =E12+(($I$12-$D$12)/4) -> 0.14502899 | G12: =F12+(($I$12-$D$12)/4) -> 0.12456127 | H12: =G12+(($I$12-$D$12)/4) -> 0.10409354 | I12: ='Master Input Center'!C35 -> 0.1
B13: Free Cash Flow to firm | D13: =D11*(1-D12) -> 15669.7 | E13: =E11*(1-E12) -> 17826.337 | F13: =F11*(1-F12) -> 19957.172 | G13: =G11*(1-G12) -> 21868.543 | H13: =H11*(1-H12) -> 23444.6 | I13: =I11*(1-I12) -> 24140.515
B14: Mid Year convention | D14: 0 | E14: ='Master Input Center'!C36 -> 0.5 | F14: =YEARFRAC($E$7,F7,0)+$E$14 -> 1.5 | G14: =YEARFRAC($E$7,G7,0)+$E$14 -> 2.5 | H14: =YEARFRAC($E$7,H7,0)+$E$14 -> 3.5 | I14: =YEARFRAC($E$7,I7,0)+$E$14 -> 4.5
B15: Discounting Factor | D15: 0 | E15: =1/(1+$D$23)^E14 -> 0.95144421 | F15: =1/(1+$D$23)^F14 -> 0.86129115 | G15: =1/(1+$D$23)^G14 -> 0.77968044 | H15: =1/(1+$D$23)^H14 -> 0.70580267 | I15: =1/(1+$D$23)^I14 -> 0.63892511
B17: Pv of FCFF | E17: =E13*E15 -> 16960.765 | F17: =F13*F15 -> 17188.936 | G17: =G13*G15 -> 17050.476 | H17: =H13*H15 -> 16547.261 | I17: =I13*I15 -> 15423.981
F19: Calculation of Equity Value
B21: Growth Rate | D21: ='Master Input Center'!C31 -> 0.13788625 | F21: PV of FCFF | I21: =SUM(E13:I13) -> 107237.17
B22: Terminal Growth Rate | D22: ='Master Input Center'!C33 -> 0.025 | F22: Pv of Terminal Value | I22: =$D$31/(1+$D$23)^5 -> 133913.06
B23: WACC | D23: ='Master Input Center'!C32 -> 0.10467199 | F23: Value of Opening Asset | I23: =SUM(I21:I22) -> 241150.23
B25: Calculation of Terminal Value | F25: Add : Cash | I25: ='Raw Fs'!N45 -> 3009
F26: Add : Investments | I26: ='Raw Fs'!N35 -> 38128
B27: Normalized Base FCFF | D27: =I17*(1+$D$21) -> 17550.736 | F27: Less : Debt | I27: =SUM('Raw Fs'!N8:N9) -> 2186
B28: =B23 -> WACC | D28: =D23 -> 0.10467199 | F28: Value of Equity | I28: =I23+I25+I26-I27 -> 280101.23
B29: =B22 -> Terminal Growth Rate | D29: =D22 -> 0.025 | F29: No.of Shares | I29: ='Data Sheet'!K93 -> 1252.95
B31: Terminal Value | D31: =D27/(D28-D29) -> 220287.4 | F31: Equity value Per Share | I31: =I28/I29 -> 223.5534
B32: Conclusion: At a current market price of ₹268.00, ITC Ltd trades at a 1.20x premium to its intrinsic fair value of ₹223.60. The valuation incorporates a fading growth rate (13.79% tapering linearly to a 2.50% terminal growth rate), a stable cost of capital (10.47%) anchored to long-term target capital weights, and adds back ₹38,128 Cr of standalone investments (current and non-current, per Notes 4 and 9) as non-operating assets not captured within EBIT.
F33: Share Price | I33: 268
F34: =IF(I33>I31,"Premium","Discount") -> Premium | I34: =IF(I31>I33,1-(I33/I31),IF(I31<I33,(I33/I31)-1,0)) -> 0.19881873
B36: Sensitivity Table
C37: =I31 -> 223.5534 | D37: =E37-0.005 -> 0.094671993 | E37: =F37-0.005 -> 0.099671993 | F37: =$D$23 -> 0.10467199 | G37: =F37+0.005 -> 0.10967199 | H37: =G37+0.005 -> 0.11467199
C38: =C39-0.005 -> 0.02 | D38: 230.70991 | E38: 223.5534 | F38: 217.24209 | G38: 211.6346 | H38: 206.61942
B39: =F31 -> Equity value Per Share | C39: =$D$22 -> 0.025 | D39: 238.8936 | E39: 230.70991 | F39: 223.5534 | G39: 217.24209 | H39: 211.6346
C40: =C39+0.005 -> 0.03 | D40: 248.34269 | E40: 238.8936 | F40: 230.70991 | G40: 223.5534 | H40: 217.24209
C41: =C40+0.005 -> 0.035 | D41: 259.3753 | E41: 248.34269 | F41: 238.8936 | G41: 230.70991 | H41: 223.5534
C42: =C41+0.005 -> 0.04 | D42: 272.42587 | E42: 259.3753 | F42: 248.34269 | G42: 238.8936 | H42: 230.70991
C44: =I28 -> 280101.23 | D44: =E44-0.005 -> 0.094671993 | E44: =F44-0.005 -> 0.099671993 | F44: =$D$23 -> 0.10467199 | G44: =F44+0.005 -> 0.10967199 | H44: =G44+0.005 -> 0.11467199
C45: =C46-0.005 -> 0.02 | D45: 289067.98 | E45: 280101.23 | F45: 272193.48 | G45: 265167.57 | H45: 258883.8
B46: =F28 -> Value of Equity | C46: =$D$22 -> 0.025 | D46: 299321.73 | E46: 289067.98 | F46: 280101.23 | G46: 272193.48 | H46: 265167.57
C47: =C46+0.005 -> 0.03 | D47: 311160.98 | E47: 299321.73 | F47: 289067.98 | G47: 280101.23 | H47: 272193.48
C48: =C47+0.005 -> 0.035 | D48: 324984.28 | E48: 311160.98 | F48: 299321.73 | G48: 289067.98 | H48: 280101.23
C49: =C48+0.005 -> 0.04 | D49: 341335.99 | E49: 324984.28 | F49: 311160.98 | G49: 299321.73 | H49: 289067.98
B51: Notes
B52: 1. Linear fade from Start Growth Rate to Terminal Growth Rate over the 5-year explicit forecast, avoiding a discontinuous jump into the terminal value calculation.
B53: 2.Investment includes both Non-current (₹19,409 Cr, Note 4) and Current (₹19,702 Cr, Note 9) Investments — treated as non-operating financial assets since related income is excluded from EBIT.

Sheet WACC
B2: Weighted Average Cost of Capital
B4: Cost of Debt | G4: Cost of Equity
B6: Pre Tax Cost of Debt | E6: ='Master Input Center'!C21+'Master Input Center'!C22 -> 0.0727 | G6: Risk Free Rate | J6: ='Master Input Center'!C21 -> 0.0677
B7: Tax Rate | E7: ='Master Input Center'!C4 -> 0.2517 | G7: ERP | J7: ='Master Input Center'!C23 -> 0.0416
G8: Levered Beta | J8: ='Master Input Center'!C25 -> 0.89703267
B10: Post Tax Cost of Debt | E10: =E6*(1-E7) -> 0.05440141 | G10: Cost of Equity | J10: =J6+(J7*J8) -> 0.10501656
B12: Capital Structure | G12: Levered Beta (Peer Comps)
D13: Current | E13: Target
B14: Debt | C14: ='Comps Beta Calculation'!F20 -> 2399.06 | D14: =C14/$C$16 -> 0.0068075697 | E14: =D14 -> 0.0068075697 | G14: Comps Median Unlevered Beta | J14: ='Comps Beta Calculation'!K28 -> 0.94891811
B15: Equity | C15: ='Comps Beta Calculation'!E20 -> 350011.58 | D15: =C15/$C$16 -> 0.99319243 | E15: =D15 -> 0.99319243 | G15: Tax Rate | J15: ='Master Input Center'!C4 -> 0.2517
B16: Total | C16: =SUM(C14:C15) -> 352410.64 | D16: =C16/$C$16 -> 1 | E16: =D16 -> 1 | G16: Target Debt to Equity | J16: =E18 -> 0.0068542303
B18: Debt to Equity | D18: =D14/D15 -> 0.0068542303 | E18: =E14/E15 -> 0.0068542303 | G18: Levered Beta | J18: =J14*(1+(1-J15)*J16) -> 0.95378513
B19: Note on Capital Structure: WACC weights are hardcoded to management's long-term target capital structure (~99.3% Equity / 0.7% Debt). This framework is intentionally unlinked from the dynamic intrinsic value of equity to prevent circularity and to reflect the steady-state capitalized profile of the firm.
B21: Weighted Average Cost of Capital
B23: Cost of Equity | E23: =J10 -> 0.10501656
B24: Equity Weight | E24: =D15 -> 0.99319243
B25: Cost of Debt | E25: =E10 -> 0.05440141
B26: Debt Weight | E26: =D14 -> 0.0068075697
B28: WACC | E28: =(E23*E24)+(E25*E26) -> 0.10467199

Sheet Intrinsic Growth
B2: Calculation Of Intrinsic Growth
B3: Particulars | C3: ='Raw Fs'!I3 -> 44256 | D3: ='Raw Fs'!J3 -> 44621 | E3: ='Raw Fs'!K3 -> 44986 | F3: ='Raw Fs'!L3 -> 45352 | G3: ='Raw Fs'!M3 -> 45717 | H3: ='Raw Fs'!N3 -> 46082
B5: Calculation of ROIC
A7: # | B7: Current Assets
B8: ='Raw Fs'!B38 -> Inventories | C8: ='Raw Fs'!I38 -> 10397 | D8: ='Raw Fs'!J38 -> 10864 | E8: ='Raw Fs'!K38 -> 11771 | F8: ='Raw Fs'!L38 -> 14153 | G8: ='Raw Fs'!M38 -> 15638 | H8: ='Raw Fs'!N38 -> 18623
B9: ='Raw Fs'!B40 -> Trade receivables - | C9: =SUM('Raw Fs'!I41:I43) -> 2501 | D9: =SUM('Raw Fs'!J41:J43) -> 2462 | E9: =SUM('Raw Fs'!K41:K43) -> 2956 | F9: =SUM('Raw Fs'!L41:L43) -> 4026 | G9: =SUM('Raw Fs'!M41:M43) -> 4720 | H9: =SUM('Raw Fs'!N41:N43) -> 3923
B10: ='Raw Fs'!B46 -> Loans n Advances | C10: ='Raw Fs'!I46 -> 7 | D10: ='Raw Fs'!J46 -> 11 | E10: ='Raw Fs'!K46 -> 13 | F10: ='Raw Fs'!L46 -> 31 | G10: ='Raw Fs'!M46 -> 10 | H10: ='Raw Fs'!N46 -> 9
B11: ='Raw Fs'!B47 -> Other asset items | C11: ='Raw Fs'!I47 -> 4015 | D11: ='Raw Fs'!J47 -> 6906 | E11: ='Raw Fs'!K47 -> 7941 | F11: ='Raw Fs'!L47 -> 4531 | G11: ='Raw Fs'!M47 -> 5858 | H11: ='Raw Fs'!N47 -> 5901
B13: Current Assets | C13: =SUM(C8:C11) -> 16920 | D13: =SUM(D8:D11) -> 20243 | E13: =SUM(E8:E11) -> 22681 | F13: =SUM(F8:F11) -> 22741 | G13: =SUM(G8:G11) -> 26226 | H13: =SUM(H8:H11) -> 28456
A15: # | B15: Current Liabilities
B16: ='Raw Fs'!B13 -> Non controlling int | C16: ='Raw Fs'!I13 -> 347 | D16: ='Raw Fs'!J13 -> 366 | E16: ='Raw Fs'!K13 -> 384 | F16: ='Raw Fs'!L13 -> 383 | G16: ='Raw Fs'!M13 -> 368 | H16: ='Raw Fs'!N13 -> 366
B17: ='Raw Fs'!B14 -> Trade Payables | C17: ='Raw Fs'!I14 -> 4319 | D17: ='Raw Fs'!J14 -> 4417 | E17: ='Raw Fs'!K14 -> 4659 | F17: ='Raw Fs'!L14 -> 4798 | G17: ='Raw Fs'!M14 -> 4807 | H17: ='Raw Fs'!N14 -> 5640
B18: ='Raw Fs'!B15 -> Advance from Customers | C18: ='Raw Fs'!I15 -> 811 | D18: ='Raw Fs'!J15 -> 1278 | E18: ='Raw Fs'!K15 -> 1295 | F18: ='Raw Fs'!L15 -> 886 | G18: ='Raw Fs'!M15 -> 1264 | H18: ='Raw Fs'!N15 -> 1342
B19: ='Raw Fs'!B16 -> Other liability items | C19: ='Raw Fs'!I16 -> 7666 | D19: ='Raw Fs'!J16 -> 8429 | E19: ='Raw Fs'!K16 -> 10032 | F19: ='Raw Fs'!L16 -> 10877 | G19: ='Raw Fs'!M16 -> 11249 | H19: ='Raw Fs'!N16 -> 11384
B21: Current Liabilities | C21: =SUM(C16:C19) -> 13143 | D21: =SUM(D16:D19) -> 14490 | E21: =SUM(E16:E19) -> 16370 | F21: =SUM(F16:F19) -> 16944 | G21: =SUM(G16:G19) -> 17688 | H21: =SUM(H16:H19) -> 18732
B23: Net Non Cash Working Capital | C23: =C13-C21 -> 3777 | D23: =D13-D21 -> 5753 | E23: =E13-E21 -> 6311 | F23: =F13-F21 -> 5797 | G23: =G13-G21 -> 8538 | H23: =H13-H21 -> 9724
A25: # | B25: Fixed Assets
B26: ='Raw Fs'!B21 -> Land | C26: ='Raw Fs'!I21 -> 2889 | D26: ='Raw Fs'!J21 -> 2829 | E26: ='Raw Fs'!K21 -> 2830 | F26: ='Raw Fs'!L21 -> 2865 | G26: ='Raw Fs'!M21 -> 1588 | H26: ='Raw Fs'!N21 -> 1633
B27: ='Raw Fs'!B22 -> Building | C27: ='Raw Fs'!I22 -> 8387 | D27: ='Raw Fs'!J22 -> 9100 | E27: ='Raw Fs'!K22 -> 9789 | F27: ='Raw Fs'!L22 -> 10944 | G27: ='Raw Fs'!M22 -> 7550 | H27: ='Raw Fs'!N22 -> 7791
B28: ='Raw Fs'!B23 -> Plant Machinery | C28: ='Raw Fs'!I23 -> 15307 | D28: ='Raw Fs'!J23 -> 16912 | E28: ='Raw Fs'!K23 -> 18480 | F28: ='Raw Fs'!L23 -> 20718 | G28: ='Raw Fs'!M23 -> 19423 | H28: ='Raw Fs'!N23 -> 20424
B29: ='Raw Fs'!B24 -> Equipment | C29: ='Raw Fs'!I24 -> 41 | D29: ='Raw Fs'!J24 -> 44 | E29: ='Raw Fs'!K24 -> 44 | F29: ='Raw Fs'!L24 -> 53 | G29: ='Raw Fs'!M24 -> 63 | H29: ='Raw Fs'!N24 -> 75
B30: ='Raw Fs'!B25 -> Furniture n fittings | C30: ='Raw Fs'!I25 -> 833 | D30: ='Raw Fs'!J25 -> 907 | E30: ='Raw Fs'!K25 -> 1000 | F30: ='Raw Fs'!L25 -> 1068 | G30: ='Raw Fs'!M25 -> 282 | H30: ='Raw Fs'!N25 -> 304
B31: ='Raw Fs'!B26 -> Railway sidings | C31: ='Raw Fs'!I26 -> 2 | D31: ='Raw Fs'!J26 -> 2 | E31: ='Raw Fs'!K26 -> 2 | F31: ='Raw Fs'!L26 -> 2 | G31: ='Raw Fs'!M26 -> 2 | H31: ='Raw Fs'!N26 -> 2
B32: ='Raw Fs'!B27 -> Vehicles | C32: ='Raw Fs'!I27 -> 180 | D32: ='Raw Fs'!J27 -> 179 | E32: ='Raw Fs'!K27 -> 189 | F32: ='Raw Fs'!L27 -> 192 | G32: ='Raw Fs'!M27 -> 141 | H32: ='Raw Fs'!N27 -> 155
B33: ='Raw Fs'!B28 -> Intangible Assets | C33: ='Raw Fs'!I28 -> 2734 | D33: ='Raw Fs'!J28 -> 2744 | E33: ='Raw Fs'!K28 -> 3490 | F33: ='Raw Fs'!L28 -> 3505 | G33: ='Raw Fs'!M28 -> 3622 | H33: ='Raw Fs'!N28 -> 4248
B34: ='Raw Fs'!B29 -> Other fixed assets | C34: ='Raw Fs'!I29 -> 716 | D34: ='Raw Fs'!J29 -> 719 | E34: ='Raw Fs'!K29 -> 786 | F34: ='Raw Fs'!L29 -> 841 | G34: ='Raw Fs'!M29 -> 967 | H34: ='Raw Fs'!N29 -> 1041
B35: ='Raw Fs'!B30 -> Gross Block | C35: =SUM(C26:C34) -> 31089 | D35: =SUM(D26:D34) -> 33436 | E35: =SUM(E26:E34) -> 36610 | F35: =SUM(F26:F34) -> 40188 | G35: =SUM(G26:G34) -> 33638 | H35: =SUM(H26:H34) -> 35673
B36: ='Raw Fs'!B31 -> Accumulated Depreciation | C36: =-'Raw Fs'!I31 -> -7790 | D36: =-'Raw Fs'!J31 -> -9204 | E36: =-'Raw Fs'!K31 -> -10757 | F36: =-'Raw Fs'!L31 -> -12368 | G36: =-'Raw Fs'!M31 -> -11683 | H36: =-'Raw Fs'!N31 -> -13230
B38: ='Raw Fs'!B32 -> Net Block | C38: =C35+C36 -> 23299 | D38: =D35+D36 -> 24232 | E38: =E35+E36 -> 25853 | F38: =F35+F36 -> 27820 | G38: =G35+G36 -> 21955 | H38: =H35+H36 -> 22443
A40: # | B40: Invested Capital | C40: =C23+C38 -> 27076 | D40: =D23+D38 -> 29985 | E40: =E23+E38 -> 32164 | F40: =F23+F38 -> 33617 | G40: =G23+G38 -> 30493 | H40: =H23+H38 -> 32167
B41: ='Historicals FS'!B23 -> EBIT | C41: ='Historicals FS'!G23 -> 15419.19 | D41: ='Historicals FS'!H23 -> 18890.74 | E41: ='Historicals FS'!I23 -> 23895.25 | F41: ='Historicals FS'!J23 -> 23669.48 | G41: ='Historicals FS'!K23 -> 24185.26 | H41: ='Historicals FS'!L23 -> 25595.47
B43: ROIC | C43: =C41/C40 -> 0.56947814 | D43: =D41/D40 -> 0.63000634 | E43: =E41/E40 -> 0.7429191 | F43: =F41/F40 -> 0.70409257 | G43: =G41/G40 -> 0.79314138 | H43: =H41/H40 -> 0.79570585
F45: Five Year Average | H45: =AVERAGE(C43:H43) -> 0.70589056
F46: Five Year Median | H46: =MEDIAN(C43:H43) -> 0.72350584
B50: Calculation of Reinvestment Rate
B52: Net Capex | D52: =-SUM('Cash Flows'!J13:J14) -> 2009 | E52: =-SUM('Cash Flows'!K13:K14) -> 2694 | F52: =-SUM('Cash Flows'!L13:L14) -> 3456 | G52: =-SUM('Cash Flows'!M13:M14) -> 2104 | H52: =-SUM('Cash Flows'!N13:N14) -> 2133
B53: Change in Working Capital | D53: =D23-C23 -> 1976 | E53: =E23-D23 -> 558 | F53: =F23-E23 -> -514 | G53: =G23-F23 -> 2741 | H53: =H23-G23 -> 1186
B55: Reinvestment Amount | D55: =D52+D53 -> 3985 | E55: =E52+E53 -> 3252 | F55: =F52+F53 -> 2942 | G55: =G52+G53 -> 4845 | H55: =H52+H53 -> 3319
B57: EBIT | D57: =D41 -> 18890.74 | E57: =E41 -> 23895.25 | F57: =F41 -> 23669.48 | G57: =G41 -> 24185.26 | H57: =H41 -> 25595.47
B58: Tax Rate | D58: ='Master Input Center'!$C$4 -> 0.2517 | E58: ='Master Input Center'!$C$4 -> 0.2517 | F58: ='Master Input Center'!$C$4 -> 0.2517 | G58: ='Master Input Center'!$C$4 -> 0.2517 | H58: ='Master Input Center'!$C$4 -> 0.2517
B60: NOPAT | D60: =D57*(1-D58) -> 14135.941 | E60: =E57*(1-E58) -> 17880.816 | F60: =F57*(1-F58) -> 17711.872 | G60: =G57*(1-G58) -> 18097.83 | H60: =H57*(1-H58) -> 19153.09
B62: Reinvestment Rate | D62: =D55/D60 -> 0.28190554 | E62: =E55/E60 -> 0.1818709 | F62: =F55/F60 -> 0.16610328 | G62: =G55/G60 -> 0.26771165 | H62: =H55/H60 -> 0.17328796
F64: Four Year Average | H64: =AVERAGE(D62:H62) -> 0.21417587
F65: Four Year Median | H65: =MEDIAN(D62:H62) -> 0.1818709
F66: 75th Percentile | H66: =PERCENTILE(D62:H62,0.75) -> 0.26771165
F67: 25th Percentile | H67: =PERCENTILE(D62:H62,0.25) -> 0.17328796
B69: Calculation of Growth Rate
B71: =B43 -> ROIC | D71: =D43 -> 0.63000634 | E71: =E43 -> 0.7429191 | F71: =F43 -> 0.70409257 | G71: =G43 -> 0.79314138 | H71: =H43 -> 0.79570585
B72: =B62 -> Reinvestment Rate | D72: =D62 -> 0.28190554 | E72: =E62 -> 0.1818709 | F72: =F62 -> 0.16610328 | G72: =G62 -> 0.26771165 | H72: =H62 -> 0.17328796
B74: Growth Rate | D74: =D71*D72 -> 0.17760228 | E74: =E71*E72 -> 0.13511536 | F74: =F71*F72 -> 0.11695209 | G74: =G71*G72 -> 0.21233319 | H74: =H71*H72 -> 0.13788625
F76: Four Year Average | H76: =AVERAGE(D74:H74) -> 0.15597783
F77: Four Year Median | H77: =MEDIAN(D74:H74) -> 0.13788625
F78: 75th Percentile | H78: =PERCENTILE(D74:H74,0.75) -> 0.17760228
F79: 25th Percentile | H79: =PERCENTILE(D74:H74,0.25) -> 0.13511536
B81: Notes
B82: 1. For calculating net Working Capital, Operating approach has been used
B83: 2.Historical figures for FY25 (Mar-25) reflect the ITC Hotels demerger, completed during that fiscal year — PP&E, working capital, and associated revenue/EBIT were transferred out mid-year (per Company's FY26 Annual Report, Note 3A). Excluding FY25 from the growth calculation, the four-year median growth rate is 15.64%, versus 13.79% used in this model (which includes the demerger-affected year) — a ~1.85pp difference. This suggests the demerger year meaningfully depressed the calculated organic growth trend, and the Start Growth Rate used here may be conservative relative to a clean continuing-operations basis.

Sheet Comps Beta Calculation
B2: Beta Calculation
B4: Comps
B7: Beta Drifting (peer comps)
C8: Raw | D8: Raw | E8: Raw Beta | F8: Market | G8: Market Beta | H8: Adjusted
B9: Company Name | C9: Beta1 | D9: Beta2 | E9: Weight | F9: Beta | G9: Weight | H9: Beta
B10: ='Daily Adjusted closings'!I3 -> ITC LTD | C10: =SLOPE('Daily Adjusted closings'!J6:J64,'Daily Adjusted closings'!$G$6:$G$64) -> 0.84554901 | D10: =_xlfn.COVARIANCE.S('Daily Adjusted closings'!J6:J64,'Daily Adjusted closings'!$G$6:$G$64)/_xlfn.VAR.S('Daily Adjusted closings'!$G$6:$G$64) -> 0.84554901 | E10: ='Master Input Center'!$C$16 -> 0.66666667 | F10: ='Master Input Center'!$C$15 -> 1 | G10: ='Master Input Center'!$C$17 -> 0.33333333 | H10: =(C10*E10)+(F10*G10) -> 0.89703267
B11: ='Daily Adjusted closings'!L3 -> Hindustan Unilever Ltd | C11: =SLOPE('Daily Adjusted closings'!M6:M64,'Daily Adjusted closings'!$G$6:$G$64) -> 0.8846964 | D11: =_xlfn.COVARIANCE.S('Daily Adjusted closings'!M6:M64,'Daily Adjusted closings'!$G$6:$G$64)/_xlfn.VAR.S('Daily Adjusted closings'!$G$6:$G$64) -> 0.8846964 | E11: ='Master Input Center'!$C$16 -> 0.66666667 | F11: ='Master Input Center'!$C$15 -> 1 | G11: ='Master Input Center'!$C$17 -> 0.33333333 | H11: =(C11*E11)+(F11*G11) -> 0.92313093
B12: ='Daily Adjusted closings'!O3 -> Nestle India Ltd | C12: =SLOPE('Daily Adjusted closings'!P6:P64,'Daily Adjusted closings'!$G$6:$G$64) -> 1.0413293 | D12: =_xlfn.COVARIANCE.S('Daily Adjusted closings'!P6:P64,'Daily Adjusted closings'!$G$6:$G$64)/_xlfn.VAR.S('Daily Adjusted closings'!$G$6:$G$64) -> 1.0413293 | E12: ='Master Input Center'!$C$16 -> 0.66666667 | F12: ='Master Input Center'!$C$15 -> 1 | G12: ='Master Input Center'!$C$17 -> 0.33333333 | H12: =(C12*E12)+(F12*G12) -> 1.0275529
B13: ='Daily Adjusted closings'!R3 -> Britannia Industries Ltd | C13: =SLOPE('Daily Adjusted closings'!S6:S64,'Daily Adjusted closings'!$G$6:$G$64) -> 0.97746311 | D13: =_xlfn.COVARIANCE.S('Daily Adjusted closings'!S6:S64,'Daily Adjusted closings'!$G$6:$G$64)/_xlfn.VAR.S('Daily Adjusted closings'!$G$6:$G$64) -> 0.97746311 | E13: ='Master Input Center'!$C$16 -> 0.66666667 | F13: ='Master Input Center'!$C$15 -> 1 | G13: ='Master Input Center'!$C$17 -> 0.33333333 | H13: =(C13*E13)+(F13*G13) -> 0.9849754
B14: ='Daily Adjusted closings'!U3 -> Godrej Consumer Products Limited | C14: =SLOPE('Daily Adjusted closings'!V6:V64,'Daily Adjusted closings'!$G$6:$G$64) -> 1.0238073 | D14: =_xlfn.COVARIANCE.S('Daily Adjusted closings'!V6:V64,'Daily Adjusted closings'!$G$6:$G$64)/_xlfn.VAR.S('Daily Adjusted closings'!$G$6:$G$64) -> 1.0238073 | E14: ='Master Input Center'!$C$16 -> 0.66666667 | F14: ='Master Input Center'!$C$15 -> 1 | G14: ='Master Input Center'!$C$17 -> 0.33333333 | H14: =(C14*E14)+(F14*G14) -> 1.0158715
B15: ='Daily Adjusted closings'!X3 -> Dabur India Ltd | C15: =SLOPE('Daily Adjusted closings'!Y6:Y64,'Daily Adjusted closings'!$G$6:$G$64) -> 0.86542745 | D15: =_xlfn.COVARIANCE.S('Daily Adjusted closings'!Y6:Y64,'Daily Adjusted closings'!$G$6:$G$64)/_xlfn.VAR.S('Daily Adjusted closings'!$G$6:$G$64) -> 0.86542745 | E15: ='Master Input Center'!$C$16 -> 0.66666667 | F15: ='Master Input Center'!$C$15 -> 1 | G15: ='Master Input Center'!$C$17 -> 0.33333333 | H15: =(C15*E15)+(F15*G15) -> 0.91028497
B17: Peer comps Data Table
H18: Debt/ | I18: Debt/ | J18: Levered | K18: Unlevered
B19: =B9 -> Company Name | C19: Ticker | D19: Country | E19: Equity | F19: Debt | G19: Tax | H19: Equity | I19: Capital | J19: Beta | K19: Beta
B20: =B10 -> ITC LTD | C20: ='Daily Adjusted closings'!I4 -> ITC | D20: ='Master Input Center'!$C$14 -> India | E20: ='Comps Data'!G3 -> 350011.58 | F20: ='Comps Data'!H3 -> 2399.06 | G20: ='Master Input Center'!C4 -> 0.2517 | H20: =F20/E20 -> 0.0068542303 | I20: =F20/SUM(E20:F20) -> 0.0068075697 | J20: =H10 -> 0.89703267 | K20: =J20/(1+(1-G20)*H20) -> 0.89245525
B21: =B11 -> Hindustan Unilever Ltd | C21: ='Daily Adjusted closings'!L4 -> HINDUNILVR | D21: ='Master Input Center'!$C$14 -> India | E21: ='Comps Data'!G5 -> 493040.06 | F21: ='Comps Data'!H5 -> 1478 | G21: ='Comps Data'!V5 -> 0.22495907 | H21: =F21/E21 -> 0.002997728 | I21: =F21/SUM(E21:F21) -> 0.0029887685 | J21: =H11 -> 0.92313093 | K21: =J21/(1+(1-G21)*H21) -> 0.92099114
B22: =B12 -> Nestle India Ltd | C22: ='Daily Adjusted closings'!O4 -> NESTLEIND | D22: ='Master Input Center'!$C$14 -> India | E22: ='Comps Data'!G6 -> 274493.51 | F22: ='Comps Data'!H6 -> 444.16 | G22: ='Comps Data'!V6 -> 0.2374757 | H22: =F22/E22 -> 0.0016181075 | I22: =F22/SUM(E22:F22) -> 0.0016154935 | J22: =H12 -> 1.0275529 | K22: =J22/(1+(1-G22)*H22) -> 1.0262866
B23: =B13 -> Britannia Industries Ltd | C23: ='Daily Adjusted closings'!R4 -> BRITANNIA | D23: ='Master Input Center'!$C$14 -> India | E23: ='Comps Data'!G8 -> 127929.94 | F23: ='Comps Data'!H8 -> 1380.28 | G23: ='Comps Data'!V8 -> 0.22858628 | H23: =F23/E23 -> 0.010789343 | I23: =F23/SUM(E23:F23) -> 0.010674175 | J23: =H13 -> 0.9849754 | K23: =J23/(1+(1-G23)*H23) -> 0.97684508
B24: =B14 -> Godrej Consumer Products Limited | C24: ='Daily Adjusted closings'!U4 -> GODREJCP.NS | D24: ='Master Input Center'!$C$14 -> India | E24: ='Comps Data'!G10 -> 108234.44 | F24: ='Comps Data'!H10 -> 4415.81 | G24: ='Comps Data'!V10 -> 0.25809776 | H24: =F24/E24 -> 0.040798566 | I24: =F24/SUM(E24:F24) -> 0.039199291 | J24: =H14 -> 1.0158715 | K24: =J24/(1+(1-G24)*H24) -> 0.98602596
B25: =B15 -> Dabur India Ltd | C25: ='Daily Adjusted closings'!X4 -> DABUR | D25: ='Master Input Center'!$C$14 -> India | E25: ='Comps Data'!G13 -> 76184.43 | F25: ='Comps Data'!H13 -> 1287.32 | G25: ='Comps Data'!V13 -> 0.22847323 | H25: =F25/E25 -> 0.016897416 | I25: =F25/SUM(E25:F25) -> 0.016616638 | J25: =H15 -> 0.91028497 | K25: =J25/(1+(1-G25)*H25) -> 0.89857047
F27: Average | G27: =AVERAGE(G20:G25) -> 0.23821534 | H27: =AVERAGE(H20:H25) -> 0.013325898 | I27: =AVERAGE(I20:I25) -> 0.012983656 | J27: =AVERAGE(J20:J25) -> 0.95980806 | K27: =AVERAGE(K20:K25) -> 0.95019575
F28: Median | G28: =MEDIAN(G20:G25) -> 0.23303099 | H28: =MEDIAN(H20:H25) -> 0.0088217864 | I28: =MEDIAN(I20:I25) -> 0.0087408724 | J28: =MEDIAN(J20:J25) -> 0.95405317 | K28: =MEDIAN(K20:K25) -> 0.94891811
B30: Notes:
B31: The weight for adjusted beta taken from Bloomberg 2026 data.
B32: The comps tax rate has been calculated by Tax Amount/EBT for last Year
B33: Standalone Blume-adjusted beta (0.90) used rather than peer-comps beta (0.95), as ITC's diversified conglomerate structure (cigarettes, FMCG, agri, paperboards) makes pure-play FMCG peers imperfectly comparable.

Sheet SOTP>

Sheet SOTP - Valuation
B1: ='Data Sheet'!B1 -> ITC LTD
B2: SOTP
B4: Calculation of SOTP
B6: Segment | C6: Metric Used | D6: Multiple Source | E6: Metric Value | F6: Multiple | G6: Segment EV
B7: Cigarettes | C7: EBITDA | D7: Godfrey Phillips, Comps Data | E7: ='SOTP - Segment Data'!H3 -> 21315.18 | F7: {=MEDIAN(IF('Comps Data'!$D$5:$D$22=B7,'Comps Data'!$P$5:$P$22))} -> 16.066213 | G7: =E7*F7 -> 342454.22
B8: FMCG-Others | C8: Total Revenue | D8: Median of 7-peer EV/Sales | E8: ='SOTP - Segment Data'!E4 -> 24209.75 | F8: {=MEDIAN(IF('Comps Data'!$D$5:$D$22=B8,'Comps Data'!$Q$5:$Q$22))} -> 7.6203708 | G8: =E8*F8 -> 184487.27
B9: Agri Business | C9: External Revenue | D9: AWL Agri Business EV/Sales | E9: ='SOTP - Segment Data'!C5 -> 12296.48 | F9: {=MEDIAN(IF('Comps Data'!$D$5:$D$22=B9,'Comps Data'!$Q$5:$Q$22))} -> 0.30041922 | G9: =E9*F9 -> 3694.0989
B10: Paperboards | C10: EBITDA | D10: Median of 3-peer EV/EBITDA | E10: ='SOTP - Segment Data'!H6 -> 1187.1 | F10: {=MEDIAN(IF('Comps Data'!$D$5:$D$22=B10,'Comps Data'!$P$5:$P$22))} -> 8.2846754 | G10: =E10*F10 -> 9834.7382
B11: Others | C11: - | D11: Net segment assets (Assets - Liabilities) | F11: 0 | G11: 159.71
B13: Sum of Segment Evs | G13: =SUM(G7:G11) -> 540630.04
B14: Less: Unallocated corporate costs adjustment | G14: =('Master Input Center'!C46*(1-'Master Input Center'!C4))/'Master Input Center'!C47 -> 8784.9047
B15: Total Enterprise Value (SOTP) | G15: =G13-G14 -> 531845.14
B16: Add : Cash | G16: =DCF!I25 -> 3009
B17: Add : Investments | G17: =DCF!I26 -> 38128
B18: Less : Debt | G18: =DCF!I27 -> 2186
B19: Value of Equity | G19: =G15+G16+G17-G18 -> 570796.14
B20: No.of Shares | G20: =DCF!I29 -> 1252.95
B22: SOTP Value Per Share | G22: =G19/G20 -> 455.56179
B24: Share Price | G24: =DCF!I33 -> 268
B25: =IF(G24>G22,"Premium","Discount") -> Discount | G25: =IF(G22>G24,1-(G24/G22),IF(G22<G24,(G24/G22)-1,0)) -> 0.41171536
B27: SOTP Methodology Note
B29: Basis: Segment Revenue/EBIT/D&A from ITC FY2026 Annual Report, Note 30.
B31: Method by segment:
B33: 1. Cigarettes — EV/EBITDA 16.1x (Godfrey Phillips, sole peer). Stable, high-margin.
B34: 2. FMCG–Others — EV/Sales 7.6x (median: HUL, Nestlé, Britannia, Marico, Godrej Consumer, Dabur, Colgate). EV/Sales used, not EV/EBITDA, since segment EBITDA margin (~10%) is depressed by brand-building/gestation costs per the segment note — not representative of steady-state profitability. Alcohol/bottling/tea peers excluded (no equivalent business in this segment).
B35: 3. Agri Business - EV/Sales 0.30x (AWL Agri, sole peer), applied to external revenue only - excludes inter-segment leaf-tobacco transfers to Cigarettes.
B36: 4. Paperboards — EV/EBITDA 8.28x (median: JK Paper, West Coast Paper, Seshasayee). Andhra Paper excluded — outlier multiple from temporarily depressed earnings, not a real premium.
B37: 5. Others — Net segment assets (₹159.71 Cr); EBIT negative and segment immaterial (<0.5% of revenue).
B38: 6. Unallocated corporate cost: ₹1,228.83 Cr capitalized as a perpetuity (Cost × (1–Tax)/WACC), not subtracted once, since it recurs indefinitely. Tax and WACC linked to the same DCF assumptions.
B39: 7. Limitations: Cigarettes and Agri each rest on a single peer. Sensitivity testing shows Cigarettes drives the output materially (±30% multiple ˜ ±₹80–90/share); Agri is immaterial (<₹1/share) due to its small scale. WACC/Tax swings affect the output by <1%.
B40: 8. vs. DCF: SOTP (₹455.6/share) exceeds DCF (₹223.60/share) because DCF applies one blended growth/discount profile to segments with very different real profiles (mature Cigarettes vs. early-stage FMCG–Others). Read as a conglomerate-discount signal, consistent with the ~41% gap to current market price — not a contradiction between methods.

Sheet Data>

Sheet Altman's Z Score
B2: ='Data Sheet'!B1 -> ITC LTD
B3: Altman's Z Score Analysis Charts
B45: ='Data Sheet'!B1 -> ITC LTD
B46: Altman's Z Score Analysis
B47: Particulars | D47: ='Common Size Statements'!G$4 -> 44286 | E47: ='Common Size Statements'!H$4 -> 44651 | F47: ='Common Size Statements'!I$4 -> 45016 | G47: ='Common Size Statements'!J$4 -> 45382 | H47: ='Common Size Statements'!K$4 -> 45747 | I47: ='Common Size Statements'!L$4 -> 46112
B49: Working Capital / Total Asset (A)
B51: Working Capital | D51: ='Intrinsic Growth'!C23 -> 3777 | E51: ='Intrinsic Growth'!D23 -> 5753 | F51: ='Intrinsic Growth'!E23 -> 6311 | G51: ='Intrinsic Growth'!F23 -> 5797 | H51: ='Intrinsic Growth'!G23 -> 8538 | I51: ='Intrinsic Growth'!H23 -> 9724
B52: Total Asset | D52: ='Historicals FS'!G71 -> 73760.76 | E52: ='Historicals FS'!H71 -> 77196.02 | F52: ='Historicals FS'!I71 -> 85830.96 | G52: ='Historicals FS'!J71 -> 91753.97 | H52: ='Historicals FS'!K71 -> 88002.7 | I52: ='Historicals FS'!L71 -> 93637.2
B54: =B49 -> Working Capital / Total Asset (A) | D54: =D51/D52 -> 0.051206088 | E54: =E51/E52 -> 0.074524567 | F54: =F51/F52 -> 0.073528247 | G54: =G51/G52 -> 0.063179828 | H54: =H51/H52 -> 0.097019751 | I54: =I51/I52 -> 0.10384762
B56: Retained Earnings / Total Asset (B)
B57: Particulars | D57: ='Common Size Statements'!G$4 -> 44286 | E57: ='Common Size Statements'!H$4 -> 44651 | F57: ='Common Size Statements'!I$4 -> 45016 | G57: ='Common Size Statements'!J$4 -> 45382 | H57: ='Common Size Statements'!K$4 -> 45747 | I57: ='Common Size Statements'!L$4 -> 46112
B59: Retained Earnings | D59: ='Historicals FS'!G57 -> 59116.46 | E59: ='Historicals FS'!H57 -> 61223.24 | F59: ='Historicals FS'!I57 -> 67912.46 | G59: ='Historicals FS'!J57 -> 73258.53 | H59: ='Historicals FS'!K57 -> 68778.64 | I59: ='Historicals FS'!L57 -> 71254.35
B60: Total Assets | D60: =D52 -> 73760.76 | E60: =E52 -> 77196.02 | F60: =F52 -> 85830.96 | G60: =G52 -> 91753.97 | H60: =H52 -> 88002.7 | I60: =I52 -> 93637.2
B62: =B56 -> Retained Earnings / Total Asset (B) | D62: =D59/D60 -> 0.80146219 | E62: =E59/E60 -> 0.79308804 | F62: =F59/F60 -> 0.791235 | G62: =G59/G60 -> 0.79842355 | H62: =H59/H60 -> 0.78155148 | I62: =I59/I60 -> 0.76096199
B64: EBIT / Total Asset (C)
B65: Particulars | D65: ='Common Size Statements'!G$4 -> 44286 | E65: ='Common Size Statements'!H$4 -> 44651 | F65: ='Common Size Statements'!I$4 -> 45016 | G65: ='Common Size Statements'!J$4 -> 45382 | H65: ='Common Size Statements'!K$4 -> 45747 | I65: ='Common Size Statements'!L$4 -> 46112
B67: EBIT | D67: ='Historicals FS'!G23 -> 15419.19 | E67: ='Historicals FS'!H23 -> 18890.74 | F67: ='Historicals FS'!I23 -> 23895.25 | G67: ='Historicals FS'!J23 -> 23669.48 | H67: ='Historicals FS'!K23 -> 24185.26 | I67: ='Historicals FS'!L23 -> 25595.47
B68: Total Asset | D68: =D52 -> 73760.76 | E68: =E52 -> 77196.02 | F68: =F52 -> 85830.96 | G68: =G52 -> 91753.97 | H68: =H52 -> 88002.7 | I68: =I52 -> 93637.2
B70: =B64 -> EBIT / Total Asset (C) | D70: =D67/D68 -> 0.20904326 | E70: =E67/E68 -> 0.24471132 | F70: =F67/F68 -> 0.27839896 | G70: =G67/G68 -> 0.25796682 | H70: =H67/H68 -> 0.27482407 | I70: =I67/I68 -> 0.27334724
B72: Market Cap. / Total Liabilities (D)
B73: Particulars | D73: ='Common Size Statements'!G$4 -> 44286 | E73: ='Common Size Statements'!H$4 -> 44651 | F73: ='Common Size Statements'!I$4 -> 45016 | G73: ='Common Size Statements'!J$4 -> 45382 | H73: ='Common Size Statements'!K$4 -> 45747 | I73: ='Common Size Statements'!L$4 -> 46112
B75: Market Cap. | D75: ='Data Sheet'!F90*'Data Sheet'!F93 -> 252108.84 | E75: ='Data Sheet'!G90*'Data Sheet'!G93 -> 289548.26 | F75: ='Data Sheet'!H90*'Data Sheet'!H93 -> 446774.17 | G75: ='Data Sheet'!I90*'Data Sheet'!I93 -> 501298.16 | H75: ='Data Sheet'!J90*'Data Sheet'!J93 -> 512765.25 | I75: ='Data Sheet'!K90*'Data Sheet'!K93 -> 360473.72
B76: Total Liabilities | D76: =SUM('Historicals FS'!G58:G59) -> 13413.42 | E76: =SUM('Historicals FS'!H58:H59) -> 14740.45 | F76: =SUM('Historicals FS'!I58:I59) -> 16675.7 | G76: =SUM('Historicals FS'!J58:J59) -> 17246.97 | H76: =SUM('Historicals FS'!K58:K59) -> 17972.65 | I76: =SUM('Historicals FS'!L58:L59) -> 21129.9
B78: =B72 -> Market Cap. / Total Liabilities (D) | D78: =D75/D76 -> 18.795269 | E78: =E75/E76 -> 19.643108 | F78: =F75/F76 -> 26.791929 | G78: =G75/G76 -> 29.065868 | H78: =H75/H76 -> 28.530308 | I78: =I75/I76 -> 17.059887
B80: Sales / Total Asset (E)
B81: Particulars | D81: ='Common Size Statements'!G$4 -> 44286 | E81: ='Common Size Statements'!H$4 -> 44651 | F81: ='Common Size Statements'!I$4 -> 45016 | G81: ='Common Size Statements'!J$4 -> 45382 | H81: ='Common Size Statements'!K$4 -> 45747 | I81: ='Common Size Statements'!L$4 -> 46112
B83: Sales | D83: ='Historicals FS'!G5 -> 49257.45 | E83: ='Historicals FS'!H5 -> 60644.54 | F83: ='Historicals FS'!I5 -> 70919.03 | G83: ='Historicals FS'!J5 -> 67931.94 | H83: ='Historicals FS'!K5 -> 75323.34 | I83: ='Historicals FS'!L5 -> 78868.4
B84: Total Asset | D84: =D52 -> 73760.76 | E84: =E52 -> 77196.02 | F84: =F52 -> 85830.96 | G84: =G52 -> 91753.97 | H84: =H52 -> 88002.7 | I84: =I52 -> 93637.2
B86: =B80 -> Sales / Total Asset (E) | D86: =D83/D84 -> 0.6678002 | E86: =E83/E84 -> 0.78559154 | F86: =F83/F84 -> 0.82626397 | G86: =G83/G84 -> 0.74037058 | H86: =H83/H84 -> 0.85592078 | I86: =I83/I84 -> 0.84227636
B88: Altman's Z Score Table
B89: Particulars | C89: Weight | D89: ='Common Size Statements'!G$4 -> 44286 | E89: ='Common Size Statements'!H$4 -> 44651 | F89: ='Common Size Statements'!I$4 -> 45016 | G89: ='Common Size Statements'!J$4 -> 45382 | H89: ='Common Size Statements'!K$4 -> 45747 | I89: ='Common Size Statements'!L$4 -> 46112
B91: =B54 -> Working Capital / Total Asset (A) | C91: ='Master Input Center'!C39 -> 1.2 | D91: =D54*$C$91 -> 0.061447306 | E91: =E54*$C$91 -> 0.089429481 | F91: =F54*$C$91 -> 0.088233896 | G91: =G54*$C$91 -> 0.075815793 | H91: =H54*$C$91 -> 0.1164237 | I91: =I54*$C$91 -> 0.12461714
B92: =B62 -> Retained Earnings / Total Asset (B) | C92: ='Master Input Center'!C40 -> 1.4 | D92: =D62*$C$92 -> 1.1220471 | E92: =E62*$C$92 -> 1.1103233 | F92: =F62*$C$92 -> 1.107729 | G92: =G62*$C$92 -> 1.117793 | H92: =H62*$C$92 -> 1.0941721 | I92: =I62*$C$92 -> 1.0653468
B93: =B70 -> EBIT / Total Asset (C) | C93: ='Master Input Center'!C41 -> 3.3 | D93: =D70*$C$93 -> 0.68984277 | E93: =E70*$C$93 -> 0.80754736 | F93: =F70*$C$93 -> 0.91871657 | G93: =G70*$C$93 -> 0.85129051 | H93: =H70*$C$93 -> 0.90691942 | I93: =I70*$C$93 -> 0.90204589
B94: =B78 -> Market Cap. / Total Liabilities (D) | C94: ='Master Input Center'!C42 -> 0.6 | D94: =D78*$C$94 -> 11.277162 | E94: =E78*$C$94 -> 11.785865 | F94: =F78*$C$94 -> 16.075157 | G94: =G78*$C$94 -> 17.439521 | H94: =H78*$C$94 -> 17.118185 | I94: =I78*$C$94 -> 10.235932
B95: =B86 -> Sales / Total Asset (E) | C95: ='Master Input Center'!C43 -> 1 | D95: =D86*$C$95 -> 0.6678002 | E95: =E86*$C$95 -> 0.78559154 | F95: =F86*$C$95 -> 0.82626397 | G95: =G86*$C$95 -> 0.74037058 | H95: =H86*$C$95 -> 0.85592078 | I95: =I86*$C$95 -> 0.84227636
B97: Altman's Z Score | D97: =SUM(D91:D95) -> 13.818299 | E97: =SUM(E91:E95) -> 14.578757 | F97: =SUM(F91:F95) -> 19.016101 | G97: =SUM(G91:G95) -> 20.224791 | H97: =SUM(H91:H95) -> 20.091621 | I97: =SUM(I91:I95) -> 13.170219
B99: Financial Stability | D99: =IF(AND(D97<=2.99,D97>=1.81)," Distressed ",IF(D97>=3," Strong "," Grey Zone ")) -> Strong | E99: =IF(AND(E97<=2.99,E97>=1.81)," Distressed ",IF(E97>=3," Strong "," Grey Zone ")) -> Strong | F99: =IF(AND(F97<=2.99,F97>=1.81)," Distressed ",IF(F97>=3," Strong "," Grey Zone ")) -> Strong | G99: =IF(AND(G97<=2.99,G97>=1.81)," Distressed ",IF(G97>=3," Strong "," Grey Zone ")) -> Strong | H99: =IF(AND(H97<=2.99,H97>=1.81)," Distressed ",IF(H97>=3," Strong "," Grey Zone ")) -> Strong | I99: =IF(AND(I97<=2.99,I97>=1.81)," Distressed ",IF(I97>=3," Strong "," Grey Zone ")) -> Strong

Sheet DuPont Analysis
B2: ='Data Sheet'!B1 -> ITC LTD
B3: DuPont Analysis Charts
B33: Return on Equity (ROE)
B34: Particulars | D34: ='Common Size Statements'!F4 -> 43921 | E34: ='Common Size Statements'!G4 -> 44286 | F34: ='Common Size Statements'!H4 -> 44651 | G34: ='Common Size Statements'!I4 -> 45016 | H34: ='Common Size Statements'!J4 -> 45382 | I34: ='Common Size Statements'!K4 -> 45747 | J34: ='Common Size Statements'!L4 -> 46112
B36: Net Profit | D36: ='Historicals FS'!F36 -> 13175.46 | E36: ='Historicals FS'!G36 -> 10805.93 | F36: ='Historicals FS'!H36 -> 13593.41 | G36: ='Historicals FS'!I36 -> 17379.08 | H36: ='Historicals FS'!J36 -> 17420.91 | I36: ='Historicals FS'!K36 -> 17249.73 | J36: ='Historicals FS'!L36 -> 18495.06
B37: Average Shareholders Equity | D37: =(SUM('Historicals FS'!F56:F57)+SUM('Historicals FS'!E56:E57))/2 -> 62207.065 | E37: =(SUM('Historicals FS'!G56:G57)+SUM('Historicals FS'!F56:F57))/2 -> 62810.3 | F37: =(SUM('Historicals FS'!H56:H57)+SUM('Historicals FS'!G56:G57))/2 -> 61401.455 | G37: =(SUM('Historicals FS'!I56:I57)+SUM('Historicals FS'!H56:H57))/2 -> 65805.415 | H37: =(SUM('Historicals FS'!J56:J57)+SUM('Historicals FS'!I56:I57))/2 -> 71831.13 | I37: =(SUM('Historicals FS'!K56:K57)+SUM('Historicals FS'!J56:J57))/2 -> 72268.525 | J37: =(SUM('Historicals FS'!L56:L57)+SUM('Historicals FS'!K56:K57))/2 -> 71268.675
B39: Return on Equity | D39: =D36/D37 -> 0.21180006 | E39: =E36/E37 -> 0.17204073 | F39: =F36/F37 -> 0.2213858 | G39: =G36/G37 -> 0.26409802 | H39: =H36/H37 -> 0.24252591 | I39: =I36/I37 -> 0.23868939 | J39: =J36/J37 -> 0.25951177
B41: ROE DuPont Analysis
B42: Particulars | D42: ='Common Size Statements'!F4 -> 43921 | E42: ='Common Size Statements'!G4 -> 44286 | F42: ='Common Size Statements'!H4 -> 44651 | G42: ='Common Size Statements'!I4 -> 45016 | H42: ='Common Size Statements'!J4 -> 45382 | I42: ='Common Size Statements'!K4 -> 45747 | J42: ='Common Size Statements'!L4 -> 46112
B44: Net Profit | D44: =D36 -> 13175.46 | E44: =E36 -> 10805.93 | F44: =F36 -> 13593.41 | G44: =G36 -> 17379.08 | H44: =H36 -> 17420.91 | I44: =I36 -> 17249.73 | J44: =J36 -> 18495.06
B45: Revenue | D45: ='Historicals FS'!F5 -> 49387.7 | E45: ='Historicals FS'!G5 -> 49257.45 | F45: ='Historicals FS'!H5 -> 60644.54 | G45: ='Historicals FS'!I5 -> 70919.03 | H45: ='Historicals FS'!J5 -> 67931.94 | I45: ='Historicals FS'!K5 -> 75323.34 | J45: ='Historicals FS'!L5 -> 78868.4
B47: Net Profit Margins (A) | D47: =D44/D45 -> 0.26677614 | E47: =E44/E45 -> 0.21937656 | F47: =F44/F45 -> 0.22414895 | G47: =G44/G45 -> 0.24505524 | H47: =H44/H45 -> 0.25644653 | I47: =I44/I45 -> 0.2290091 | J47: =J44/J45 -> 0.23450533
B49: Revenue | D49: =D45 -> 49387.7 | E49: =E45 -> 49257.45 | F49: =F45 -> 60644.54 | G49: =G45 -> 70919.03 | H49: =H45 -> 67931.94 | I49: =I45 -> 75323.34 | J49: =J45 -> 78868.4
B50: Average Total Asset | D50: =SUM('Historicals FS'!E71:F71) -> 149049.79 | E50: =SUM('Historicals FS'!F71:G71) -> 151071.51 | F50: =SUM('Historicals FS'!G71:H71) -> 150956.78 | G50: =SUM('Historicals FS'!H71:I71) -> 163026.98 | H50: =SUM('Historicals FS'!I71:J71) -> 177584.93 | I50: =SUM('Historicals FS'!J71:K71) -> 179756.67 | J50: =SUM('Historicals FS'!K71:L71) -> 181639.9
B52: Asset Turnover Ratio (B) | D52: =D49/D50 -> 0.33135035 | E52: =E49/E50 -> 0.32605387 | F52: =F49/F50 -> 0.40173446 | G52: =G49/G50 -> 0.43501407 | H52: =H49/H50 -> 0.38253212 | I52: =I49/I50 -> 0.41902946 | J52: =J49/J50 -> 0.43420196
B54: Average Total Asset | D54: =D50 -> 149049.79 | E54: =E50 -> 151071.51 | F54: =F50 -> 150956.78 | G54: =G50 -> 163026.98 | H54: =H50 -> 177584.93 | I54: =I50 -> 179756.67 | J54: =J50 -> 181639.9
B55: Average Shareholders Equity | D55: =D37 -> 62207.065 | E55: =E37 -> 62810.3 | F55: =F37 -> 61401.455 | G55: =G37 -> 65805.415 | H55: =H37 -> 71831.13 | I55: =I37 -> 72268.525 | J55: =J37 -> 71268.675
B57: Equity Multiplier (C) | D57: =D54/D55 -> 2.3960267 | E57: =E54/E55 -> 2.4052028 | F57: =F54/F55 -> 2.4585212 | G57: =G54/G55 -> 2.4774098 | H57: =H54/H55 -> 2.4722558 | I57: =I54/I55 -> 2.4873438 | J57: =J54/J55 -> 2.5486639
B59: ROE (A*B*C) | D59: =D47*D52*D57 -> 0.21180006 | E59: =E47*E52*E57 -> 0.17204073 | F59: =F47*F52*F57 -> 0.2213858 | G59: =G47*G52*G57 -> 0.26409802 | H59: =H47*H52*H57 -> 0.24252591 | I59: =I47*I52*I57 -> 0.23868939 | J59: =J47*J52*J57 -> 0.25951177
D60: =D39=D59 -> TRUE | E60: =E39=E59 -> TRUE | F60: =F39=F59 -> TRUE | G60: =G39=G59 -> TRUE | H60: =H39=H59 -> TRUE | I60: =I39=I59 -> TRUE | J60: =J39=J59 -> TRUE
B62: Return on Assets (ROA)
B63: Particulars | D63: ='Common Size Statements'!F4 -> 43921 | E63: ='Common Size Statements'!G4 -> 44286 | F63: ='Common Size Statements'!H4 -> 44651 | G63: ='Common Size Statements'!I4 -> 45016 | H63: ='Common Size Statements'!J4 -> 45382 | I63: ='Common Size Statements'!K4 -> 45747 | J63: ='Common Size Statements'!L4 -> 46112
B65: Net Profit | D65: =D44 -> 13175.46 | E65: =E44 -> 10805.93 | F65: =F44 -> 13593.41 | G65: =G44 -> 17379.08 | H65: =H44 -> 17420.91 | I65: =I44 -> 17249.73 | J65: =J44 -> 18495.06
B66: Average Total Asset | D66: =D50 -> 149049.79 | E66: =E50 -> 151071.51 | F66: =F50 -> 150956.78 | G66: =G50 -> 163026.98 | H66: =H50 -> 177584.93 | I66: =I50 -> 179756.67 | J66: =J50 -> 181639.9
B68: Return on Asset(ROA) | D68: =D65/D66 -> 0.088396367 | E68: =E65/E66 -> 0.071528576 | F68: =F65/F66 -> 0.090048357 | G68: =G65/G66 -> 0.10660248 | H68: =H65/H66 -> 0.098099034 | I68: =I65/I66 -> 0.095961557 | J68: =J65/J66 -> 0.10182267
B70: ROA - DuPont Analysis
B71: Particulars | D71: ='Common Size Statements'!F24 -> 43921 | E71: ='Common Size Statements'!G24 -> 44286 | F71: ='Common Size Statements'!H24 -> 44651 | G71: ='Common Size Statements'!I24 -> 45016 | H71: ='Common Size Statements'!J24 -> 45382 | I71: ='Common Size Statements'!K24 -> 45747 | J71: ='Common Size Statements'!L24 -> 46112
B73: Net Profit | D73: =D44 -> 13175.46 | E73: =E44 -> 10805.93 | F73: =F44 -> 13593.41 | G73: =G44 -> 17379.08 | H73: =H44 -> 17420.91 | I73: =I44 -> 17249.73 | J73: =J44 -> 18495.06
B74: Revenue | D74: =D45 -> 49387.7 | E74: =E45 -> 49257.45 | F74: =F45 -> 60644.54 | G74: =G45 -> 70919.03 | H74: =H45 -> 67931.94 | I74: =I45 -> 75323.34 | J74: =J45 -> 78868.4
B76: Net Profit Margins (A) | D76: =D73/D74 -> 0.26677614 | E76: =E73/E74 -> 0.21937656 | F76: =F73/F74 -> 0.22414895 | G76: =G73/G74 -> 0.24505524 | H76: =H73/H74 -> 0.25644653 | I76: =I73/I74 -> 0.2290091 | J76: =J73/J74 -> 0.23450533
B78: Revenue | D78: =D49 -> 49387.7 | E78: =E49 -> 49257.45 | F78: =F49 -> 60644.54 | G78: =G49 -> 70919.03 | H78: =H49 -> 67931.94 | I78: =I49 -> 75323.34 | J78: =J49 -> 78868.4
B79: Average Total Asset | D79: =D50 -> 149049.79 | E79: =E50 -> 151071.51 | F79: =F50 -> 150956.78 | G79: =G50 -> 163026.98 | H79: =H50 -> 177584.93 | I79: =I50 -> 179756.67 | J79: =J50 -> 181639.9
B81: Asset Turnover Ratio (B) | D81: =D78/D79 -> 0.33135035 | E81: =E78/E79 -> 0.32605387 | F81: =F78/F79 -> 0.40173446 | G81: =G78/G79 -> 0.43501407 | H81: =H78/H79 -> 0.38253212 | I81: =I78/I79 -> 0.41902946 | J81: =J78/J79 -> 0.43420196
B83: Return on Asset (A*B) | D83: =D81*D76 -> 0.088396367 | E83: =E81*E76 -> 0.071528576 | F83: =F81*F76 -> 0.090048357 | G83: =G81*G76 -> 0.10660248 | H83: =H81*H76 -> 0.098099034 | I83: =I81*I76 -> 0.095961557 | J83: =J81*J76 -> 0.10182267
D84: =D68=D83 -> TRUE | E84: =E68=E83 -> TRUE | F84: =F68=F83 -> TRUE | G84: =G68=G83 -> TRUE | H84: =H68=H83 -> TRUE | I84: =I68=I83 -> TRUE | J84: =J68=J83 -> TRUE

Sheet Ratio Analysis
B4: ="Ratio Analysis "&'Data Sheet'!B1 -> Ratio Analysis ITC LTD
B5: Particulars | C5: =IFERROR('Data Sheet'!B16,_xleta.NA) -> 42825 | D5: =IFERROR('Data Sheet'!C16,_xleta.NA) -> 43190 | E5: =IFERROR('Data Sheet'!D16,_xleta.NA) -> 43555 | F5: =IFERROR('Data Sheet'!E16,_xleta.NA) -> 43921 | G5: =IFERROR('Data Sheet'!F16,_xleta.NA) -> 44286 | H5: =IFERROR('Data Sheet'!G16,_xleta.NA) -> 44651 | I5: =IFERROR('Data Sheet'!H16,_xleta.NA) -> 45016 | J5: =IFERROR('Data Sheet'!I16,_xleta.NA) -> 45382 | ... L5: =IFERROR('Data Sheet'!K16,_xleta.NA) -> 46112 | M5: Trend Line | N5: Mean | O5: Median
B7: Revenue (Y-o-Y) Growth | C7: 0 | D7: ='Historicals FS'!D6 -> 0.015931219 | E7: ='Historicals FS'!E6 -> 0.11256063 | F7: ='Historicals FS'!F6 -> 0.021682439 | G7: ='Historicals FS'!G6 -> -0.0026372963 | H7: ='Historicals FS'!H6 -> 0.23117498 | I7: ='Historicals FS'!I6 -> 0.16942152 | J7: ='Historicals FS'!J6 -> -0.042119724 | K7: ='Historicals FS'!K6 -> 0.10880596 | L7: ='Historicals FS'!L6 -> 0.047064562 | N7: =AVERAGE(D7:L7) -> 0.073542698 | O7: =MEDIAN(D7:L7) -> 0.047064562
B8: Gross Profit (Y-o-Y) Growth | C8: 0 | D8: =IFERROR(('Historicals FS'!D11/'Historicals FS'!C11)-1,0) -> 0.031844784 | E8: =IFERROR(('Historicals FS'!E11/'Historicals FS'!D11)-1,0) -> 0.12299874 | F8: =IFERROR(('Historicals FS'!F11/'Historicals FS'!E11)-1,0) -> 0.038703545 | G8: =IFERROR(('Historicals FS'!G11/'Historicals FS'!F11)-1,0) -> -0.10700914 | H8: =IFERROR(('Historicals FS'!H11/'Historicals FS'!G11)-1,0) -> 0.18839611 | I8: =IFERROR(('Historicals FS'!I11/'Historicals FS'!H11)-1,0) -> 0.22659213 | J8: =IFERROR(('Historicals FS'!J11/'Historicals FS'!I11)-1,0) -> -0.01075976 | K8: =IFERROR(('Historicals FS'!K11/'Historicals FS'!J11)-1,0) -> 0.049221548 | L8: =IFERROR(('Historicals FS'!L11/'Historicals FS'!K11)-1,0) -> 0.063646592 | N8: =AVERAGE(D8:L8) -> 0.067070505 | O8: =MEDIAN(D8:L8) -> 0.049221548
B9: EBITDA (Y-o-Y) Growth | C9: 0 | D9: =IFERROR(('Historicals FS'!D17/'Historicals FS'!C17)-1,0) -> 0.067945268 | E9: =IFERROR(('Historicals FS'!E17/'Historicals FS'!D17)-1,0) -> 0.12207796 | F9: =IFERROR(('Historicals FS'!F17/'Historicals FS'!E17)-1,0) -> 0.043487783 | G9: =IFERROR(('Historicals FS'!G17/'Historicals FS'!F17)-1,0) -> -0.1178047 | H9: =IFERROR(('Historicals FS'!H17/'Historicals FS'!G17)-1,0) -> 0.20852129 | I9: =IFERROR(('Historicals FS'!I17/'Historicals FS'!H17)-1,0) -> 0.24637895 | J9: =IFERROR(('Historicals FS'!J17/'Historicals FS'!I17)-1,0) -> -0.020102893 | K9: =IFERROR(('Historicals FS'!K17/'Historicals FS'!J17)-1,0) -> 0.025570193 | L9: =IFERROR(('Historicals FS'!L17/'Historicals FS'!K17)-1,0) -> 0.057078197 | N9: =AVERAGE(D9:L9) -> 0.070350228 | O9: =MEDIAN(D9:L9) -> 0.057078197
B10: EBIT (Y-o-Y) Growth | C10: 0 | D10: =IFERROR(('Historicals FS'!D23/'Historicals FS'!C23)-1,0) -> 0.067584614 | E10: =IFERROR(('Historicals FS'!E23/'Historicals FS'!D23)-1,0) -> 0.12146247 | F10: =IFERROR(('Historicals FS'!F23/'Historicals FS'!E23)-1,0) -> 0.032545193 | G10: =IFERROR(('Historicals FS'!G23/'Historicals FS'!F23)-1,0) -> -0.12879189 | H10: =IFERROR(('Historicals FS'!H23/'Historicals FS'!G23)-1,0) -> 0.22514477 | I10: =IFERROR(('Historicals FS'!I23/'Historicals FS'!H23)-1,0) -> 0.26491869 | J10: =IFERROR(('Historicals FS'!J23/'Historicals FS'!I23)-1,0) -> -0.0094483213 | K10: =IFERROR(('Historicals FS'!K23/'Historicals FS'!J23)-1,0) -> 0.021790931 | L10: =IFERROR(('Historicals FS'!L23/'Historicals FS'!K23)-1,0) -> 0.058308656 | N10: =AVERAGE(D10:L10) -> 0.07261279 | O10: =MEDIAN(D10:L10) -> 0.058308656
B11: EBT (Y-o-Y) Growth | C11: 0 | D11: =IFERROR(('Historicals FS'!D29/'Historicals FS'!C29)-1,0) -> 0.06319243 | E11: =IFERROR(('Historicals FS'!E29/'Historicals FS'!D29)-1,0) -> 0.12525825 | F11: =IFERROR(('Historicals FS'!F29/'Historicals FS'!E29)-1,0) -> 0.032096655 | G11: =IFERROR(('Historicals FS'!G29/'Historicals FS'!F29)-1,0) -> -0.12805801 | H11: =IFERROR(('Historicals FS'!H29/'Historicals FS'!G29)-1,0) -> 0.22586292 | I11: =IFERROR(('Historicals FS'!I29/'Historicals FS'!H29)-1,0) -> 0.26481845 | J11: =IFERROR(('Historicals FS'!J29/'Historicals FS'!I29)-1,0) -> -0.0078559948 | K11: =IFERROR(('Historicals FS'!K29/'Historicals FS'!J29)-1,0) -> 0.021575202 | L11: =IFERROR(('Historicals FS'!L29/'Historicals FS'!K29)-1,0) -> 0.056755951 | N11: =AVERAGE(D11:L11) -> 0.072627317 | O11: =MEDIAN(D11:L11) -> 0.056755951
B12: Net Profit (Y-o-Y) Growth | C12: 0 | D12: =IFERROR(('Historicals FS'!D36/'Historicals FS'!C36)-1,0) -> 0.061279334 | E12: =IFERROR(('Historicals FS'!E36/'Historicals FS'!D36)-1,0) -> 0.16239178 | F12: =IFERROR(('Historicals FS'!F36/'Historicals FS'!E36)-1,0) -> 0.225002 | G12: =IFERROR(('Historicals FS'!G36/'Historicals FS'!F36)-1,0) -> -0.1798442 | H12: =IFERROR(('Historicals FS'!H36/'Historicals FS'!G36)-1,0) -> 0.25795836 | I12: =IFERROR(('Historicals FS'!I36/'Historicals FS'!H36)-1,0) -> 0.27849303 | J12: =IFERROR(('Historicals FS'!J36/'Historicals FS'!I36)-1,0) -> 0.0024069168 | K12: =IFERROR(('Historicals FS'!K36/'Historicals FS'!J36)-1,0) -> -0.0098261227 | L12: =IFERROR(('Historicals FS'!L36/'Historicals FS'!K36)-1,0) -> 0.072194173 | N12: =AVERAGE(D12:L12) -> 0.096672809 | O12: =MEDIAN(D12:L12) -> 0.072194173
B13: Earnings Per Share (Y-o-Y) Growth | C13: 0 | D13: =IFERROR('Historicals FS'!D44,0) -> 0.056331341 | E13: =IFERROR('Historicals FS'!E44,0) -> 0.15724291 | F13: =IFERROR('Historicals FS'!F44,0) -> 0.22165353 | G13: =IFERROR('Historicals FS'!G44,0) -> -0.18095028 | H13: =IFERROR('Historicals FS'!H44,0) -> 0.25647821 | I13: =IFERROR('Historicals FS'!I44,0) -> 0.26772234 | J13: =IFERROR('Historicals FS'!J44,0) -> -0.0021455732 | K13: =IFERROR('Historicals FS'!K44,0) -> -0.012152388 | L13: =IFERROR('Historicals FS'!L44,0) -> 0.07087634 | N13: =AVERAGE(D13:L13) -> 0.092784047 | O13: =MEDIAN(D13:L13) -> 0.07087634
B14: Dividend Per Share (Y-o-Y) Growth | C14: 0 | D14: =IFERROR(('Historicals FS'!D46/'Historicals FS'!C46)-1,0) -> 0.084208811 | E14: =IFERROR(('Historicals FS'!E46/'Historicals FS'!D46)-1,0) -> 0.11650645 | F14: =IFERROR(('Historicals FS'!F46/'Historicals FS'!E46)-1,0) -> 0.76521571 | G14: =IFERROR(('Historicals FS'!G46/'Historicals FS'!F46)-1,0) -> 0.059113555 | H14: =IFERROR(('Historicals FS'!H46/'Historicals FS'!G46)-1,0) -> 0.069767819 | I14: =IFERROR(('Historicals FS'!I46/'Historicals FS'!H46)-1,0) -> 0.34782561 | J14: =IFERROR(('Historicals FS'!J46/'Historicals FS'!I46)-1,0) -> -0.11290335 | K14: =IFERROR(('Historicals FS'!K46/'Historicals FS'!J46)-1,0) -> 0.043636312 | L14: =IFERROR(('Historicals FS'!L46/'Historicals FS'!K46)-1,0) -> 0.010453437 | N14: =AVERAGE(D14:L14) -> 0.15375826 | O14: =MEDIAN(D14:L14) -> 0.069767819
B16: Gross Margins | C16: ='Historicals FS'!C12 -> 0.48678158 | D16: ='Historicals FS'!D12 -> 0.49440654 | E16: ='Historicals FS'!E12 -> 0.49904509 | F16: ='Historicals FS'!F12 -> 0.50735912 | G16: ='Historicals FS'!G12 -> 0.45426509 | H16: ='Historicals FS'!H12 -> 0.43848102 | I16: ='Historicals FS'!I12 -> 0.45991746 | J16: ='Historicals FS'!J12 -> 0.47497466 | ... L16: ='Historicals FS'!L12 -> 0.45656854 | N16: =AVERAGE(C16:L16) -> 0.47212498 | O16: =MEDIAN(C16:L16) -> 0.46744606
B17: EBITDA Margins | C17: ='Historicals FS'!C18 -> 0.36171097 | D17: ='Historicals FS'!D18 -> 0.38022999 | E17: ='Historicals FS'!E18 -> 0.38348265 | F17: ='Historicals FS'!F18 -> 0.39166716 | G17: ='Historicals FS'!G18 -> 0.34644059 | H17: ='Historicals FS'!H18 -> 0.34006606 | I17: ='Historicals FS'!I18 -> 0.36244517 | J17: ='Historicals FS'!J18 -> 0.37077596 | ... L17: ='Historicals FS'!L18 -> 0.34622231 | N17: =AVERAGE(C17:L17) -> 0.36259834 | O17: =MEDIAN(C17:L17) -> 0.36207807
B18: EBIT Margins | C18: ='Historicals FS'!C24 -> 0.33475622 | D18: ='Historicals FS'!D24 -> 0.35177636 | E18: ='Historicals FS'!E24 -> 0.354591 | F18: ='Historicals FS'!F24 -> 0.35836109 | G18: ='Historicals FS'!G24 -> 0.31303265 | H18: ='Historicals FS'!H24 -> 0.31149944 | I18: ='Historicals FS'!I24 -> 0.33693707 | J18: ='Historicals FS'!J24 -> 0.34842932 | ... L18: ='Historicals FS'!L24 -> 0.32453391 | N18: =AVERAGE(C18:L18) -> 0.33550029 | O18: =MEDIAN(C18:L18) -> 0.33584664
B19: EBT Margins | C19: ='Historicals FS'!C30 -> 0.33360979 | D19: ='Historicals FS'!D30 -> 0.34912935 | E19: ='Historicals FS'!E30 -> 0.35311395 | F19: ='Historicals FS'!F30 -> 0.35671331 | G19: ='Historicals FS'!G30 -> 0.31185577 | H19: ='Historicals FS'!H30 -> 0.31051023 | I19: ='Historicals FS'!I30 -> 0.33584046 | J19: ='Historicals FS'!J30 -> 0.3478536 | ... L19: ='Historicals FS'!L30 -> 0.32345401 | N19: =AVERAGE(C19:L19) -> 0.33425681 | O19: =MEDIAN(C19:L19) -> 0.33472513
B20: Net Margins | C20: ='Historicals FS'!C37 -> 0.20385993 | D20: ='Historicals FS'!D37 -> 0.21295963 | E20: ='Historicals FS'!E37 -> 0.222498 | F20: ='Historicals FS'!F37 -> 0.26677614 | G20: ='Historicals FS'!G37 -> 0.21937656 | H20: ='Historicals FS'!H37 -> 0.22414895 | I20: ='Historicals FS'!I37 -> 0.24505524 | J20: ='Historicals FS'!J37 -> 0.25644653 | ... L20: ='Historicals FS'!L37 -> 0.23450533 | N20: =AVERAGE(C20:L20) -> 0.23146354 | O20: =MEDIAN(C20:L20) -> 0.22657902
B22: COGS % of Sales | C22: ='Historicals FS'!C9 -> 0.51321842 | D22: ='Historicals FS'!D9 -> 0.50559346 | E22: ='Historicals FS'!E9 -> 0.50095491 | F22: ='Historicals FS'!F9 -> 0.49264088 | G22: ='Historicals FS'!G9 -> 0.54573491 | H22: ='Historicals FS'!H9 -> 0.56151898 | I22: ='Historicals FS'!I9 -> 0.54008254 | J22: ='Historicals FS'!J9 -> 0.52502534 | ... L22: ='Historicals FS'!L9 -> 0.54343146 | N22: =AVERAGE(C22:L22) -> 0.52787502 | O22: =MEDIAN(C22:L22) -> 0.53255394
B23: S&G Expenses % of Sales | C23: ='Historicals FS'!C15 -> 0.12507061 | D23: ='Historicals FS'!D15 -> 0.11417655 | E23: ='Historicals FS'!E15 -> 0.11556244 | F23: ='Historicals FS'!F15 -> 0.11569196 | G23: ='Historicals FS'!G15 -> 0.1078245 | H23: ='Historicals FS'!H15 -> 0.09841496 | I23: ='Historicals FS'!I15 -> 0.097472286 | J23: ='Historicals FS'!J15 -> 0.1041987 | ... L23: ='Historicals FS'!L15 -> 0.11034622 | N23: =AVERAGE(C23:L23) -> 0.10952664 | O23: =MEDIAN(C23:L23) -> 0.10908536
B24: Depreciaton % of Sales | C24: ='Historicals FS'!C21 -> 0.026954751 | D24: ='Historicals FS'!D21 -> 0.028453629 | E24: ='Historicals FS'!E21 -> 0.028891645 | F24: ='Historicals FS'!F21 -> 0.033306066 | G24: ='Historicals FS'!G21 -> 0.033407941 | H24: ='Historicals FS'!H21 -> 0.028566628 | I24: ='Historicals FS'!I21 -> 0.025508104 | J24: ='Historicals FS'!J21 -> 0.022346631 | ... L24: ='Historicals FS'!L21 -> 0.021688408 | N24: =AVERAGE(C24:L24) -> 0.027098051 | O24: =MEDIAN(C24:L24) -> 0.02770419
B25: Operating Income % of Sales | C25: =C18 -> 0.33475622 | D25: =D18 -> 0.35177636 | E25: =E18 -> 0.354591 | F25: =F18 -> 0.35836109 | G25: =G18 -> 0.31303265 | H25: =H18 -> 0.31149944 | I25: =I18 -> 0.33693707 | J25: =J18 -> 0.34842932 | ... L25: =L18 -> 0.32453391 | N25: =AVERAGE(C25:L25) -> 0.33550029 | O25: =MEDIAN(C25:L25) -> 0.33584664
B27: Return on Capital Employed (ROCE) | C27: =IFERROR('Historicals FS'!C23/SUM('Data Sheet'!B57:B59),0) -> 0.30816048 | D27: =IFERROR('Historicals FS'!D23/SUM('Data Sheet'!C57:C59),0) -> 0.29087469 | E27: =IFERROR('Historicals FS'!E23/SUM('Data Sheet'!D57:D59),0) -> 0.28976384 | F27: =IFERROR('Historicals FS'!F23/SUM('Data Sheet'!E57:E59),0) -> 0.26999906 | G27: =IFERROR('Historicals FS'!G23/SUM('Data Sheet'!F57:F59),0) -> 0.25436581 | H27: =IFERROR('Historicals FS'!H23/SUM('Data Sheet'!G57:G59),0) -> 0.30126365 | I27: =IFERROR('Historicals FS'!I23/SUM('Data Sheet'!H57:H59),0) -> 0.3440081 | J27: =IFERROR('Historicals FS'!J23/SUM('Data Sheet'!I57:I59),0) -> 0.31639278 | ... L27: =IFERROR('Historicals FS'!L23/SUM('Data Sheet'!K57:K59),0) -> 0.34169956 | N27: =AVERAGE(C27:L27) -> 0.30604859 | O27: =MEDIAN(C27:L27) -> 0.30471206
B28: Retained Earnings | C28: ='Historicals FS'!C49 -> 0.33819421 | D28: ='Historicals FS'!D49 -> 0.3207286 | E28: ='Historicals FS'!E49 -> 0.34463984 | F28: ='Historicals FS'!F49 -> 0.053044068 | G28: ='Historicals FS'!G49 -> 0 | H28: ='Historicals FS'!H49 -> 0 | I28: ='Historicals FS'!I49 -> 0 | J28: ='Historicals FS'!J49 -> 0.014606011 | ... L28: ='Historicals FS'!L49 -> 0.017695536 | N28: =AVERAGE(C28:L28) -> 0.10889083 | O28: =MEDIAN(C28:L28) -> 0.016150773
B29: Return on Equity (ROE) | C29: =IFERROR('Historicals FS'!C36/SUM('Data Sheet'!B57:B58),0) -> 0.18784852 | D29: =IFERROR('Historicals FS'!D36/SUM('Data Sheet'!C57:C58),0) -> 0.17621121 | E29: =IFERROR('Historicals FS'!E36/SUM('Data Sheet'!D57:D58),0) -> 0.18186171 | F29: =IFERROR('Historicals FS'!F36/SUM('Data Sheet'!E57:E58),0) -> 0.2018508 | G29: =IFERROR('Historicals FS'!G36/SUM('Data Sheet'!F57:F58),0) -> 0.17906224 | H29: =IFERROR('Historicals FS'!H36/SUM('Data Sheet'!G57:G58),0) -> 0.21764928 | I29: =IFERROR('Historicals FS'!I36/SUM('Data Sheet'!H57:H58),0) -> 0.25130525 | J29: =IFERROR('Historicals FS'!J36/SUM('Data Sheet'!I57:I58),0) -> 0.23381575 | ... L29: =IFERROR('Historicals FS'!L36/SUM('Data Sheet'!K57:K58),0) -> 0.25507859 | N29: =AVERAGE(C29:L29) -> 0.21310023 | O29: =MEDIAN(C29:L29) -> 0.20975004
B30: Self Sustained Growth Rate | C30: =C28*C29 -> 0.063529279 | D30: =D28*D29 -> 0.056515974 | E30: =E28*E29 -> 0.062676792 | F30: =F28*F29 -> 0.010706988 | G30: =G28*G29 -> 0 | H30: =H28*H29 -> 0 | I30: =I28*I29 -> 0 | J30: =J28*J29 -> 0.0034151154 | ... L30: =L28*L29 -> 0.0045137524 | N30: =AVERAGE(C30:L30) -> 0.02013579 | O30: =MEDIAN(C30:L30) -> 0.0039644339
B31: Interest Coverage Ratio | C31: ='Historicals FS'!C23/'Historicals FS'!C26 -> 291.99918 | D31: ='Historicals FS'!D23/'Historicals FS'!D26 -> 132.89549 | E31: ='Historicals FS'!E23/'Historicals FS'!E26 -> 240.06695 | F31: ='Historicals FS'!F23/'Historicals FS'!F26 -> 217.48132 | G31: ='Historicals FS'!G23/'Historicals FS'!G26 -> 265.98568 | H31: ='Historicals FS'!H23/'Historicals FS'!H26 -> 314.89815 | I31: ='Historicals FS'!I23/'Historicals FS'!I26 -> 307.25537 | J31: ='Historicals FS'!J23/'Historicals FS'!J26 -> 605.20276 | ... L31: ='Historicals FS'!L23/'Historicals FS'!L26 -> 300.52213 | N31: =AVERAGE(C31:L31) -> 321.30416 | O31: =MEDIAN(C31:L31) -> 296.26066
B33: Debtor Turnover Ratio | C33: =IFERROR('Historicals FS'!C5/((SUM('Raw Fs'!E41:E43)+SUM('Raw Fs'!D41:D43))/2),0) -> 19.479663 | D33: =IFERROR('Historicals FS'!D5/((SUM('Raw Fs'!F41:F43)+SUM('Raw Fs'!E41:E43))/2),0) -> 16.853739 | E33: =IFERROR('Historicals FS'!E5/((SUM('Raw Fs'!G41:G43)+SUM('Raw Fs'!F41:F43))/2),0) -> 14.393205 | F33: =IFERROR('Historicals FS'!F5/((SUM('Raw Fs'!H41:H43)+SUM('Raw Fs'!G41:G43))/2),0) -> 14.972776 | G33: =IFERROR('Historicals FS'!G5/((SUM('Raw Fs'!I41:I43)+SUM('Raw Fs'!H41:H43))/2),0) -> 19.457812 | H33: =IFERROR('Historicals FS'!H5/((SUM('Raw Fs'!J41:J43)+SUM('Raw Fs'!I41:I43))/2),0) -> 24.438662 | I33: =IFERROR('Historicals FS'!I5/((SUM('Raw Fs'!K41:K43)+SUM('Raw Fs'!J41:J43))/2),0) -> 26.179044 | J33: =IFERROR('Historicals FS'!J5/((SUM('Raw Fs'!L41:L43)+SUM('Raw Fs'!K41:K43))/2),0) -> 19.459164 | ... L33: =IFERROR('Historicals FS'!L5/((SUM('Raw Fs'!N41:N43)+SUM('Raw Fs'!M41:M43))/2),0) -> 18.250237 | N33: =AVERAGE(C33:L33) -> 19.070894 | O33: =MEDIAN(C33:L33) -> 18.854024
B34: Creditor Turnover Ratio | C34: =IFERROR(('Data Sheet'!B18/(SUM('Raw Fs'!D14:E14)/2)),0) -> 6.18511 | D34: =IFERROR(('Data Sheet'!C18/(SUM('Raw Fs'!E14:F14)/2)),0) -> 4.8181056 | E34: =IFERROR(('Data Sheet'!D18/(SUM('Raw Fs'!F14:G14)/2)),0) -> 5.0309792 | F34: =IFERROR(('Data Sheet'!E18/(SUM('Raw Fs'!G14:H14)/2)),0) -> 5.0556303 | G34: =IFERROR(('Data Sheet'!F18/(SUM('Raw Fs'!H14:I14)/2)),0) -> 5.2275028 | H34: =IFERROR(('Data Sheet'!G18/(SUM('Raw Fs'!I14:J14)/2)),0) -> 6.1975893 | I34: =IFERROR(('Data Sheet'!H18/(SUM('Raw Fs'!J14:K14)/2)),0) -> 6.4707713 | J34: =IFERROR(('Data Sheet'!I18/(SUM('Raw Fs'!K14:L14)/2)),0) -> 5.7837729 | ... L34: =IFERROR(('Data Sheet'!K18/(SUM('Raw Fs'!M14:N14)/2)),0) -> 6.7193146 | N34: =AVERAGE(C34:L34) -> 5.829864 | O34: =MEDIAN(C34:L34) -> 5.9844415
B35: Inventory Turnover Ratio | C35: =IFERROR(('Historicals FS'!C8/(SUM('Raw Fs'!D38:E38)/2)),0) -> 2.5554919 | D35: =IFERROR(('Historicals FS'!D8/(SUM('Raw Fs'!E38:F38)/2)),0) -> 2.8143617 | E35: =IFERROR(('Historicals FS'!E8/(SUM('Raw Fs'!F38:G38)/2)),0) -> 3.1541452 | F35: =IFERROR(('Historicals FS'!F8/(SUM('Raw Fs'!G38:H38)/2)),0) -> 2.9070315 | G35: =IFERROR(('Historicals FS'!G8/(SUM('Raw Fs'!H38:I38)/2)),0) -> 2.789117 | H35: =IFERROR(('Historicals FS'!H8/(SUM('Raw Fs'!I38:J38)/2)),0) -> 3.2033357 | I35: =IFERROR(('Historicals FS'!I8/(SUM('Raw Fs'!J38:K38)/2)),0) -> 3.3843278 | J35: =IFERROR(('Historicals FS'!J8/(SUM('Raw Fs'!K38:L38)/2)),0) -> 2.7515808 | ... L35: =IFERROR(('Historicals FS'!L8/(SUM('Raw Fs'!M38:N38)/2)),0) -> 2.5019451 | N35: =AVERAGE(C35:L35) -> 2.8845346 | O35: =MEDIAN(C35:L35) -> 2.8017394
B36: Fixed Asset Turnover Ratio | C36: =IFERROR(('Historicals FS'!C5/(SUM('Raw Fs'!D32:E32)/2)),0) -> 2.7592 | D36: =IFERROR(('Historicals FS'!D5/(SUM('Raw Fs'!E32:F32)/2)),0) -> 2.6806268 | E36: =IFERROR(('Historicals FS'!E5/(SUM('Raw Fs'!F32:G32)/2)),0) -> 2.6931629 | F36: =IFERROR(('Historicals FS'!F5/(SUM('Raw Fs'!G32:H32)/2)),0) -> 2.4040548 | G36: =IFERROR(('Historicals FS'!G5/(SUM('Raw Fs'!H32:I32)/2)),0) -> 2.188685 | H36: =IFERROR(('Historicals FS'!H5/(SUM('Raw Fs'!I32:J32)/2)),0) -> 2.5518963 | I36: =IFERROR(('Historicals FS'!I5/(SUM('Raw Fs'!J32:K32)/2)),0) -> 2.8321165 | J36: =IFERROR(('Historicals FS'!J5/(SUM('Raw Fs'!K32:L32)/2)),0) -> 2.5313735 | ... L36: =IFERROR(('Historicals FS'!L5/(SUM('Raw Fs'!M32:N32)/2)),0) -> 3.5528707 | N36: =AVERAGE(C36:L36) -> 2.7220479 | O36: =MEDIAN(C36:L36) -> 2.6868948
B37: Capital Turnover Ratio | C37: =IFERROR('Historicals FS'!C5/((SUM('Raw Fs'!E5:E6,'Raw Fs'!E8)+SUM('Raw Fs'!D5:D6,'Raw Fs'!D8))/2),0) -> 0.95958177 | D37: =IFERROR('Historicals FS'!D5/((SUM('Raw Fs'!F5:F6,'Raw Fs'!F8)+SUM('Raw Fs'!E5:E6,'Raw Fs'!E8))/2),0) -> 0.87817327 | E37: =IFERROR('Historicals FS'!E5/((SUM('Raw Fs'!G5:G6,'Raw Fs'!G8)+SUM('Raw Fs'!F5:F6,'Raw Fs'!F8))/2),0) -> 0.86574993 | F37: =IFERROR('Historicals FS'!F5/((SUM('Raw Fs'!H5:H6,'Raw Fs'!H8)+SUM('Raw Fs'!G5:G6,'Raw Fs'!G8))/2),0) -> 0.79383579 | G37: =IFERROR('Historicals FS'!G5/((SUM('Raw Fs'!I5:I6,'Raw Fs'!I8)+SUM('Raw Fs'!H5:H6,'Raw Fs'!H8))/2),0) -> 0.78415451 | H37: =IFERROR('Historicals FS'!H5/((SUM('Raw Fs'!J5:J6,'Raw Fs'!J8)+SUM('Raw Fs'!I5:I6,'Raw Fs'!I8))/2),0) -> 0.98759154 | I37: =IFERROR('Historicals FS'!I5/((SUM('Raw Fs'!K5:K6,'Raw Fs'!K8)+SUM('Raw Fs'!J5:J6,'Raw Fs'!J8))/2),0) -> 1.0776494 | J37: =IFERROR('Historicals FS'!J5/((SUM('Raw Fs'!L5:L6,'Raw Fs'!L8)+SUM('Raw Fs'!K5:K6,'Raw Fs'!K8))/2),0) -> 0.94568607 | ... L37: =IFERROR('Historicals FS'!L5/((SUM('Raw Fs'!N5:N6,'Raw Fs'!N8)+SUM('Raw Fs'!M5:M6,'Raw Fs'!M8))/2),0) -> 1.1061719 | N37: =AVERAGE(C37:L37) -> 0.94408505 | O37: =MEDIAN(C37:L37) -> 0.95263392
B38: 365
B39: Debtor Days | C39: =$B$38/C33 -> 18.737491 | D39: =$B$38/D33 -> 21.656915 | E39: =$B$38/E33 -> 25.359188 | F39: =$B$38/F33 -> 24.377578 | G39: =$B$38/G33 -> 18.758533 | H39: =$B$38/H33 -> 14.935351 | I39: =$B$38/I33 -> 13.94245 | J39: =$B$38/J33 -> 18.75723 | ... L39: =$B$38/L33 -> 19.99974 | N39: =AVERAGE(C39:L39) -> 19.771505 | O39: =MEDIAN(C39:L39) -> 19.379137
B40: Creditor Days | C40: =$B$38/C34 -> 59.012693 | D40: =$B$38/D34 -> 75.755915 | E40: =$B$38/E34 -> 72.550489 | F40: =$B$38/F34 -> 72.196735 | G40: =$B$38/G34 -> 69.823013 | H40: =$B$38/H34 -> 58.893867 | I40: =$B$38/I34 -> 56.407495 | J40: =$B$38/J34 -> 63.107596 | ... L40: =$B$38/L34 -> 54.321016 | N40: =AVERAGE(C40:L40) -> 63.566754 | O40: =MEDIAN(C40:L40) -> 61.060144
B41: Inventory Days | C41: =$B$38/C35 -> 142.82964 | D41: =$B$38/D35 -> 129.69193 | E41: =$B$38/E35 -> 115.72073 | F41: =$B$38/F35 -> 125.55764 | G41: =$B$38/G35 -> 130.86579 | H41: =$B$38/H35 -> 113.94372 | I41: =$B$38/I35 -> 107.85007 | J41: =$B$38/J35 -> 132.65102 | ... L41: =$B$38/L35 -> 145.8865 | N41: =AVERAGE(C41:L41) -> 127.61029 | O41: =MEDIAN(C41:L41) -> 130.27886
B42: Cash Conversion Cycle | C42: =SUM(C39,C41)-C40 -> 102.55444 | D42: =SUM(D39,D41)-D40 -> 75.592931 | E42: =SUM(E39,E41)-E40 -> 68.529432 | F42: =SUM(F39,F41)-F40 -> 77.738478 | G42: =SUM(G39,G41)-G40 -> 79.801308 | H42: =SUM(H39,H41)-H40 -> 69.985209 | I42: =SUM(I39,I41)-I40 -> 65.385027 | J42: =SUM(J39,J41)-J40 -> 88.300655 | K42: =SUM(K39,K41)-K40 -> 98.697738 | N42: =AVERAGE(C42:L42) -> 80.731691 | O42: =MEDIAN(C42:L42) -> 77.738478
B44: CFO/Sales | C44: ='Historicals FS'!C83/'Historicals FS'!C5 -> 0.2484825 | D44: ='Historicals FS'!D83/'Historicals FS'!D5 -> 0.3030914 | E44: ='Historicals FS'!E83/'Historicals FS'!E5 -> 0.26030429 | F44: ='Historicals FS'!F83/'Historicals FS'!F5 -> 0.29744248 | G44: ='Historicals FS'!G83/'Historicals FS'!G5 -> 0.25431686 | H44: ='Historicals FS'!H83/'Historicals FS'!H5 -> 0.26013884 | I44: ='Historicals FS'!I83/'Historicals FS'!I5 -> 0.26619089 | J44: ='Historicals FS'!J83/'Historicals FS'!J5 -> 0.25288546 | ... L44: ='Historicals FS'!L83/'Historicals FS'!L5 -> 0.23411151 | N44: =AVERAGE(C44:L44) -> 0.2610982 | O44: =MEDIAN(C44:L44) -> 0.25722785
B45: CFO/Total Assets | C45: ='Historicals FS'!C83/'Historicals FS'!C71 -> 0.19011305 | D45: ='Historicals FS'!D83/'Historicals FS'!D71 -> 0.20499408 | E45: ='Historicals FS'!E83/'Historicals FS'!E71 -> 0.17539962 | F45: ='Historicals FS'!F83/'Historicals FS'!F71 -> 0.19001239 | G45: ='Historicals FS'!G83/'Historicals FS'!G71 -> 0.16983285 | H45: ='Historicals FS'!H83/'Historicals FS'!H71 -> 0.20436287 | I45: ='Historicals FS'!I83/'Historicals FS'!I71 -> 0.21994395 | J45: ='Historicals FS'!J83/'Historicals FS'!J71 -> 0.18722896 | ... L45: ='Historicals FS'!L83/'Historicals FS'!L71 -> 0.19718659 | N45: =AVERAGE(C45:L45) -> 0.1939375 | O45: =MEDIAN(C45:L45) -> 0.19364982
B46: CFO/Total Debt | C46: ='Historicals FS'!C83/'Historicals FS'!C58 -> 232.43657 | D46: ='Historicals FS'!D83/'Historicals FS'!D58 -> 366.62027 | E46: ='Historicals FS'!E83/'Historicals FS'!E58 -> 936.23512 | F46: ='Historicals FS'!F83/'Historicals FS'!F58 -> 52.946477 | G46: ='Historicals FS'!G83/'Historicals FS'!G58 -> 46.254108 | H46: ='Historicals FS'!H83/'Historicals FS'!H58 -> 63.24567 | I46: ='Historicals FS'!I83/'Historicals FS'!I58 -> 61.684747 | J46: ='Historicals FS'!J83/'Historicals FS'!J58 -> 56.616023 | ... L46: ='Historicals FS'!L83/'Historicals FS'!L58 -> 7.6963477 | N46: =AVERAGE(C46:L46) -> 188.56844 | O46: =MEDIAN(C46:L46) -> 61.816929

Sheet VAR
B2: ="Calculation of VAR of "&'Data Sheet'!B1 -> Calculation of VAR of ITC LTD
B4: Historical Approach
B6: Mean | F6: =AVERAGE('Daily Adjusted closings'!$AD$4:$AD$7658) -> 0.00081209066
B7: Std.Deviation | F7: =_xlfn.STDEV.S('Daily Adjusted closings'!$AD$4:$AD$7658) -> 0.019857158
B8: Min | F8: =MIN('Daily Adjusted closings'!$AD$4:$AD$7658) -> -0.12816399
B9: Max | F9: =MAX('Daily Adjusted closings'!$AD$4:$AD$7658) -> 0.16461916
B10: Stock Price | F10: ='Data Sheet'!$B$8 -> 276.65
B12: Percentile | C12: Confidence | D12: VAR | E12: Stock Price | F12: VAR (INR)
B13: 0.05 | C13: =1-B13 -> 0.95 | D13: =-_xlfn.PERCENTILE.INC('Daily Adjusted closings'!$AD$4:$AD$7658,B13) -> 0.028114168 | E13: =$F$10*(1-D13) -> 268.87222 | F13: =$F$10-E13 -> 7.7777847
B14: 0.01 | C14: =1-B14 -> 0.99 | D14: =-_xlfn.PERCENTILE.INC('Daily Adjusted closings'!$AD$4:$AD$7658,B14) -> 0.054851577 | E14: =$F$10*(1-D14) -> 261.47531 | F14: =$F$10-E14 -> 15.174689
B15: 0.005 | C15: =1-B15 -> 0.995 | D15: =-_xlfn.PERCENTILE.INC('Daily Adjusted closings'!$AD$4:$AD$7658,B15) -> 0.069487428 | E15: =$F$10*(1-D15) -> 257.4263 | F15: =$F$10-E15 -> 19.223697
B16: 0.1 | C16: =1-B16 -> 0.9 | D16: =-_xlfn.PERCENTILE.INC('Daily Adjusted closings'!$AD$4:$AD$7658,B16) -> 0.019794146 | E16: =$F$10*(1-D16) -> 271.17395 | F16: =$F$10-E16 -> 5.4760504
B18: Monte Carlo Simulation
B20: Mean | F20: =AVERAGE('Daily Adjusted closings'!$AJ$4:$AJ$7658) -> 0.0011739949
B21: Std.Deviation | F21: =_xlfn.STDEV.S('Daily Adjusted closings'!$AJ$4:$AJ$7658) -> 0.019630032
B22: Min | F22: =MIN('Daily Adjusted closings'!$AJ$4:$AJ$7658) -> -0.081840992
B23: Max | F23: =MAX('Daily Adjusted closings'!$AD$4:$AD$7658) -> 0.16461916
B24: Stock Price | F24: ='Data Sheet'!$B$8 -> 276.65
B26: Percentile | C26: Confidence | D26: VAR | E26: Stock Price | F26: VAR (INR)
B27: 0.05 | C27: =1-B27 -> 0.95 | D27: =-_xlfn.PERCENTILE.INC('Daily Adjusted closings'!$AJ$4:$AJ$7658,B27) -> 0.030691285 | E27: =$F$10*(1-D27) -> 268.15926 | F27: =$F$10-E27 -> 8.4907439
B28: 0.01 | C28: =1-B28 -> 0.99 | D28: =-_xlfn.PERCENTILE.INC('Daily Adjusted closings'!$AJ$4:$AJ$7658,B28) -> 0.04358815 | E28: =$F$10*(1-D28) -> 264.59134 | F28: =$F$10-E28 -> 12.058662
B29: 0.005 | C29: =1-B29 -> 0.995 | D29: =-_xlfn.PERCENTILE.INC('Daily Adjusted closings'!$AJ$4:$AJ$7658,B29) -> 0.049593553 | E29: =$F$10*(1-D29) -> 262.92994 | F29: =$F$10-E29 -> 13.720056
B30: 0.1 | C30: =1-B30 -> 0.9 | D30: =-_xlfn.PERCENTILE.INC('Daily Adjusted closings'!$AJ$4:$AJ$7658,B30) -> 0.023338083 | E30: =$F$10*(1-D30) -> 270.19352 | F30: =$F$10-E30 -> 6.4564807

Sheet Common Size Statements
B2: ="Common Size Income Statement of "&'Data Sheet'!B1 -> Common Size Income Statement of ITC LTD
B4: Particulars | C4: ='Data Sheet'!B16 -> 42825 | D4: ='Data Sheet'!C16 -> 43190 | E4: ='Data Sheet'!D16 -> 43555 | F4: ='Data Sheet'!E16 -> 43921 | G4: ='Data Sheet'!F16 -> 44286 | H4: ='Data Sheet'!G16 -> 44651 | I4: ='Data Sheet'!H16 -> 45016 | J4: ='Data Sheet'!I16 -> 45382 | ... L4: ='Data Sheet'!K16 -> 46112
B6: ='Data Sheet'!A17 -> Sales | C6: ='Data Sheet'!B17/'Data Sheet'!B$17 -> 1 | D6: ='Data Sheet'!C17/'Data Sheet'!C$17 -> 1 | E6: ='Data Sheet'!D17/'Data Sheet'!D$17 -> 1 | F6: ='Data Sheet'!E17/'Data Sheet'!E$17 -> 1 | G6: ='Data Sheet'!F17/'Data Sheet'!F$17 -> 1 | H6: ='Data Sheet'!G17/'Data Sheet'!G$17 -> 1 | I6: ='Data Sheet'!H17/'Data Sheet'!H$17 -> 1 | J6: ='Data Sheet'!I17/'Data Sheet'!I$17 -> 1 | ... L6: ='Data Sheet'!K17/'Data Sheet'!K$17 -> 1
B8: ='Data Sheet'!A18 -> Raw Material Cost | C8: ='Data Sheet'!B18/'Data Sheet'!B$17 -> 0.36140887 | D8: ='Data Sheet'!C18/'Data Sheet'!C$17 -> 0.3412677 | E8: ='Data Sheet'!D18/'Data Sheet'!D$17 -> 0.36457743 | F8: ='Data Sheet'!E18/'Data Sheet'!E$17 -> 0.36544727 | G8: ='Data Sheet'!F18/'Data Sheet'!F$17 -> 0.42179833 | H8: ='Data Sheet'!G18/'Data Sheet'!G$17 -> 0.44638924 | I8: ='Data Sheet'!H18/'Data Sheet'!H$17 -> 0.41405473 | J8: ='Data Sheet'!I18/'Data Sheet'!I$17 -> 0.4025878 | ... L8: ='Data Sheet'!K18/'Data Sheet'!K$17 -> 0.44502412
B9: ='Data Sheet'!A19 -> Change in Inventory | C9: ='Data Sheet'!B19/'Data Sheet'!B$17 -> -0.013855582 | D9: ='Data Sheet'!C19/'Data Sheet'!C$17 -> -0.023654432 | E9: ='Data Sheet'!D19/'Data Sheet'!D$17 -> 0.0042033878 | F9: ='Data Sheet'!E19/'Data Sheet'!E$17 -> 0.014236946 | G9: ='Data Sheet'!F19/'Data Sheet'!F$17 -> 0.013099947 | H9: ='Data Sheet'!G19/'Data Sheet'!G$17 -> 0.011311818 | I9: ='Data Sheet'!H19/'Data Sheet'!H$17 -> 0.0050563297 | J9: ='Data Sheet'!I19/'Data Sheet'!I$17 -> 0.0054138009 | ... L9: ='Data Sheet'!K19/'Data Sheet'!K$17 -> 0.032338173
B10: ='Data Sheet'!A20 -> Power and Fuel | C10: ='Data Sheet'!B20/'Data Sheet'!B$17 -> 0.013662913 | D10: ='Data Sheet'!C20/'Data Sheet'!C$17 -> 0.015040643 | E10: ='Data Sheet'!D20/'Data Sheet'!D$17 -> 0.01544759 | F10: ='Data Sheet'!E20/'Data Sheet'!E$17 -> 0.015810617 | G10: ='Data Sheet'!F20/'Data Sheet'!F$17 -> 0.014202116 | H10: ='Data Sheet'!G20/'Data Sheet'!G$17 -> 0.01467189 | I10: ='Data Sheet'!H20/'Data Sheet'!H$17 -> 0.017376718 | J10: ='Data Sheet'!I20/'Data Sheet'!I$17 -> 0.014027275 | ... L10: ='Data Sheet'!K20/'Data Sheet'!K$17 -> 0.012016346
B11: ='Data Sheet'!A21 -> Other Mfr. Exp | C11: ='Data Sheet'!B21/'Data Sheet'!B$17 -> 0.039373264 | D11: ='Data Sheet'!C21/'Data Sheet'!C$17 -> 0.039071609 | E11: ='Data Sheet'!D21/'Data Sheet'!D$17 -> 0.038705549 | F11: ='Data Sheet'!E21/'Data Sheet'!E$17 -> 0.038638973 | G11: ='Data Sheet'!F21/'Data Sheet'!F$17 -> 0.032222131 | H11: ='Data Sheet'!G21/'Data Sheet'!G$17 -> 0.031126792 | I11: ='Data Sheet'!H21/'Data Sheet'!H$17 -> 0.032823348 | J11: ='Data Sheet'!I21/'Data Sheet'!I$17 -> 0.032146292 | ... L11: ='Data Sheet'!K21/'Data Sheet'!K$17 -> 0.032744166
B12: ='Data Sheet'!A22 -> Employee Cost | C12: ='Data Sheet'!B22/'Data Sheet'!B$17 -> 0.084917788 | D12: ='Data Sheet'!C22/'Data Sheet'!C$17 -> 0.086559074 | E12: ='Data Sheet'!D22/'Data Sheet'!D$17 -> 0.086427727 | F12: ='Data Sheet'!E22/'Data Sheet'!E$17 -> 0.086980969 | G12: ='Data Sheet'!F22/'Data Sheet'!F$17 -> 0.090612283 | H12: ='Data Sheet'!G22/'Data Sheet'!G$17 -> 0.080642874 | I12: ='Data Sheet'!H22/'Data Sheet'!H$17 -> 0.080884073 | J12: ='Data Sheet'!I22/'Data Sheet'!I$17 -> 0.081677779 | ... L12: ='Data Sheet'!K22/'Data Sheet'!K$17 -> 0.085985008
B13: ='Data Sheet'!A23 -> Selling and admin | C13: ='Data Sheet'!B23/'Data Sheet'!B$17 -> 0.09773146 | D13: ='Data Sheet'!C23/'Data Sheet'!C$17 -> 0.091023394 | E13: ='Data Sheet'!D23/'Data Sheet'!D$17 -> 0.094051086 | F13: ='Data Sheet'!E23/'Data Sheet'!E$17 -> 0.090885585 | G13: ='Data Sheet'!F23/'Data Sheet'!F$17 -> 0.086012776 | H13: ='Data Sheet'!G23/'Data Sheet'!G$17 -> 0.080112406 | I13: ='Data Sheet'!H23/'Data Sheet'!H$17 -> 0.079020821 | J13: ='Data Sheet'!I23/'Data Sheet'!I$17 -> 0.078202536 | ... L13: ='Data Sheet'!K23/'Data Sheet'!K$17 -> 0.080868256
B14: ='Data Sheet'!A24 -> Other Expenses | C14: ='Data Sheet'!B24/'Data Sheet'!B$17 -> 0.027339154 | D14: ='Data Sheet'!C24/'Data Sheet'!C$17 -> 0.023153154 | E14: ='Data Sheet'!D24/'Data Sheet'!D$17 -> 0.021511358 | F14: ='Data Sheet'!E24/'Data Sheet'!E$17 -> 0.024806379 | G14: ='Data Sheet'!F24/'Data Sheet'!F$17 -> 0.021811726 | H14: ='Data Sheet'!G24/'Data Sheet'!G$17 -> 0.018302555 | I14: ='Data Sheet'!H24/'Data Sheet'!H$17 -> 0.018451465 | J14: ='Data Sheet'!I24/'Data Sheet'!I$17 -> 0.025996166 | ... L14: ='Data Sheet'!K24/'Data Sheet'!K$17 -> 0.029477966
B15: ='Data Sheet'!A25 -> Other Income | C15: ='Data Sheet'!B25/'Data Sheet'!B$17 -> 0.041120615 | D15: ='Data Sheet'!C25/'Data Sheet'!C$17 -> 0.051550395 | E15: ='Data Sheet'!D25/'Data Sheet'!D$17 -> 0.043038024 | F15: ='Data Sheet'!E25/'Data Sheet'!E$17 -> 0.04894579 | G15: ='Data Sheet'!F25/'Data Sheet'!F$17 -> 0.052315944 | H15: ='Data Sheet'!G25/'Data Sheet'!G$17 -> 0.031490386 | I15: ='Data Sheet'!H25/'Data Sheet'!H$17 -> 0.029577957 | J15: ='Data Sheet'!I25/'Data Sheet'!I$17 -> 0.049026275 | ... L15: ='Data Sheet'!K25/'Data Sheet'!K$17 -> 0.03199114
B16: ='Data Sheet'!A26 -> Depreciation | C16: ='Data Sheet'!B26/'Data Sheet'!B$17 -> 0.026954751 | D16: ='Data Sheet'!C26/'Data Sheet'!C$17 -> 0.028453629 | E16: ='Data Sheet'!D26/'Data Sheet'!D$17 -> 0.028891645 | F16: ='Data Sheet'!E26/'Data Sheet'!E$17 -> 0.033306066 | G16: ='Data Sheet'!F26/'Data Sheet'!F$17 -> 0.033407941 | H16: ='Data Sheet'!G26/'Data Sheet'!G$17 -> 0.028566628 | I16: ='Data Sheet'!H26/'Data Sheet'!H$17 -> 0.025508104 | J16: ='Data Sheet'!I26/'Data Sheet'!I$17 -> 0.022346631 | ... L16: ='Data Sheet'!K26/'Data Sheet'!K$17 -> 0.021688408
B17: ='Data Sheet'!A27 -> Interest | C17: ='Data Sheet'!B27/'Data Sheet'!B$17 -> 0.0011464286 | D17: ='Data Sheet'!C27/'Data Sheet'!C$17 -> 0.0026470151 | E17: ='Data Sheet'!D27/'Data Sheet'!D$17 -> 0.0014770505 | F17: ='Data Sheet'!E27/'Data Sheet'!E$17 -> 0.0016477787 | G17: ='Data Sheet'!F27/'Data Sheet'!F$17 -> 0.0011768778 | H17: ='Data Sheet'!G27/'Data Sheet'!G$17 -> 0.00098920694 | I17: ='Data Sheet'!H27/'Data Sheet'!H$17 -> 0.0010966027 | J17: ='Data Sheet'!I27/'Data Sheet'!I$17 -> 0.00057572329 | ... L17: ='Data Sheet'!K27/'Data Sheet'!K$17 -> 0.0010799002
B18: ='Data Sheet'!A28 -> Profit before tax | C18: ='Data Sheet'!B28/'Data Sheet'!B$17 -> 0.3747304 | D18: ='Data Sheet'!C28/'Data Sheet'!C$17 -> 0.40067974 | E18: ='Data Sheet'!D28/'Data Sheet'!D$17 -> 0.39615197 | F18: ='Data Sheet'!E28/'Data Sheet'!E$17 -> 0.4056591 | G18: ='Data Sheet'!F28/'Data Sheet'!F$17 -> 0.36417171 | H18: ='Data Sheet'!G28/'Data Sheet'!G$17 -> 0.34200062 | I18: ='Data Sheet'!H28/'Data Sheet'!H$17 -> 0.36541842 | J18: ='Data Sheet'!I28/'Data Sheet'!I$17 -> 0.39687988 | ... L18: ='Data Sheet'!K28/'Data Sheet'!K$17 -> 0.35544515
B19: ='Data Sheet'!A29 -> Tax | C19: ='Data Sheet'!B29/'Data Sheet'!B$17 -> 0.12974986 | D19: ='Data Sheet'!C29/'Data Sheet'!C$17 -> 0.13616972 | E19: ='Data Sheet'!D29/'Data Sheet'!D$17 -> 0.13061595 | F19: ='Data Sheet'!E29/'Data Sheet'!E$17 -> 0.089937171 | G19: ='Data Sheet'!F29/'Data Sheet'!F$17 -> 0.092479209 | H19: ='Data Sheet'!G29/'Data Sheet'!G$17 -> 0.086361278 | I19: ='Data Sheet'!H29/'Data Sheet'!H$17 -> 0.090785224 | J19: ='Data Sheet'!I29/'Data Sheet'!I$17 -> 0.091407076 | ... L19: ='Data Sheet'!K29/'Data Sheet'!K$17 -> 0.088948679
B20: ='Data Sheet'!A30 -> Net profit | C20: ='Data Sheet'!B30/'Data Sheet'!B$17 -> 0.24058961 | D20: ='Data Sheet'!C30/'Data Sheet'!C$17 -> 0.25941254 | E20: ='Data Sheet'!D30/'Data Sheet'!D$17 -> 0.2604973 | F20: ='Data Sheet'!E30/'Data Sheet'!E$17 -> 0.30991988 | G20: ='Data Sheet'!F30/'Data Sheet'!F$17 -> 0.26719187 | H20: ='Data Sheet'!G30/'Data Sheet'!G$17 -> 0.25134431 | I20: ='Data Sheet'!H30/'Data Sheet'!H$17 -> 0.27061368 | J20: ='Data Sheet'!I30/'Data Sheet'!I$17 -> 0.30116584 | ... L20: ='Data Sheet'!K30/'Data Sheet'!K$17 -> 0.26232902
B22: ="Common Size Balance Sheet of "&'Data Sheet'!B1 -> Common Size Balance Sheet of ITC LTD
B24: Particulars | C24: ='Data Sheet'!B16 -> 42825 | D24: ='Data Sheet'!C16 -> 43190 | E24: ='Data Sheet'!D16 -> 43555 | F24: ='Data Sheet'!E16 -> 43921 | G24: ='Data Sheet'!F16 -> 44286 | H24: ='Data Sheet'!G16 -> 44651 | I24: ='Data Sheet'!H16 -> 45016 | J24: ='Data Sheet'!I16 -> 45382 | ... L24: ='Data Sheet'!K16 -> 46112
B26: ='Historicals FS'!B61 -> Total Liabilities | C26: ='Historicals FS'!C61/'Historicals FS'!C61 -> 1 | D26: ='Historicals FS'!D61/'Historicals FS'!D61 -> 1 | E26: ='Historicals FS'!E61/'Historicals FS'!E61 -> 1 | F26: ='Historicals FS'!F61/'Historicals FS'!F61 -> 1 | G26: ='Historicals FS'!G61/'Historicals FS'!G61 -> 1 | H26: ='Historicals FS'!H61/'Historicals FS'!H61 -> 1 | I26: ='Historicals FS'!I61/'Historicals FS'!I61 -> 1 | J26: ='Historicals FS'!J61/'Historicals FS'!J61 -> 1 | ... L26: ='Historicals FS'!L61/'Historicals FS'!L61 -> 1
B28: ='Historicals FS'!B56 -> Equity Share Capital | C28: ='Historicals FS'!C56/'Historicals FS'!C$61 -> 0.021731243 | D28: ='Historicals FS'!D56/'Historicals FS'!D$61 -> 0.018997716 | E28: ='Historicals FS'!E56/'Historicals FS'!E$61 -> 0.017087767 | F28: ='Historicals FS'!F56/'Historicals FS'!F$61 -> 0.015899729 | G28: ='Historicals FS'!G56/'Historicals FS'!G$61 -> 0.016687464 | H28: ='Historicals FS'!H56/'Historicals FS'!H$61 -> 0.015963647 | I28: ='Historicals FS'!I56/'Historicals FS'!I$61 -> 0.014479624 | J28: ='Historicals FS'!J56/'Historicals FS'!J$61 -> 0.013606714 | ... L28: ='Historicals FS'!L56/'Historicals FS'!L$61 -> 0.0133809
B29: ='Historicals FS'!B57 -> Reserves | C29: ='Historicals FS'!C57/'Historicals FS'!C$61 -> 0.80857868 | D29: ='Historicals FS'!D57/'Historicals FS'!D$61 -> 0.79839629 | E29: ='Historicals FS'!E57/'Historicals FS'!E$61 -> 0.80730116 | F29: ='Historicals FS'!F57/'Historicals FS'!F$61 -> 0.8283976 | G29: ='Historicals FS'!G57/'Historicals FS'!G$61 -> 0.80146219 | H29: ='Historicals FS'!H57/'Historicals FS'!H$61 -> 0.79308804 | I29: ='Historicals FS'!I57/'Historicals FS'!I$61 -> 0.791235 | J29: ='Historicals FS'!J57/'Historicals FS'!J$61 -> 0.79842355 | ... L29: ='Historicals FS'!L57/'Historicals FS'!L$61 -> 0.76096199
B30: ='Historicals FS'!B58 -> Borrowings | C30: ='Historicals FS'!C58/'Historicals FS'!C$61 -> 0.00081791367 | D30: ='Historicals FS'!D58/'Historicals FS'!D$61 -> 0.00055914552 | E30: ='Historicals FS'!E58/'Historicals FS'!E$61 -> 0.00018734569 | F30: ='Historicals FS'!F58/'Historicals FS'!F$61 -> 0.0035887635 | G30: ='Historicals FS'!G58/'Historicals FS'!G$61 -> 0.0036717355 | H30: ='Historicals FS'!H58/'Historicals FS'!H$61 -> 0.0032312547 | I30: ='Historicals FS'!I58/'Historicals FS'!I$61 -> 0.0035656132 | J30: ='Historicals FS'!J58/'Historicals FS'!J$61 -> 0.0033069959 | ... L30: ='Historicals FS'!L58/'Historicals FS'!L$61 -> 0.0256208
B31: ='Historicals FS'!B59 -> Other Liabilities | C31: ='Historicals FS'!C59/'Historicals FS'!C$61 -> 0.16887216 | D31: ='Historicals FS'!D59/'Historicals FS'!D$61 -> 0.18204685 | E31: ='Historicals FS'!E59/'Historicals FS'!E$61 -> 0.17542373 | F31: ='Historicals FS'!F59/'Historicals FS'!F$61 -> 0.1521139 | G31: ='Historicals FS'!G59/'Historicals FS'!G$61 -> 0.17817861 | H31: ='Historicals FS'!H59/'Historicals FS'!H$61 -> 0.18771706 | I31: ='Historicals FS'!I59/'Historicals FS'!I$61 -> 0.19071976 | J31: ='Historicals FS'!J59/'Historicals FS'!J$61 -> 0.18466275 | ... L31: ='Historicals FS'!L59/'Historicals FS'!L$61 -> 0.20003631
B33: ='Historicals FS'!B71 -> Total Assets | C33: ='Historicals FS'!C71/'Historicals FS'!C71 -> 1 | D33: ='Historicals FS'!D71/'Historicals FS'!D71 -> 1 | E33: ='Historicals FS'!E71/'Historicals FS'!E71 -> 1 | F33: ='Historicals FS'!F71/'Historicals FS'!F71 -> 1 | G33: ='Historicals FS'!G71/'Historicals FS'!G71 -> 1 | H33: ='Historicals FS'!H71/'Historicals FS'!H71 -> 1 | I33: ='Historicals FS'!I71/'Historicals FS'!I71 -> 1 | J33: ='Historicals FS'!J71/'Historicals FS'!J71 -> 1 | ... L33: ='Historicals FS'!L71/'Historicals FS'!L71 -> 1
B35: ='Historicals FS'!B63 -> Net Block | C35: ='Historicals FS'!C63/'Historicals FS'!C$71 -> 0.2843284 | D35: ='Historicals FS'!D63/'Historicals FS'!D$71 -> 0.25721877 | E35: ='Historicals FS'!E63/'Historicals FS'!E$71 -> 0.27006481 | F35: ='Historicals FS'!F63/'Historicals FS'!F$71 -> 0.28085797 | G35: ='Historicals FS'!G63/'Historicals FS'!G$71 -> 0.31586551 | H35: ='Historicals FS'!H63/'Historicals FS'!H$71 -> 0.31389688 | I35: ='Historicals FS'!I63/'Historicals FS'!I$71 -> 0.30118817 | J35: ='Historicals FS'!J63/'Historicals FS'!J$71 -> 0.30320454 | ... L35: ='Historicals FS'!L63/'Historicals FS'!L$71 -> 0.23967536
B36: ='Historicals FS'!B64 -> Capital Work in Progress | C36: ='Historicals FS'!C64/'Historicals FS'!C$71 -> 0.066726335 | D36: ='Historicals FS'!D64/'Historicals FS'!D$71 -> 0.085744934 | E36: ='Historicals FS'!E64/'Historicals FS'!E$71 -> 0.057659261 | F36: ='Historicals FS'!F64/'Historicals FS'!F$71 -> 0.042121697 | G36: ='Historicals FS'!G64/'Historicals FS'!G$71 -> 0.054382439 | H36: ='Historicals FS'!H64/'Historicals FS'!H$71 -> 0.04178376 | I36: ='Historicals FS'!I64/'Historicals FS'!I$71 -> 0.03499087 | J36: ='Historicals FS'!J64/'Historicals FS'!J$71 -> 0.031178814 | ... L36: ='Historicals FS'!L64/'Historicals FS'!L$71 -> 0.017107304
B37: ='Historicals FS'!B65 -> Investments | C37: ='Historicals FS'!C65/'Historicals FS'!C$71 -> 0.3145243 | D37: ='Historicals FS'!D65/'Historicals FS'!D$71 -> 0.3432839 | E37: ='Historicals FS'!E65/'Historicals FS'!E$71 -> 0.34909151 | F37: ='Historicals FS'!F65/'Historicals FS'!F$71 -> 0.37075504 | G37: ='Historicals FS'!G65/'Historicals FS'!G$71 -> 0.33718294 | H37: ='Historicals FS'!H65/'Historicals FS'!H$71 -> 0.32179133 | I37: ='Historicals FS'!I65/'Historicals FS'!I$71 -> 0.34270874 | J37: ='Historicals FS'!J65/'Historicals FS'!J$71 -> 0.33910271 | ... L37: ='Historicals FS'!L65/'Historicals FS'!L$71 -> 0.40719319
B38: ='Historicals FS'!B66 -> Other Assets | C38: ='Historicals FS'!C66/'Historicals FS'!C$71 -> 0.09187718 | D38: ='Historicals FS'!D66/'Historicals FS'!D$71 -> 0.11019074 | E38: ='Historicals FS'!E66/'Historicals FS'!E$71 -> 0.099500495 | F38: ='Historicals FS'!F66/'Historicals FS'!F$71 -> 0.064136617 | G38: ='Historicals FS'!G66/'Historicals FS'!G$71 -> 0.054530891 | H38: ='Historicals FS'!H66/'Historicals FS'!H$71 -> 0.089608376 | I38: ='Historicals FS'!I66/'Historicals FS'!I$71 -> 0.092668776 | J38: ='Historicals FS'!J66/'Historicals FS'!J$71 -> 0.049726132 | ... L38: ='Historicals FS'!L66/'Historicals FS'!L$71 -> 0.063113271
B39: ='Historicals FS'!B67 -> Receivables | C39: ='Historicals FS'!C67/'Historicals FS'!C$71 -> 0.044264121 | D39: ='Historicals FS'!D67/'Historicals FS'!D$71 -> 0.041753631 | E39: ='Historicals FS'!E67/'Historicals FS'!E$71 -> 0.056249428 | F39: ='Historicals FS'!F67/'Historicals FS'!F$71 -> 0.033145196 | G39: ='Historicals FS'!G67/'Historicals FS'!G$71 -> 0.033916408 | H39: ='Historicals FS'!H67/'Historicals FS'!H$71 -> 0.031891541 | I39: ='Historicals FS'!I67/'Historicals FS'!I$71 -> 0.034441768 | J39: ='Historicals FS'!J67/'Historicals FS'!J$71 -> 0.043876249 | ... L39: ='Historicals FS'!L67/'Historicals FS'!L$71 -> 0.041894247
B40: ='Historicals FS'!B68 -> Inventory | C40: ='Historicals FS'!C68/'Historicals FS'!C$71 -> 0.14519399 | D40: ='Historicals FS'!D68/'Historicals FS'!D$71 -> 0.11667166 | E40: ='Historicals FS'!E68/'Historicals FS'!E$71 -> 0.10955764 | F40: ='Historicals FS'!F68/'Historicals FS'!F$71 -> 0.11485246 | G40: ='Historicals FS'!G68/'Historicals FS'!G$71 -> 0.14095788 | H40: ='Historicals FS'!H68/'Historicals FS'!H$71 -> 0.14073459 | I40: ='Historicals FS'!I68/'Historicals FS'!I$71 -> 0.13714352 | J40: ='Historicals FS'!J68/'Historicals FS'!J$71 -> 0.15424815 | ... L40: ='Historicals FS'!L68/'Historicals FS'!L$71 -> 0.1988842
B41: ='Historicals FS'!B69 -> Cash & Bank | C41: ='Historicals FS'!C69/'Historicals FS'!C$71 -> 0.053085674 | D41: ='Historicals FS'!D69/'Historicals FS'!D$71 -> 0.045136368 | E41: ='Historicals FS'!E69/'Historicals FS'!E$71 -> 0.057876855 | F41: ='Historicals FS'!F69/'Historicals FS'!F$71 -> 0.094131023 | G41: ='Historicals FS'!G69/'Historicals FS'!G$71 -> 0.063163937 | H41: ='Historicals FS'!H69/'Historicals FS'!H$71 -> 0.060293523 | I41: ='Historicals FS'!I69/'Historicals FS'!I$71 -> 0.056858155 | J41: ='Historicals FS'!J69/'Historicals FS'!J$71 -> 0.078663408 | ... L41: ='Historicals FS'!L69/'Historicals FS'!L$71 -> 0.032132422

Sheet Historicals FS
A2: # | B2: ="Income Statement of "&'Data Sheet'!$B$1 -> Income Statement of ITC LTD
B3: Particulars | C3: ='Data Sheet'!B16 -> 42825 | D3: ='Data Sheet'!C16 -> 43190 | E3: ='Data Sheet'!D16 -> 43555 | F3: ='Data Sheet'!E16 -> 43921 | G3: ='Data Sheet'!F16 -> 44286 | H3: ='Data Sheet'!G16 -> 44651 | I3: ='Data Sheet'!H16 -> 45016 | J3: ='Data Sheet'!I16 -> 45382 | ... L3: ='Data Sheet'!K16 -> 46112
B5: Revenue | C5: =IFERROR('Data Sheet'!B17,0) -> 42767.6 | D5: =IFERROR('Data Sheet'!C17,0) -> 43448.94 | E5: =IFERROR('Data Sheet'!D17,0) -> 48339.58 | F5: =IFERROR('Data Sheet'!E17,0) -> 49387.7 | G5: =IFERROR('Data Sheet'!F17,0) -> 49257.45 | H5: =IFERROR('Data Sheet'!G17,0) -> 60644.54 | I5: =IFERROR('Data Sheet'!H17,0) -> 70919.03 | J5: =IFERROR('Data Sheet'!I17,0) -> 67931.94 | ... L5: =IFERROR('Data Sheet'!K17,0) -> 78868.4
B6: Revenue Growth (y-o-y) | D6: =(D5/C5)-1 -> 0.015931219 | E6: =(E5/D5)-1 -> 0.11256063 | F6: =(F5/E5)-1 -> 0.021682439 | G6: =(G5/F5)-1 -> -0.0026372963 | H6: =(H5/G5)-1 -> 0.23117498 | I6: =(I5/H5)-1 -> 0.16942152 | J6: =(J5/I5)-1 -> -0.042119724 | K6: =(K5/J5)-1 -> 0.10880596 | L6: =(L5/K5)-1 -> 0.047064562
B8: COGS | C8: =IFERROR(SUM('Data Sheet'!B18,'Data Sheet'!B20:B22)-1*'Data Sheet'!B19,0) -> 21949.12 | D8: =IFERROR(SUM('Data Sheet'!C18,'Data Sheet'!C20:C22)-1*'Data Sheet'!C19,0) -> 21967.5 | E8: =IFERROR(SUM('Data Sheet'!D18,'Data Sheet'!D20:D22)-1*'Data Sheet'!D19,0) -> 24215.95 | F8: =IFERROR(SUM('Data Sheet'!E18,'Data Sheet'!E20:E22)-1*'Data Sheet'!E19,0) -> 24330.4 | G8: =IFERROR(SUM('Data Sheet'!F18,'Data Sheet'!F20:F22)-1*'Data Sheet'!F19,0) -> 26881.51 | H8: =IFERROR(SUM('Data Sheet'!G18,'Data Sheet'!G20:G22)-1*'Data Sheet'!G19,0) -> 34053.06 | I8: =IFERROR(SUM('Data Sheet'!H18,'Data Sheet'!H20:H22)-1*'Data Sheet'!H19,0) -> 38302.13 | J8: =IFERROR(SUM('Data Sheet'!I18,'Data Sheet'!I20:I22)-1*'Data Sheet'!I19,0) -> 35665.99 | ... L8: =IFERROR(SUM('Data Sheet'!K18,'Data Sheet'!K20:K22)-1*'Data Sheet'!K19,0) -> 42859.57
B9: COGS (% Sales) | C9: =C8/C5 -> 0.51321842 | D9: =D8/D5 -> 0.50559346 | E9: =E8/E5 -> 0.50095491 | F9: =F8/F5 -> 0.49264088 | G9: =G8/G5 -> 0.54573491 | H9: =H8/H5 -> 0.56151898 | I9: =I8/I5 -> 0.54008254 | J9: =J8/J5 -> 0.52502534 | ... L9: =L8/L5 -> 0.54343146
B11: Gross Profit | C11: =C5-C8 -> 20818.48 | D11: =D5-D8 -> 21481.44 | E11: =E5-E8 -> 24123.63 | F11: =F5-F8 -> 25057.3 | G11: =G5-G8 -> 22375.94 | H11: =H5-H8 -> 26591.48 | I11: =I5-I8 -> 32616.9 | J11: =J5-J8 -> 32265.95 | ... L11: =L5-L8 -> 36008.83
B12: Gross Margins (%) | C12: =C11/C5 -> 0.48678158 | D12: =D11/D5 -> 0.49440654 | E12: =E11/E5 -> 0.49904509 | F12: =F11/F5 -> 0.50735912 | G12: =G11/G5 -> 0.45426509 | H12: =H11/H5 -> 0.43848102 | I12: =I11/I5 -> 0.45991746 | J12: =J11/J5 -> 0.47497466 | ... L12: =L11/L5 -> 0.45656854
B14: S&G Exp. | C14: =IFERROR(SUM('Data Sheet'!B23:B24),0) -> 5348.97 | D14: =IFERROR(SUM('Data Sheet'!C23:C24),0) -> 4960.85 | E14: =IFERROR(SUM('Data Sheet'!D23:D24),0) -> 5586.24 | F14: =IFERROR(SUM('Data Sheet'!E23:E24),0) -> 5713.76 | G14: =IFERROR(SUM('Data Sheet'!F23:F24),0) -> 5311.16 | H14: =IFERROR(SUM('Data Sheet'!G23:G24),0) -> 5968.33 | I14: =IFERROR(SUM('Data Sheet'!H23:H24),0) -> 6912.64 | J14: =IFERROR(SUM('Data Sheet'!I23:I24),0) -> 7078.42 | ... L14: =IFERROR(SUM('Data Sheet'!K23:K24),0) -> 8702.83
B15: S&G Exp. (% Sales) | C15: =C14/C5 -> 0.12507061 | D15: =D14/D5 -> 0.11417655 | E15: =E14/E5 -> 0.11556244 | F15: =F14/F5 -> 0.11569196 | G15: =G14/G5 -> 0.1078245 | H15: =H14/H5 -> 0.09841496 | I15: =I14/I5 -> 0.097472286 | J15: =J14/J5 -> 0.1041987 | ... L15: =L14/L5 -> 0.11034622
B17: EBITDA | C17: =C11-C14 -> 15469.51 | D17: =D11-D14 -> 16520.59 | E17: =E11-E14 -> 18537.39 | F17: =F11-F14 -> 19343.54 | G17: =G11-G14 -> 17064.78 | H17: =H11-H14 -> 20623.15 | I17: =I11-I14 -> 25704.26 | J17: =J11-J14 -> 25187.53 | ... L17: =L11-L14 -> 27306
B18: EBITDA Margin (%) | C18: =C17/C5 -> 0.36171097 | D18: =D17/D5 -> 0.38022999 | E18: =E17/E5 -> 0.38348265 | F18: =F17/F5 -> 0.39166716 | G18: =G17/G5 -> 0.34644059 | H18: =H17/H5 -> 0.34006606 | I18: =I17/I5 -> 0.36244517 | J18: =J17/J5 -> 0.37077596 | ... L18: =L17/L5 -> 0.34622231
B20: Depreciation | C20: =IFERROR('Data Sheet'!B26,0) -> 1152.79 | D20: =IFERROR('Data Sheet'!C26,0) -> 1236.28 | E20: =IFERROR('Data Sheet'!D26,0) -> 1396.61 | F20: =IFERROR('Data Sheet'!E26,0) -> 1644.91 | G20: =IFERROR('Data Sheet'!F26,0) -> 1645.59 | H20: =IFERROR('Data Sheet'!G26,0) -> 1732.41 | I20: =IFERROR('Data Sheet'!H26,0) -> 1809.01 | J20: =IFERROR('Data Sheet'!I26,0) -> 1518.05 | ... L20: =IFERROR('Data Sheet'!K26,0) -> 1710.53
B21: Depreciation (% Sales) | C21: =C20/C5 -> 0.026954751 | D21: =D20/D5 -> 0.028453629 | E21: =E20/E5 -> 0.028891645 | F21: =F20/F5 -> 0.033306066 | G21: =G20/G5 -> 0.033407941 | H21: =H20/H5 -> 0.028566628 | I21: =I20/I5 -> 0.025508104 | J21: =J20/J5 -> 0.022346631 | ... L21: =L20/L5 -> 0.021688408
B23: EBIT | C23: =C17-C20 -> 14316.72 | D23: =D17-D20 -> 15284.31 | E23: =E17-E20 -> 17140.78 | F23: =F17-F20 -> 17698.63 | G23: =G17-G20 -> 15419.19 | H23: =H17-H20 -> 18890.74 | I23: =I17-I20 -> 23895.25 | J23: =J17-J20 -> 23669.48 | ... L23: =L17-L20 -> 25595.47
B24: EBIT Margin (%) | C24: =C23/C5 -> 0.33475622 | D24: =D23/D5 -> 0.35177636 | E24: =E23/E5 -> 0.354591 | F24: =F23/F5 -> 0.35836109 | G24: =G23/G5 -> 0.31303265 | H24: =H23/H5 -> 0.31149944 | I24: =I23/I5 -> 0.33693707 | J24: =J23/J5 -> 0.34842932 | ... L24: =L23/L5 -> 0.32453391
B26: Interest | C26: =IFERROR('Data Sheet'!B27,0) -> 49.03 | D26: =IFERROR('Data Sheet'!C27,0) -> 115.01 | E26: =IFERROR('Data Sheet'!D27,0) -> 71.4 | F26: =IFERROR('Data Sheet'!E27,0) -> 81.38 | G26: =IFERROR('Data Sheet'!F27,0) -> 57.97 | H26: =IFERROR('Data Sheet'!G27,0) -> 59.99 | I26: =IFERROR('Data Sheet'!H27,0) -> 77.77 | J26: =IFERROR('Data Sheet'!I27,0) -> 39.11 | ... L26: =IFERROR('Data Sheet'!K27,0) -> 85.17
B27: Interest (% Sales) | C27: =C26/C5 -> 0.0011464286 | D27: =D26/D5 -> 0.0026470151 | E27: =E26/E5 -> 0.0014770505 | F27: =F26/F5 -> 0.0016477787 | G27: =G26/G5 -> 0.0011768778 | H27: =H26/H5 -> 0.00098920694 | I27: =I26/I5 -> 0.0010966027 | J27: =J26/J5 -> 0.00057572329 | ... L27: =L26/L5 -> 0.0010799002
B29: EBT | C29: =C23-C26 -> 14267.69 | D29: =D23-D26 -> 15169.3 | E29: =E23-E26 -> 17069.38 | F29: =F23-F26 -> 17617.25 | G29: =G23-G26 -> 15361.22 | H29: =H23-H26 -> 18830.75 | I29: =I23-I26 -> 23817.48 | J29: =J23-J26 -> 23630.37 | ... L29: =L23-L26 -> 25510.3
B30: EBT Margin (%) | C30: =C29/C5 -> 0.33360979 | D30: =D29/D5 -> 0.34912935 | E30: =E29/E5 -> 0.35311395 | F30: =F29/F5 -> 0.35671331 | G30: =G29/G5 -> 0.31185577 | H30: =H29/H5 -> 0.31051023 | I30: =I29/I5 -> 0.33584046 | J30: =J29/J5 -> 0.3478536 | ... L30: =L29/L5 -> 0.32345401
B32: Tax | C32: =IFERROR('Data Sheet'!B29,0) -> 5549.09 | D32: =IFERROR('Data Sheet'!C29,0) -> 5916.43 | E32: =IFERROR('Data Sheet'!D29,0) -> 6313.92 | F32: =IFERROR('Data Sheet'!E29,0) -> 4441.79 | G32: =IFERROR('Data Sheet'!F29,0) -> 4555.29 | H32: =IFERROR('Data Sheet'!G29,0) -> 5237.34 | I32: =IFERROR('Data Sheet'!H29,0) -> 6438.4 | J32: =IFERROR('Data Sheet'!I29,0) -> 6209.46 | ... L32: =IFERROR('Data Sheet'!K29,0) -> 7015.24
B33: Tax (% Sales) | C33: =C32/C5 -> 0.12974986 | D33: =D32/D5 -> 0.13616972 | E33: =E32/E5 -> 0.13061595 | F33: =F32/F5 -> 0.089937171 | G33: =G32/G5 -> 0.092479209 | H33: =H32/H5 -> 0.086361278 | I33: =I32/I5 -> 0.090785224 | J33: =J32/J5 -> 0.091407076 | ... L33: =L32/L5 -> 0.088948679
B34: Tax (% EBT) | C34: =C32/C29 -> 0.38892701 | D34: =D32/D29 -> 0.39002657 | E34: =E32/E29 -> 0.36989744 | F34: =F32/F29 -> 0.25212732 | G34: =G32/G29 -> 0.29654481 | H34: =H32/H29 -> 0.278127 | I34: =I32/I29 -> 0.27032247 | J34: =J32/J29 -> 0.26277456 | ... L34: =L32/L29 -> 0.27499637
B36: Net Profit | C36: =C29-C32 -> 8718.6 | D36: =D29-D32 -> 9252.87 | E36: =E29-E32 -> 10755.46 | F36: =F29-F32 -> 13175.46 | G36: =G29-G32 -> 10805.93 | H36: =H29-H32 -> 13593.41 | I36: =I29-I32 -> 17379.08 | J36: =J29-J32 -> 17420.91 | ... L36: =L29-L32 -> 18495.06
B37: Net Margin(%) | C37: =C36/C5 -> 0.20385993 | D37: =D36/D5 -> 0.21295963 | E37: =E36/E5 -> 0.222498 | F37: =F36/F5 -> 0.26677614 | G37: =G36/G5 -> 0.21937656 | H37: =H36/H5 -> 0.22414895 | I37: =I36/I5 -> 0.24505524 | J37: =J36/J5 -> 0.25644653 | ... L37: =L36/L5 -> 0.23450533
B39: No. of Shares | C39: ='Data Sheet'!B93 -> 1214.74 | D39: ='Data Sheet'!C93 -> 1220.43 | E39: ='Data Sheet'!D93 -> 1225.86 | F39: ='Data Sheet'!E93 -> 1229.22 | G39: ='Data Sheet'!F93 -> 1230.88 | H39: ='Data Sheet'!G93 -> 1232.33 | I39: ='Data Sheet'!H93 -> 1242.8 | J39: ='Data Sheet'!I93 -> 1248.47 | ... L39: ='Data Sheet'!K93 -> 1252.95
B41: Dividend Amount | C41: ='Data Sheet'!B31 -> 5770.02 | D41: ='Data Sheet'!C31 -> 6285.21 | E41: ='Data Sheet'!D31 -> 7048.7 | F41: ='Data Sheet'!E31 -> 12476.58 | G41: ='Data Sheet'!F31 -> 13231.96 | H41: ='Data Sheet'!G31 -> 14171.8 | I41: ='Data Sheet'!H31 -> 19263.4 | J41: ='Data Sheet'!I31 -> 17166.46 | ... L41: ='Data Sheet'!K31 -> 18167.78
B43: Earnings Per Share | C43: =C36/C39 -> 7.1773384 | D43: =D36/D39 -> 7.5816475 | E43: =E36/E39 -> 8.7738078 | F43: =F36/F39 -> 10.718553 | G43: =G36/G39 -> 8.779028 | H43: =H36/H39 -> 11.030657 | I43: =I36/I39 -> 13.983811 | J43: =J36/J39 -> 13.953807 | ... L43: =L36/L39 -> 14.761212
B44: EPS Growth % (y-o-y) | D44: =(D43/C43)-1 -> 0.056331341 | E44: =(E43/D43)-1 -> 0.15724291 | F44: =(F43/E43)-1 -> 0.22165353 | G44: =(G43/F43)-1 -> -0.18095028 | H44: =(H43/G43)-1 -> 0.25647821 | I44: =(I43/H43)-1 -> 0.26772234 | J44: =(J43/I43)-1 -> -0.0021455732 | K44: =(K43/J43)-1 -> -0.012152388 | L44: =(L43/K43)-1 -> 0.07087634
B46: Dividend Per Share | C46: =C41/C39 -> 4.7500041 | D46: =D41/D39 -> 5.1499963 | E46: =E41/E39 -> 5.7500041 | F46: =F41/F39 -> 10.149998 | G46: =G41/G39 -> 10.75 | H46: =H41/H39 -> 11.500004 | I46: =I41/I39 -> 15.5 | J46: =J41/J39 -> 13.749998 | ... L46: =L41/L39 -> 14.500004
B47: Dividend Payout Ratio (%) | C47: =IF(C46>0,C46/C43) -> 0.66180579 | D47: =IF(D46>0,D46/D43) -> 0.6792714 | E47: =IF(E46>0,E46/E43) -> 0.65536016 | F47: =IF(F46>0,F46/F43) -> 0.94695593 | G47: =IF(G46>0,G46/G43) -> 1.2245091 | H47: =IF(H46>0,H46/H43) -> 1.0425493 | I47: =IF(I46>0,I46/I43) -> 1.1084246 | J47: =IF(J46>0,J46/J43) -> 0.98539399 | ... L47: =IF(L46>0,L46/L43) -> 0.98230446
B49: Retained Earnings (%) | C49: =IF(C46<C43,(C43-C46)/C43,0) -> 0.33819421 | D49: =IF(D46<D43,(D43-D46)/D43,0) -> 0.3207286 | E49: =IF(E46<E43,(E43-E46)/E43,0) -> 0.34463984 | F49: =IF(F46<F43,(F43-F46)/F43,0) -> 0.053044068 | G49: =IF(G46<G43,(G43-G46)/G43,0) -> 0 | H49: =IF(H46<H43,(H43-H46)/H43,0) -> 0 | I49: =IF(I46<I43,(I43-I46)/I43,0) -> 0 | J49: =IF(J46<J43,(J43-J46)/J43,0) -> 0.014606011 | ... L49: =IF(L46<L43,(L43-L46)/L43,0) -> 0.017695536
B51: NOPAT | C51: =C23*(1-C33) -> 12459.128 | D51: =D23*(1-D33) -> 13203.05 | E51: =E23*(1-E33) -> 14901.921 | F51: =F23*(1-F33) -> 16106.865 | G51: =G23*(1-G33) -> 13993.236 | H51: =H23*(1-H33) -> 17259.312 | I51: =I23*(1-I33) -> 21725.914 | J51: =J23*(1-J33) -> 21505.922 | ... L51: =L23*(1-L33) -> 23318.787
A53: # | B53: ="Balance Sheet of "&'Data Sheet'!$B$1 -> Balance Sheet of ITC LTD
B54: Particulars | C54: ='Data Sheet'!B56 -> 42825 | D54: ='Data Sheet'!C56 -> 43190 | E54: ='Data Sheet'!D56 -> 43555 | F54: ='Data Sheet'!E56 -> 43921 | G54: ='Data Sheet'!F56 -> 44286 | H54: ='Data Sheet'!G56 -> 44651 | I54: ='Data Sheet'!H56 -> 45016 | J54: ='Data Sheet'!I56 -> 45382 | ... L54: ='Data Sheet'!K56 -> 46112
B56: =IFERROR('Data Sheet'!A57,0) -> Equity Share Capital | C56: =IFERROR('Data Sheet'!B57,0) -> 1214.74 | D56: =IFERROR('Data Sheet'!C57,0) -> 1220.43 | E56: =IFERROR('Data Sheet'!D57,0) -> 1225.86 | F56: =IFERROR('Data Sheet'!E57,0) -> 1229.22 | G56: =IFERROR('Data Sheet'!F57,0) -> 1230.88 | H56: =IFERROR('Data Sheet'!G57,0) -> 1232.33 | I56: =IFERROR('Data Sheet'!H57,0) -> 1242.8 | ... L56: =IFERROR('Data Sheet'!K57,0) -> 1252.95
B57: ='Data Sheet'!A58 -> Reserves | C57: ='Data Sheet'!B58 -> 45198.19 | D57: ='Data Sheet'!C58 -> 51289.68 | E57: ='Data Sheet'!D58 -> 57915.01 | F57: ='Data Sheet'!E58 -> 64044.04 | G57: ='Data Sheet'!F58 -> 59116.46 | H57: ='Data Sheet'!G58 -> 61223.24 | I57: ='Data Sheet'!H58 -> 67912.46 | ... L57: ='Data Sheet'!K58 -> 71254.35
B58: ='Data Sheet'!A59 -> Borrowings | C58: ='Data Sheet'!B59 -> 45.72 | D58: ='Data Sheet'!C59 -> 35.92 | E58: ='Data Sheet'!D59 -> 13.44 | F58: ='Data Sheet'!E59 -> 277.45 | G58: ='Data Sheet'!F59 -> 270.83 | H58: ='Data Sheet'!G59 -> 249.44 | I58: ='Data Sheet'!H59 -> 306.04 | ... L58: ='Data Sheet'!K59 -> 2399.06
B59: ='Data Sheet'!A60 -> Other Liabilities | C59: ='Data Sheet'!B60 -> 9439.67 | D59: ='Data Sheet'!C60 -> 11694.85 | E59: ='Data Sheet'!D60 -> 12584.73 | F59: ='Data Sheet'!E60 -> 11760.04 | G59: ='Data Sheet'!F60 -> 13142.59 | H59: ='Data Sheet'!G60 -> 14491.01 | I59: ='Data Sheet'!H60 -> 16369.66 | ... L59: ='Data Sheet'!K60 -> 18730.84
B61: Total Liabilities | C61: =SUM(C56:C59) -> 55898.32 | D61: =SUM(D56:D59) -> 64240.88 | E61: =SUM(E56:E59) -> 71739.04 | F61: =SUM(F56:F59) -> 77310.75 | G61: =SUM(G56:G59) -> 73760.76 | H61: =SUM(H56:H59) -> 77196.02 | I61: =SUM(I56:I59) -> 85830.96 | J61: =SUM(J56:J59) -> 91753.97 | ... L61: =SUM(L56:L59) -> 93637.2
B63: =IFERROR('Data Sheet'!A62,0) -> Net Block | C63: =IFERROR('Data Sheet'!B62,0) -> 15893.48 | D63: =IFERROR('Data Sheet'!C62,0) -> 16523.96 | E63: =IFERROR('Data Sheet'!D62,0) -> 19374.19 | F63: =IFERROR('Data Sheet'!E62,0) -> 21713.34 | G63: =IFERROR('Data Sheet'!F62,0) -> 23298.48 | H63: =IFERROR('Data Sheet'!G62,0) -> 24231.59 | I63: =IFERROR('Data Sheet'!H62,0) -> 25851.27 | ... L63: =IFERROR('Data Sheet'!K62,0) -> 22442.53
B64: =IFERROR('Data Sheet'!A63,0) -> Capital Work in Progress | C64: =IFERROR('Data Sheet'!B63,0) -> 3729.89 | D64: =IFERROR('Data Sheet'!C63,0) -> 5508.33 | E64: =IFERROR('Data Sheet'!D63,0) -> 4136.42 | F64: =IFERROR('Data Sheet'!E63,0) -> 3256.46 | G64: =IFERROR('Data Sheet'!F63,0) -> 4011.29 | H64: =IFERROR('Data Sheet'!G63,0) -> 3225.54 | I64: =IFERROR('Data Sheet'!H63,0) -> 3003.3 | ... L64: =IFERROR('Data Sheet'!K63,0) -> 1601.88
B65: =IFERROR('Data Sheet'!A64,0) -> Investments | C65: =IFERROR('Data Sheet'!B64,0) -> 17581.38 | D65: =IFERROR('Data Sheet'!C64,0) -> 22052.86 | E65: =IFERROR('Data Sheet'!D64,0) -> 25043.49 | F65: =IFERROR('Data Sheet'!E64,0) -> 28663.35 | G65: =IFERROR('Data Sheet'!F64,0) -> 24870.87 | H65: =IFERROR('Data Sheet'!G64,0) -> 24841.01 | I65: =IFERROR('Data Sheet'!H64,0) -> 29415.02 | ... L65: =IFERROR('Data Sheet'!K64,0) -> 38128.43
B66: =IFERROR('Data Sheet'!A65,0) -> Other Assets | C66: =IFERROR('Data Sheet'!B65-SUM('Data Sheet'!B67:B69),0) -> 5135.78 | D66: =IFERROR('Data Sheet'!C65-SUM('Data Sheet'!C67:C69),0) -> 7078.75 | E66: =IFERROR('Data Sheet'!D65-SUM('Data Sheet'!D67:D69),0) -> 7138.07 | F66: =IFERROR('Data Sheet'!E65-SUM('Data Sheet'!E67:E69),0) -> 4958.45 | G66: =IFERROR('Data Sheet'!F65-SUM('Data Sheet'!F67:F69),0) -> 4022.24 | H66: =IFERROR('Data Sheet'!G65-SUM('Data Sheet'!G67:G69),0) -> 6917.41 | I66: =IFERROR('Data Sheet'!H65-SUM('Data Sheet'!H67:H69),0) -> 7953.85 | J66: =IFERROR('Data Sheet'!I65-SUM('Data Sheet'!I67:I69),0) -> 4562.57 | ... L66: =IFERROR('Data Sheet'!K65-SUM('Data Sheet'!K67:K69),0) -> 5909.75
B67: =IFERROR('Data Sheet'!A67,0) -> Receivables | C67: =IFERROR('Data Sheet'!B67,0) -> 2474.29 | D67: =IFERROR('Data Sheet'!C67,0) -> 2682.29 | E67: =IFERROR('Data Sheet'!D67,0) -> 4035.28 | F67: =IFERROR('Data Sheet'!E67,0) -> 2562.48 | G67: =IFERROR('Data Sheet'!F67,0) -> 2501.7 | H67: =IFERROR('Data Sheet'!G67,0) -> 2461.9 | I67: =IFERROR('Data Sheet'!H67,0) -> 2956.17 | ... L67: =IFERROR('Data Sheet'!K67,0) -> 3922.86
B68: =IFERROR('Data Sheet'!A68,0) -> Inventory | C68: =IFERROR('Data Sheet'!B68,0) -> 8116.1 | D68: =IFERROR('Data Sheet'!C68,0) -> 7495.09 | E68: =IFERROR('Data Sheet'!D68,0) -> 7859.56 | F68: =IFERROR('Data Sheet'!E68,0) -> 8879.33 | G68: =IFERROR('Data Sheet'!F68,0) -> 10397.16 | H68: =IFERROR('Data Sheet'!G68,0) -> 10864.15 | I68: =IFERROR('Data Sheet'!H68,0) -> 11771.16 | ... L68: =IFERROR('Data Sheet'!K68,0) -> 18622.96
B69: =IFERROR('Data Sheet'!A69,0) -> Cash & Bank | C69: =IFERROR('Data Sheet'!B69,0) -> 2967.4 | D69: =IFERROR('Data Sheet'!C69,0) -> 2899.6 | E69: =IFERROR('Data Sheet'!D69,0) -> 4152.03 | F69: =IFERROR('Data Sheet'!E69,0) -> 7277.34 | G69: =IFERROR('Data Sheet'!F69,0) -> 4659.02 | H69: =IFERROR('Data Sheet'!G69,0) -> 4654.42 | I69: =IFERROR('Data Sheet'!H69,0) -> 4880.19 | ... L69: =IFERROR('Data Sheet'!K69,0) -> 3008.79
B71: Total Assets | C71: =SUM(C63:C69) -> 55898.32 | D71: =SUM(D63:D69) -> 64240.88 | E71: =SUM(E63:E69) -> 71739.04 | F71: =SUM(F63:F69) -> 77310.75 | G71: =SUM(G63:G69) -> 73760.76 | H71: =SUM(H63:H69) -> 77196.02 | I71: =SUM(I63:I69) -> 85830.96 | J71: =SUM(J63:J69) -> 91753.97 | ... L71: =SUM(L63:L69) -> 93637.2
A73: # | B73: ="Cash Flow Statement of "&'Data Sheet'!$B$1 -> Cash Flow Statement of ITC LTD
B74: Particulars | C74: ='Cash Flows'!E3 -> 42795 | D74: ='Cash Flows'!F3 -> 43160 | E74: ='Cash Flows'!G3 -> 43525 | F74: ='Cash Flows'!H3 -> 43891 | G74: ='Cash Flows'!I3 -> 44256 | H74: ='Cash Flows'!J3 -> 44621 | I74: ='Cash Flows'!K3 -> 44986 | J74: ='Cash Flows'!L3 -> 45352 | ... L74: ='Cash Flows'!N3 -> 46082
B76: Operating Activities-
B77: =IFERROR('Cash Flows'!B5,0) -> Profit from operations | C77: =IFERROR('Cash Flows'!E5,0) -> 16075 | D77: =IFERROR('Cash Flows'!F5,0) -> 17433 | E77: =IFERROR('Cash Flows'!G5,0) -> 18862 | F77: =IFERROR('Cash Flows'!H5,0) -> 19416 | G77: =IFERROR('Cash Flows'!I5,0) -> 17326 | H77: =IFERROR('Cash Flows'!J5,0) -> 20857 | I77: =IFERROR('Cash Flows'!K5,0) -> 26052 | J77: =IFERROR('Cash Flows'!L5,0) -> 26635 | ... L77: =IFERROR('Cash Flows'!N5,0) -> 27600
B78: =IFERROR('Cash Flows'!B6,0) -> Receivables | C78: =IFERROR('Cash Flows'!E6,0) -> -870 | D78: =IFERROR('Cash Flows'!F6,0) -> -964 | E78: =IFERROR('Cash Flows'!G6,0) -> -755 | F78: =IFERROR('Cash Flows'!H6,0) -> 1411 | G78: =IFERROR('Cash Flows'!I6,0) -> -66 | H78: =IFERROR('Cash Flows'!J6,0) -> -732 | I78: =IFERROR('Cash Flows'!K6,0) -> -884 | J78: =IFERROR('Cash Flows'!L6,0) -> -934 | ... L78: =IFERROR('Cash Flows'!N6,0) -> 468
B79: =IFERROR('Cash Flows'!B7,0) -> Inventory | C79: =IFERROR('Cash Flows'!E7,0) -> 593 | D79: =IFERROR('Cash Flows'!F7,0) -> 602 | E79: =IFERROR('Cash Flows'!G7,0) -> -359 | F79: =IFERROR('Cash Flows'!H7,0) -> -508 | G79: =IFERROR('Cash Flows'!I7,0) -> -1460 | H79: =IFERROR('Cash Flows'!J7,0) -> -466 | I79: =IFERROR('Cash Flows'!K7,0) -> -1098 | J79: =IFERROR('Cash Flows'!L7,0) -> -2545 | ... L79: =IFERROR('Cash Flows'!N7,0) -> -3306
B80: =IFERROR('Cash Flows'!B8,0) -> Payables | C80: =IFERROR('Cash Flows'!E8,0) -> 321 | D80: =IFERROR('Cash Flows'!F8,0) -> 2098 | E80: =IFERROR('Cash Flows'!G8,0) -> 639 | F80: =IFERROR('Cash Flows'!H8,0) -> -607 | G80: =IFERROR('Cash Flows'!I8,0) -> 1112 | H80: =IFERROR('Cash Flows'!J8,0) -> 1099 | I80: =IFERROR('Cash Flows'!K8,0) -> 1058 | J80: =IFERROR('Cash Flows'!L8,0) -> 141 | ... L80: =IFERROR('Cash Flows'!N8,0) -> 76
B81: =IFERROR('Cash Flows'!B9,0) -> Working capital changes | C81: =IFERROR('Cash Flows'!E9,0) -> 44 | D81: =IFERROR('Cash Flows'!F9,0) -> 1736 | E81: =IFERROR('Cash Flows'!G9,0) -> -476 | F81: =IFERROR('Cash Flows'!H9,0) -> 296 | G81: =IFERROR('Cash Flows'!I9,0) -> -413 | H81: =IFERROR('Cash Flows'!J9,0) -> -100 | I81: =IFERROR('Cash Flows'!K9,0) -> -924 | J81: =IFERROR('Cash Flows'!L9,0) -> -3337 | ... L81: =IFERROR('Cash Flows'!N9,0) -> -2762
B82: =IFERROR('Cash Flows'!B10,0) -> Direct taxes | C82: =IFERROR('Cash Flows'!E10,0) -> -5492 | D82: =IFERROR('Cash Flows'!F10,0) -> -6000 | E82: =IFERROR('Cash Flows'!G10,0) -> -5803 | F82: =IFERROR('Cash Flows'!H10,0) -> -5023 | G82: =IFERROR('Cash Flows'!I10,0) -> -4387 | H82: =IFERROR('Cash Flows'!J10,0) -> -4982 | I82: =IFERROR('Cash Flows'!K10,0) -> -6250 | J82: =IFERROR('Cash Flows'!L10,0) -> -6120 | ... L82: =IFERROR('Cash Flows'!N10,0) -> -6374
B83: =IFERROR('Cash Flows'!B4,0) -> Cash from Operating Activity - | C83: =IFERROR('Cash Flows'!E4,0) -> 10627 | D83: =IFERROR('Cash Flows'!F4,0) -> 13169 | E83: =IFERROR('Cash Flows'!G4,0) -> 12583 | F83: =IFERROR('Cash Flows'!H4,0) -> 14690 | G83: =IFERROR('Cash Flows'!I4,0) -> 12527 | H83: =IFERROR('Cash Flows'!J4,0) -> 15776 | I83: =IFERROR('Cash Flows'!K4,0) -> 18878 | J83: =IFERROR('Cash Flows'!L4,0) -> 17179 | ... L83: =IFERROR('Cash Flows'!N4,0) -> 18464
B85: Investing Activities-
B86: =IFERROR('Cash Flows'!B13,0) -> Fixed assets purchased | C86: =IFERROR('Cash Flows'!E13,0) -> -3122 | D86: =IFERROR('Cash Flows'!F13,0) -> -2878 | E86: =IFERROR('Cash Flows'!G13,0) -> -3169 | F86: =IFERROR('Cash Flows'!H13,0) -> -2441 | G86: =IFERROR('Cash Flows'!I13,0) -> -1837 | H86: =IFERROR('Cash Flows'!J13,0) -> -2142 | I86: =IFERROR('Cash Flows'!K13,0) -> -2743 | J86: =IFERROR('Cash Flows'!L13,0) -> -3563 | ... L86: =IFERROR('Cash Flows'!N13,0) -> -2183
B87: =IFERROR('Cash Flows'!B14,0) -> Fixed assets sold | C87: =IFERROR('Cash Flows'!E14,0) -> 50 | D87: =IFERROR('Cash Flows'!F14,0) -> 80 | E87: =IFERROR('Cash Flows'!G14,0) -> 28 | F87: =IFERROR('Cash Flows'!H14,0) -> 27 | G87: =IFERROR('Cash Flows'!I14,0) -> 3 | H87: =IFERROR('Cash Flows'!J14,0) -> 133 | I87: =IFERROR('Cash Flows'!K14,0) -> 49 | J87: =IFERROR('Cash Flows'!L14,0) -> 107 | ... L87: =IFERROR('Cash Flows'!N14,0) -> 50
B88: =IFERROR('Cash Flows'!B15,0) -> Investments purchased | C88: =IFERROR('Cash Flows'!E15,0) -> -85683 | D88: =IFERROR('Cash Flows'!F15,0) -> -98330 | E88: =IFERROR('Cash Flows'!G15,0) -> -94187 | F88: =IFERROR('Cash Flows'!H15,0) -> -79835 | G88: =IFERROR('Cash Flows'!I15,0) -> -57553 | H88: =IFERROR('Cash Flows'!J15,0) -> -69776 | I88: =IFERROR('Cash Flows'!K15,0) -> -80932 | J88: =IFERROR('Cash Flows'!L15,0) -> -75107 | ... L88: =IFERROR('Cash Flows'!N15,0) -> -68173
B89: =IFERROR('Cash Flows'!B16,0) -> Investments sold | C89: =IFERROR('Cash Flows'!E16,0) -> 81034 | D89: =IFERROR('Cash Flows'!F16,0) -> 95017 | E89: =IFERROR('Cash Flows'!G16,0) -> 92454 | F89: =IFERROR('Cash Flows'!H16,0) -> 75835 | G89: =IFERROR('Cash Flows'!I16,0) -> 62797 | H89: =IFERROR('Cash Flows'!J16,0) -> 70992 | I89: =IFERROR('Cash Flows'!K16,0) -> 77230 | J89: =IFERROR('Cash Flows'!L16,0) -> 77830 | ... L89: =IFERROR('Cash Flows'!N16,0) -> 65737
B90: =IFERROR('Cash Flows'!B17,0) -> Interest received | C90: =IFERROR('Cash Flows'!E17,0) -> 756 | D90: =IFERROR('Cash Flows'!F17,0) -> 736 | E90: =IFERROR('Cash Flows'!G17,0) -> 1184 | F90: =IFERROR('Cash Flows'!H17,0) -> 1513 | G90: =IFERROR('Cash Flows'!I17,0) -> 1275 | H90: =IFERROR('Cash Flows'!J17,0) -> 1035 | I90: =IFERROR('Cash Flows'!K17,0) -> 1324 | J90: =IFERROR('Cash Flows'!L17,0) -> 1138 | ... L90: =IFERROR('Cash Flows'!N17,0) -> 917
B91: =IFERROR('Cash Flows'!B18,0) -> Dividends received | C91: =IFERROR('Cash Flows'!E18,0) -> 4 | D91: =IFERROR('Cash Flows'!F18,0) -> 13 | E91: =IFERROR('Cash Flows'!G18,0) -> 13 | F91: =IFERROR('Cash Flows'!H18,0) -> 17 | G91: =IFERROR('Cash Flows'!I18,0) -> 7 | H91: =IFERROR('Cash Flows'!J18,0) -> 16 | I91: =IFERROR('Cash Flows'!K18,0) -> 19 | J91: =IFERROR('Cash Flows'!L18,0) -> 36 | ... L91: =IFERROR('Cash Flows'!N18,0) -> 45
B92: =IFERROR('Cash Flows'!B19,0) -> Invest in subsidiaries | C92: =IFERROR('Cash Flows'!E19,0) -> 0 | D92: =IFERROR('Cash Flows'!F19,0) -> 0 | E92: =IFERROR('Cash Flows'!G19,0) -> 0 | F92: =IFERROR('Cash Flows'!H19,0) -> 0 | G92: =IFERROR('Cash Flows'!I19,0) -> 0 | H92: =IFERROR('Cash Flows'!J19,0) -> 0 | I92: =IFERROR('Cash Flows'!K19,0) -> 0 | J92: =IFERROR('Cash Flows'!L19,0) -> 0 | ... L92: =IFERROR('Cash Flows'!N19,0) -> 0
B93: =IFERROR('Cash Flows'!B20,0) -> Investment in group cos | C93: =IFERROR('Cash Flows'!E20,0) -> 0 | D93: =IFERROR('Cash Flows'!F20,0) -> 0 | E93: =IFERROR('Cash Flows'!G20,0) -> 0 | F93: =IFERROR('Cash Flows'!H20,0) -> 0 | G93: =IFERROR('Cash Flows'!I20,0) -> -2 | H93: =IFERROR('Cash Flows'!J20,0) -> -2 | I93: =IFERROR('Cash Flows'!K20,0) -> -2 | J93: =IFERROR('Cash Flows'!L20,0) -> -65 | ... L93: =IFERROR('Cash Flows'!N20,0) -> -183
B94: =IFERROR('Cash Flows'!B21,0) -> Redemption & Cancellation of Shares | C94: =IFERROR('Cash Flows'!E21,0) -> 129 | D94: =IFERROR('Cash Flows'!F21,0) -> 18 | E94: =IFERROR('Cash Flows'!G21,0) -> 18 | F94: =IFERROR('Cash Flows'!H21,0) -> 0 | G94: =IFERROR('Cash Flows'!I21,0) -> 0 | H94: =IFERROR('Cash Flows'!J21,0) -> 0 | I94: =IFERROR('Cash Flows'!K21,0) -> 56 | J94: =IFERROR('Cash Flows'!L21,0) -> 0 | ... L94: =IFERROR('Cash Flows'!N21,0) -> 0
B95: =IFERROR('Cash Flows'!B22,0) -> Other investing items | C95: =IFERROR('Cash Flows'!E22,0) -> 3579 | D95: =IFERROR('Cash Flows'!F22,0) -> -1769 | E95: =IFERROR('Cash Flows'!G22,0) -> -1887 | F95: =IFERROR('Cash Flows'!H22,0) -> -1290 | G95: =IFERROR('Cash Flows'!I22,0) -> 1051 | H95: =IFERROR('Cash Flows'!J22,0) -> -2494 | I95: =IFERROR('Cash Flows'!K22,0) -> -733 | J95: =IFERROR('Cash Flows'!L22,0) -> 1187 | ... L95: =IFERROR('Cash Flows'!N22,0) -> 1469
B96: =IFERROR('Cash Flows'!B12,0) -> Cash from Investing Activity - | C96: =IFERROR('Cash Flows'!E12,0) -> -3251 | D96: =IFERROR('Cash Flows'!F12,0) -> -7114 | E96: =IFERROR('Cash Flows'!G12,0) -> -5546 | F96: =IFERROR('Cash Flows'!H12,0) -> -6174 | G96: =IFERROR('Cash Flows'!I12,0) -> 5740 | H96: =IFERROR('Cash Flows'!J12,0) -> -2238 | I96: =IFERROR('Cash Flows'!K12,0) -> -5732 | J96: =IFERROR('Cash Flows'!L12,0) -> 1563 | ... L96: =IFERROR('Cash Flows'!N12,0) -> -2321
B98: Financing Activities-
B99: =IFERROR('Cash Flows'!B25,0) -> Proceeds from shares | C99: =IFERROR('Cash Flows'!E25,0) -> 1067 | D99: =IFERROR('Cash Flows'!F25,0) -> 913 | E99: =IFERROR('Cash Flows'!G25,0) -> 969 | F99: =IFERROR('Cash Flows'!H25,0) -> 625 | G99: =IFERROR('Cash Flows'!I25,0) -> 291 | H99: =IFERROR('Cash Flows'!J25,0) -> 292 | I99: =IFERROR('Cash Flows'!K25,0) -> 2477 | J99: =IFERROR('Cash Flows'!L25,0) -> 1443 | ... L99: =IFERROR('Cash Flows'!N25,0) -> 405
B100: =IFERROR('Cash Flows'!B26,0) -> Proceeds from borrowings | C100: =IFERROR('Cash Flows'!E26,0) -> 0 | D100: =IFERROR('Cash Flows'!F26,0) -> 11 | E100: =IFERROR('Cash Flows'!G26,0) -> 0 | F100: =IFERROR('Cash Flows'!H26,0) -> 0 | G100: =IFERROR('Cash Flows'!I26,0) -> 0 | H100: =IFERROR('Cash Flows'!J26,0) -> 0 | I100: =IFERROR('Cash Flows'!K26,0) -> 0 | J100: =IFERROR('Cash Flows'!L26,0) -> 8 | ... L100: =IFERROR('Cash Flows'!N26,0) -> 2120
B101: =IFERROR('Cash Flows'!B27,0) -> Repayment of borrowings | C101: =IFERROR('Cash Flows'!E27,0) -> -13 | D101: =IFERROR('Cash Flows'!F27,0) -> -8 | E101: =IFERROR('Cash Flows'!G27,0) -> -18 | F101: =IFERROR('Cash Flows'!H27,0) -> -3 | G101: =IFERROR('Cash Flows'!I27,0) -> -2 | H101: =IFERROR('Cash Flows'!J27,0) -> -1 | I101: =IFERROR('Cash Flows'!K27,0) -> -1 | J101: =IFERROR('Cash Flows'!L27,0) -> -2 | ... L101: =IFERROR('Cash Flows'!N27,0) -> -105
B102: =IFERROR('Cash Flows'!B28,0) -> Interest paid fin | C102: =IFERROR('Cash Flows'!E28,0) -> -25 | D102: =IFERROR('Cash Flows'!F28,0) -> -49 | E102: =IFERROR('Cash Flows'!G28,0) -> -98 | F102: =IFERROR('Cash Flows'!H28,0) -> -44 | G102: =IFERROR('Cash Flows'!I28,0) -> -41 | H102: =IFERROR('Cash Flows'!J28,0) -> -40 | I102: =IFERROR('Cash Flows'!K28,0) -> -41 | J102: =IFERROR('Cash Flows'!L28,0) -> -46 | ... L102: =IFERROR('Cash Flows'!N28,0) -> -82
B103: =IFERROR('Cash Flows'!B29,0) -> Dividends paid | C103: =IFERROR('Cash Flows'!E29,0) -> -6994 | D103: =IFERROR('Cash Flows'!F29,0) -> -5952 | E103: =IFERROR('Cash Flows'!G29,0) -> -6519 | F103: =IFERROR('Cash Flows'!H29,0) -> -7302 | G103: =IFERROR('Cash Flows'!I29,0) -> -18881 | H103: =IFERROR('Cash Flows'!J29,0) -> -13788 | I103: =IFERROR('Cash Flows'!K29,0) -> -15418 | J103: =IFERROR('Cash Flows'!L29,0) -> -19899 | ... L103: =IFERROR('Cash Flows'!N29,0) -> -18271
B104: =IFERROR('Cash Flows'!B30,0) -> Financial liabilities | C104: =IFERROR('Cash Flows'!E30,0) -> 0 | D104: =IFERROR('Cash Flows'!F30,0) -> 0 | E104: =IFERROR('Cash Flows'!G30,0) -> 0 | F104: =IFERROR('Cash Flows'!H30,0) -> -49 | G104: =IFERROR('Cash Flows'!I30,0) -> -55 | H104: =IFERROR('Cash Flows'!J30,0) -> -59 | I104: =IFERROR('Cash Flows'!K30,0) -> -59 | J104: =IFERROR('Cash Flows'!L30,0) -> -67 | ... L104: =IFERROR('Cash Flows'!N30,0) -> -68
B105: =IFERROR('Cash Flows'!B31,0) -> Other financing items | C105: =IFERROR('Cash Flows'!E31,0) -> -1335 | D105: =IFERROR('Cash Flows'!F31,0) -> -1136 | E105: =IFERROR('Cash Flows'!G31,0) -> -1203 | F105: =IFERROR('Cash Flows'!H31,0) -> -1409 | G105: =IFERROR('Cash Flows'!I31,0) -> 55 | H105: =IFERROR('Cash Flows'!J31,0) -> 15 | I105: =IFERROR('Cash Flows'!K31,0) -> 35 | J105: =IFERROR('Cash Flows'!L31,0) -> 12 | ... L105: =IFERROR('Cash Flows'!N31,0) -> -146
B106: =IFERROR('Cash Flows'!B24,0) -> Cash from Financing Activity - | C106: =IFERROR('Cash Flows'!E24,0) -> -7301 | D106: =IFERROR('Cash Flows'!F24,0) -> -6221 | E106: =IFERROR('Cash Flows'!G24,0) -> -6869 | F106: =IFERROR('Cash Flows'!H24,0) -> -8181 | G106: =IFERROR('Cash Flows'!I24,0) -> -18634 | H106: =IFERROR('Cash Flows'!J24,0) -> -13580 | I106: =IFERROR('Cash Flows'!K24,0) -> -13006 | J106: =IFERROR('Cash Flows'!L24,0) -> -18551 | ... L106: =IFERROR('Cash Flows'!N24,0) -> -16147
B108: =IFERROR('Cash Flows'!B33,0) -> Net Cash Flow | C108: =IFERROR('Cash Flows'!E33,0) -> 75 | D108: =IFERROR('Cash Flows'!F33,0) -> -166 | E108: =IFERROR('Cash Flows'!G33,0) -> 169 | F108: =IFERROR('Cash Flows'!H33,0) -> 334 | G108: =IFERROR('Cash Flows'!I33,0) -> -367 | H108: =IFERROR('Cash Flows'!J33,0) -> -43 | I108: =IFERROR('Cash Flows'!K33,0) -> 139 | J108: =IFERROR('Cash Flows'!L33,0) -> 191 | ... L108: =IFERROR('Cash Flows'!N33,0) -> -4

Sheet Data Room>

Sheet Master Input Center
A2: # | B2: All Sheets
B4: Tax Rate | C4: 0.2517
B6: Median Tax Rate (% EBT) - Last five years | C6: =MEDIAN('Historicals FS'!H34:L34) -> 0.27499637
B7: Assumed Tax for ITC | C7: =IFERROR(IF('Historicals FS'!L34>'Master Input Center'!C6,'Historicals FS'!L34,'Master Input Center'!C6),0) -> 0.27499637
B8: Statutory Marginal Tax Rate (India) | C8: 0.2517
A12: # | B12: Sheet : Comps Beta Calculation
B14: Country | C14: India
B15: Market Beta | C15: 1
B16: Raw Beta Weight | C16: 0.66666667
B17: Market Beta Wight | C17: 0.33333333
A19: # | B19: Sheet : WACC
B21: Risk Free Rate | C21: 0.0677
B22: Premium for Credit Spread (Crisil AAA/Stable/Crisil A1+) | C22: 0.005
B23: Implied ERP | C23: 0.0416
B24: Rm | C24: =C21+C23 -> 0.1093
B25: Levered Beta | C25: 0.89703267 | D25: ='Comps Beta Calculation'!H10 -> 0.89703267 | E25: =WACC!J18 -> 0.95378513
A27: # | B27: Sheet : DCF
B29: No of Years of Forecast | C29: 5
B30: Reinvestment Rate | C30: 0.1818709
B31: Start Growth Rate | C31: 0.13788625
B32: WACC | C32: =WACC!E28 -> 0.10467199
B33: Terminal Growth Rate | C33: 0.025
B34: Target Terminal ROIC | C34: 0.25
B35: Implied Terminal Reinvestment Rate | C35: =C33/C34 -> 0.1
B36: Mid Year Convention | C36: 0.5
A38: # | B38: Sheet : Altman's Z score Analysis | C38: Weight
B39: Working Capital / Total Asset (A) | C39: 1.2
B40: Retained Earnings / Total Asset (B) | C40: 1.4
B41: EBIT / Total Asset (C) | C41: 3.3
B42: Market Cap. / Total Liabilities (D) | C42: 0.6
B43: Sales / Total Asset (E) | C43: 1
A45: # | B45: Sheet : SOTP - Segment
B46: Unallocated Corporate Expenses (Net), FY2026 — Annual Report Note 30 | C46: 1228.83
B47: WACC | C47: =C32 -> 0.10467199

Sheet Data Sheet
A1: COMPANY NAME | B1: ITC LTD | E1: =IF(B2<>B3, "A NEW VERSION OF THE WORKSHEET IS AVAILABLE", "")
A2: LATEST VERSION | B2: 2.1 | E2: PLEASE DO NOT MAKE ANY CHANGES TO THIS SHEET
A3: CURRENT VERSION | B3: 2.1
A5: META
A6: Number of shares | B6: =IF(B9>0, B9/B8, 0) -> 1252.9468
A7: Face Value | B7: 1
A8: Current Price | B8: 276.65
A9: Market Capitalization | B9: 346627.74
A15: PROFIT & LOSS
A16: Report Date | B16: 42825 | C16: 43190 | D16: 43555 | E16: 43921 | F16: 44286 | G16: 44651 | H16: 45016 | I16: 45382 | J16: 45747 | K16: 46112
A17: Sales | B17: 42767.6 | C17: 43448.94 | D17: 48339.58 | E17: 49387.7 | F17: 49257.45 | G17: 60644.54 | H17: 70919.03 | I17: 67931.94 | J17: 75323.34 | K17: 78868.4
A18: Raw Material Cost | B18: 15456.59 | C18: 14827.72 | D18: 17623.52 | E18: 18048.6 | F18: 20776.71 | G18: 27071.07 | H18: 29364.36 | I18: 27348.57 | J18: 32704.37 | K18: 35098.34
A19: Change in Inventory | B19: -592.57 | C19: -1027.76 | D19: 203.19 | E19: 703.13 | F19: 645.27 | G19: 686 | H19: 358.59 | I19: 367.77 | J19: 725.65 | K19: 2550.46
A20: Power and Fuel | B20: 584.33 | C20: 653.5 | D20: 746.73 | E20: 780.85 | F20: 699.56 | G20: 889.77 | H20: 1232.34 | I20: 952.9 | J20: 975.35 | K20: 947.71
A21: Other Mfr. Exp | B21: 1683.9 | C21: 1697.62 | D21: 1871.01 | E21: 1908.29 | F21: 1587.18 | G21: 1887.67 | H21: 2327.8 | I21: 2183.76 | J21: 2345.36 | K21: 2582.48
A22: Employee Cost | B22: 3631.73 | C22: 3760.9 | D22: 4177.88 | E22: 4295.79 | F22: 4463.33 | G22: 4890.55 | H22: 5736.22 | I22: 5548.53 | J22: 6169.78 | K22: 6781.5
A23: Selling and admin | B23: 4179.74 | C23: 3954.87 | D23: 4546.39 | E23: 4488.63 | F23: 4236.77 | G23: 4858.38 | H23: 5604.08 | I23: 5312.45 | J23: 5793.29 | K23: 6377.95
A24: Other Expenses | B24: 1169.23 | C24: 1005.98 | D24: 1039.85 | E24: 1225.13 | F24: 1074.39 | G24: 1109.95 | H24: 1308.56 | I24: 1765.97 | J24: 2229.26 | K24: 2324.88
A25: Other Income | B25: 1758.63 | C25: 2239.81 | D25: 2080.44 | E25: 2417.32 | F25: 2576.95 | G25: 1909.72 | H25: 2097.64 | I25: 3330.45 | J25: 17802.75 | K25: 2523.09
A26: Depreciation | B26: 1152.79 | C26: 1236.28 | D26: 1396.61 | E26: 1644.91 | F26: 1645.59 | G26: 1732.41 | H26: 1809.01 | I26: 1518.05 | J26: 1646.32 | K26: 1710.53
A27: Interest | B27: 49.03 | C27: 115.01 | D27: 71.4 | E27: 81.38 | F27: 57.97 | G27: 59.99 | H27: 77.77 | I27: 39.11 | J27: 45.06 | K27: 85.17
... A31: Dividend Amount | B31: 5770.02 | C31: 6285.21 | D31: 7048.7 | E31: 12476.58 | F31: 13231.96 | G31: 14171.8 | H31: 19263.4 | I31: 17166.46 | J31: 17957.73 | K31: 18167.78
A40: Quarters
A41: Report Date | B41: 45291 | C41: 45382 | D41: 45473 | E41: 45565 | F41: 45657 | G41: 45747 | H41: 45838 | I41: 45930 | J41: 46022 | K41: 46112
A42: Sales | B42: 17195.24 | C42: 17037.8 | D42: 17777.81 | E42: 19990.36 | F42: 18790.17 | G42: 18765 | H42: 21494.79 | I42: 19501.63 | J42: 20047.3 | K42: 17824.68
A43: Expenses | B43: 10985.01 | C43: 10735.73 | D43: 11232.97 | E43: 13438.28 | F43: 12428.27 | G43: 12245.61 | H43: 14678.32 | I43: 12806.94 | J43: 13164.78 | K43: 10900.45
A44: Other Income | B44: 820.26 | C44: 868 | D44: 771.13 | E44: 690.31 | F44: 803.4 | G44: 15391.28 | H44: 750.97 | I44: 738.84 | J44: 321.85 | K44: 699.52
A45: Depreciation | B45: 384.04 | C45: 385.09 | D45: 403.13 | E45: 416.18 | F45: 415.98 | G45: 411.03 | H45: 422.96 | I45: 434.8 | J45: 430.82 | K45: 421.95
A46: Interest | B46: 11.94 | C46: 10.72 | D46: 9.6 | E46: 14.73 | F46: 9.82 | G46: 10.91 | H46: 16.47 | I46: 20.05 | J46: 19.47 | K46: 29.18
A47: Profit before tax | B47: 6634.51 | C47: 6774.26 | D47: 6903.24 | E47: 6811.48 | F47: 6739.5 | G47: 21488.73 | H47: 7128.01 | I47: 6978.68 | J47: 6754.08 | K47: 7172.62
A48: Tax | B48: 1227.99 | C48: 1583.55 | D48: 1726.25 | E48: 1757.05 | F48: 1726.32 | G48: 1680.85 | H48: 1784.6 | I48: 1792.13 | J48: 1735.63 | K48: 1702.88
A49: Net profit | B49: 5335.23 | C49: 5120.55 | D49: 5091.59 | E49: 4992.87 | F49: 4934.8 | G49: 19727.37 | H49: 5244.2 | I49: 5126.11 | J49: 4931.19 | K49: 5387.97
A50: Operating Profit | B50: 6210.23 | C50: 6302.07 | D50: 6544.84 | E50: 6552.08 | F50: 6361.9 | G50: 6519.39 | H50: 6816.47 | I50: 6694.69 | J50: 6882.52 | K50: 6924.23
A55: BALANCE SHEET
A56: Report Date | B56: 42825 | C56: 43190 | D56: 43555 | E56: 43921 | F56: 44286 | G56: 44651 | H56: 45016 | I56: 45382 | J56: 45747 | K56: 46112
A57: Equity Share Capital | B57: 1214.74 | C57: 1220.43 | D57: 1225.86 | E57: 1229.22 | F57: 1230.88 | G57: 1232.33 | H57: 1242.8 | I57: 1248.47 | J57: 1251.41 | K57: 1252.95
A58: Reserves | B58: 45198.19 | C58: 51289.68 | D58: 57915.01 | E58: 64044.04 | F58: 59116.46 | G58: 61223.24 | H58: 67912.46 | I58: 73258.53 | J58: 68778.64 | K58: 71254.35
A59: Borrowings | B59: 45.72 | C59: 35.92 | D59: 13.44 | E59: 277.45 | F59: 270.83 | G59: 249.44 | H59: 306.04 | I59: 303.43 | J59: 284.54 | K59: 2399.06
A60: Other Liabilities | B60: 9439.67 | C60: 11694.85 | D60: 12584.73 | E60: 11760.04 | F60: 13142.59 | G60: 14491.01 | H60: 16369.66 | I60: 16943.54 | J60: 17688.11 | K60: 18730.84
A61: Total | B61: 55898.32 | C61: 64240.88 | D61: 71739.04 | E61: 77310.75 | F61: 73760.76 | G61: 77196.02 | H61: 85830.96 | I61: 91753.97 | J61: 88002.7 | K61: 93637.2
A62: Net Block | B62: 15893.48 | C62: 16523.96 | D62: 19374.19 | E62: 21713.34 | F62: 23298.48 | G62: 24231.59 | H62: 25851.27 | I62: 27820.22 | J62: 21954.85 | K62: 22442.53
A63: Capital Work in Progress | B63: 3729.89 | C63: 5508.33 | D63: 4136.42 | E63: 3256.46 | F63: 4011.29 | G63: 3225.54 | H63: 3003.3 | I63: 2860.78 | J63: 1090.91 | K63: 1601.88
A64: Investments | B64: 17581.38 | C64: 22052.86 | D64: 25043.49 | E64: 28663.35 | F64: 24870.87 | G64: 24841.01 | H64: 29415.02 | I64: 31114.02 | J64: 34719.82 | K64: 38128.43
A65: Other Assets | B65: 18693.57 | C65: 20155.73 | D65: 23184.94 | E65: 23677.6 | F65: 21580.12 | G65: 24897.88 | H65: 27561.37 | I65: 29958.95 | J65: 30237.12 | K65: 31464.36
A66: Total | B66: 55898.32 | C66: 64240.88 | D66: 71739.04 | E66: 77310.75 | F66: 73760.76 | G66: 77196.02 | H66: 85830.96 | I66: 91753.97 | J66: 88002.7 | K66: 93637.2
A67: Receivables | B67: 2474.29 | C67: 2682.29 | D67: 4035.28 | E67: 2562.48 | F67: 2501.7 | G67: 2461.9 | H67: 2956.17 | I67: 4025.82 | J67: 4719.67 | K67: 3922.86
... A70: No. of Equity Shares | B70: 12147383071 | C70: 12204294911 | D70: 12258631601 | E70: 12292231241 | F70: 12308844231 | G70: 12323255931 | H70: 12428017741 | I70: 12484700000 | J70: 12514119781 | K70: 12529468231
A71: New Bonus Shares | B71: 4026657100
A72: Face value | B72: 1 | C72: 1 | D72: 1 | E72: 1 | F72: 1 | G72: 1 | H72: 1 | I72: 1 | J72: 1 | K72: 1
A80: CASH FLOW:
A81: Report Date | B81: 42825 | C81: 43190 | D81: 43555 | E81: 43921 | F81: 44286 | G81: 44651 | H81: 45016 | I81: 45382 | J81: 45747 | K81: 46112
A82: Cash from Operating Activity | B82: 10627.31 | C82: 13169.4 | D82: 12583.41 | E82: 14689.66 | F82: 12526.97 | G82: 15775.51 | H82: 18877.55 | I82: 17178.86 | J82: 17627.04 | K82: 18464.31
A83: Cash from Investing Activity | B83: -3250.93 | C83: -7113.89 | D83: -5545.68 | E83: -6174.02 | F83: 5739.98 | G83: -2238.49 | H83: -5732.29 | I83: 1562.77 | J83: -563.84 | K83: -2320.74
A84: Cash from Financing Activity | B84: -7301.03 | C84: -6221.13 | D84: -6868.64 | E84: -8181.48 | F84: -18633.83 | G84: -13580.5 | H84: -13006.03 | I84: -18550.96 | J84: -17037.4 | K84: -16147.12
A85: Net Cash Flow | B85: 75.35 | C85: -165.62 | D85: 169.09 | E85: 334.16 | F85: -366.88 | G85: -43.48 | H85: 139.23 | I85: 190.67 | J85: 25.8 | K85: -3.55
A90: PRICE: | B90: 262.75 | C90: 239.5 | D90: 278.64 | E90: 160.95 | F90: 204.82 | G90: 234.96 | H90: 359.49 | I90: 401.53 | J90: 409.75 | K90: 287.7
A92: DERIVED:
A93: Adjusted Equity Shares in Cr | B93: 1214.74 | C93: 1220.43 | D93: 1225.86 | E93: 1229.22 | F93: 1230.88 | G93: 1232.33 | H93: 1242.8 | I93: 1248.47 | J93: 1251.41 | K93: 1252.95

Sheet Comps Data
B2: S.No. | C2: Name | D2: SOTP Segment Tag | E2: CMP Rs. | F2: No. Eq. Shares Cr. | G2: Mar Cap Rs.Cr. | H2: Debt Rs.Cr. | I2: Cash End Rs.Cr. | J2: Net Debt | K2: EV Rs.Cr. | L2: NP 12M Rs.Cr. | M2: Sales Rs.Cr. | N2: P/E | O2: EBITDA | P2: EV / EBITDA | Q2: EV / Sales | R2: EBIT | S2: Interest | T2: EBT | U2: Tax Amount | V2: Tax percent
B3: 2 | C3: ITC | E3: 279.35 | F3: 1252.95 | G3: =E3*F3 -> 350011.58 | H3: 2399.06 | I3: 3008.79 | J3: =H3-I3 -> -609.73 | K3: =G3+J3 -> 349401.85 | L3: 21018.15 | M3: 78868.4 | N3: =G3/L3 -> 16.652825 | O3: 30108.95 | P3: =K3/O3 -> 11.604584 | Q3: =K3/M3 -> 4.4301882 | R3: 28398.42 | S3: 85.17 | T3: =R3-S3 -> 28313.25 | U3: 7015.24 | V3: =U3/T3 -> 0.24777233
B5: 1 | C5: Hind. Unilever | D5: FMCG-Others | E5: 2098.4 | F5: 234.96 | G5: =E5*F5 -> 493040.06 | H5: 1478 | I5: 3248 | J5: =H5-I5 -> -1770 | K5: =G5+J5 -> 491270.06 | L5: 15059 | M5: 64468 | N5: =G5/L5 -> 32.740558 | O5: 15790 | P5: =K5/O5 -> 31.112734 | Q5: =K5/M5 -> 7.6203708 | R5: 14457 | S5: 410 | T5: =R5-S5 -> 14047 | U5: 3160 | V5: =U5/T5 -> 0.22495907
B6: 3 | C6: Nestle India | D6: FMCG-Others | E6: 1423.5 | F6: 192.83 | G6: =E6*F6 -> 274493.51 | H6: 444.16 | I6: 1340.87 | J6: =H6-I6 -> -896.71 | K6: =G6+J6 -> 273596.79 | L6: 3544.6 | M6: 23154.6 | N6: =G6/L6 -> 77.43991 | O6: 5342.42 | P6: =K6/O6 -> 51.212146 | Q6: =K6/M6 -> 11.816088 | R6: 4643.19 | S6: 158.31 | T6: =R6-S6 -> 4484.88 | U6: 1065.05 | V6: =U6/T6 -> 0.2374757
B7: 4 | C7: Varun Beverages | D7: Not used | E7: 466.55 | F7: 338.25 | G7: =E7*F7 -> 157810.54 | H7: 2508.18 | I7: 1998.49 | J7: =H7-I7 -> 509.69 | K7: =G7+J7 -> 158320.23 | L7: 3209.4 | M7: 22692.63 | N7: =G7/L7 -> 49.171352 | O7: 5672.75 | P7: =K7/O7 -> 27.908903 | Q7: =K7/M7 -> 6.9767245 | R7: 4372.01 | S7: 195.98 | T7: =R7-S7 -> 4176.03 | U7: 985.63 | V7: =U7/T7 -> 0.23602081
B8: 5 | C8: Britannia Inds. | D8: FMCG-Others | E8: 5310.5 | F8: 24.09 | G8: =E8*F8 -> 127929.94 | H8: 1380.28 | I8: 352.44 | J8: =H8-I8 -> 1027.84 | K8: =G8+J8 -> 128957.78 | L8: 2537.01 | M8: 19151.59 | N8: =G8/L8 -> 50.425479 | O8: 3738.37 | P8: =K8/O8 -> 34.495725 | Q8: =K8/M8 -> 6.7335289 | R8: 3401.54 | S8: 112.76 | T8: =R8-S8 -> 3288.78 | U8: 751.77 | V8: =U8/T8 -> 0.22858628
B9: 6 | C9: Marico | D9: FMCG-Others | E9: 839.35 | F9: 129.84 | G9: =E9*F9 -> 108981.2 | H9: 557 | I9: 493 | J9: =H9-I9 -> 64 | K9: =G9+J9 -> 109045.2 | L9: 1813 | M9: 13611 | N9: =G9/L9 -> 60.110978 | O9: 2524 | P9: =K9/O9 -> 43.20333 | Q9: =K9/M9 -> 8.0115498 | R9: 2322 | S9: 53 | T9: =R9-S9 -> 2269 | U9: 464 | V9: =U9/T9 -> 0.20449537
B10: 7 | C10: Godrej Consumer | D10: FMCG-Others | E10: 1057.7 | F10: 102.33 | G10: =E10*F10 -> 108234.44 | H10: 4415.81 | I10: 1005.41 | J10: =H10-I10 -> 3410.4 | K10: =G10+J10 -> 111644.84 | L10: 1861.47 | M10: 15177.9 | N10: =G10/L10 -> 58.144607 | O10: 3422.41 | P10: =K10/O10 -> 32.621703 | Q10: =K10/M10 -> 7.3557502 | R10: 3154.88 | S10: 331.57 | T10: =R10-S10 -> 2823.31 | U10: 728.69 | V10: =U10/T10 -> 0.25809776
B11: 8 | C11: Tata Consumer | D11: Not used | E11: 1088.5 | F11: 98.97 | G11: =E11*F11 -> 107728.85 | H11: 2819.51 | I11: 3420.49 | J11: =H11-I11 -> -600.98 | K11: =G11+J11 -> 107127.87 | L11: 1546.8 | M11: 20290.43 | N11: =G11/L11 -> 69.646266 | O11: 2928 | P11: =K11/O11 -> 36.587386 | Q11: =K11/M11 -> 5.2797237 | R11: 2301.32 | S11: 137.03 | T11: =R11-S11 -> 2164.29 | U11: 535.28 | V11: =U11/T11 -> 0.2473236
B12: 9 | C12: United Spirits | D12: Not used | E12: 1381.6 | F12: 72.74 | G12: =E12*F12 -> 100497.58 | H12: 413 | I12: 1977 | J12: =H12-I12 -> -1564 | K12: =G12+J12 -> 98933.584 | L12: 1838 | M12: 12467 | N12: =G12/L12 -> 54.677684 | O12: 2658 | P12: =K12/O12 -> 37.221062 | Q12: =K12/M12 -> 7.9356368 | R12: 2369 | S12: 158 | T12: =R12-S12 -> 2211 | U12: 510 | V12: =U12/T12 -> 0.23066486
B13: 10 | C13: Dabur India | D13: FMCG-Others | E13: 429.45 | F13: 177.4 | G13: =E13*F13 -> 76184.43 | H13: 1287.32 | I13: 562.07 | J13: =H13-I13 -> 725.25 | K13: =G13+J13 -> 76909.68 | L13: 1868.69 | M13: 13192.57 | N13: =G13/L13 -> 40.768897 | O13: 3029.23 | P13: =K13/O13 -> 25.389185 | Q13: =K13/M13 -> 5.8297724 | R13: 2560.3 | S13: 145.4 | T13: =R13-S13 -> 2414.9 | U13: 551.74 | V13: =U13/T13 -> 0.22847323
B14: 11 | C14: Radico Khaitan | D14: Not used | E14: 4106 | F14: 13.4 | G14: =E14*F14 -> 55020.4 | H14: 498.45 | I14: 88.33 | J14: =H14-I14 -> 410.12 | K14: =G14+J14 -> 55430.52 | L14: 604.48 | M14: 6037.07 | N14: =G14/L14 -> 91.021043 | O14: 1036.59 | P14: =K14/O14 -> 53.47391 | Q14: =K14/M14 -> 9.1816924 | R14: 883.57 | S14: 64.53 | T14: =R14-S14 -> 819.04 | U14: 200.76 | V14: =U14/T14 -> 0.24511623
B15: 12 | C15: Colgate-Palmoliv | D15: FMCG-Others | E15: 2001.1 | F15: 27.2 | G15: =E15*F15 -> 54429.92 | H15: 47.41 | I15: 1468.82 | J15: =H15-I15 -> -1421.41 | K15: =G15+J15 -> 53008.51 | L15: 1325.31 | M15: 6035.04 | N15: =G15/L15 -> 41.069576 | O15: 1959.03 | P15: =K15/O15 -> 27.058549 | Q15: =K15/M15 -> 8.7834563 | R15: 1812.97 | S15: 3.79 | T15: =R15-S15 -> 1809.18 | U15: 458.65 | V15: =U15/T15 -> 0.25351264
B16: 13 | C16: Patanjali Foods | D16: Not used | E16: 347.25 | F16: 108.81 | G16: =E16*F16 -> 37784.272 | H16: 2788.83 | I16: 746.36 | J16: =H16-I16 -> 2042.47 | K16: =G16+J16 -> 39826.743 | L16: 1814.87 | M16: 40169.58 | N16: =G16/L16 -> 20.819272 | O16: 1931.52 | P16: =K16/O16 -> 20.619379 | Q16: =K16/M16 -> 0.99146525 | R16: 1683.12 | S16: 130.18 | T16: =R16-S16 -> 1552.94 | U16: -460.94 | V16: =U16/T16 -> -0.29681765
... B21: 18 | C21: Seshasayee Paper | D21: Paperboards | E21: 246.27 | F21: 6.31 | G21: =E21*F21 -> 1553.9637 | H21: 0 | I21: 146.07 | J21: =H21-I21 -> -146.07 | K21: =G21+J21 -> 1407.8937 | L21: 99.01 | M21: 1817.12 | N21: =G21/L21 -> 15.695018 | O21: 181.61 | P21: =K21/O21 -> 7.7522917 | Q21: =K21/M21 -> 0.77479401 | R21: 136.53 | S21: 8.76 | T21: =R21-S21 -> 127.77 | U21: 29.42 | V21: =U21/T21 -> 0.23025749
B22: 19 | C22: AWL Agri Business Ltd | D22: Agri Business | E22: 184.34 | F22: 129.97 | G22: =E22*F22 -> 23958.67 | H22: 1109.27 | I22: 1719.31 | J22: =H22-I22 -> -610.04 | K22: =G22+J22 -> 23348.63 | L22: 1158.33 | M22: 77720.16 | N22: 20.4 | O22: 2782.05 | P22: =K22/O22 -> 8.3925989 | Q22: =K22/M22 -> 0.30041922 | R22: 2319 | S22: 706.91 | T22: =R22-S22 -> 1612.09 | U22: 424.86 | V22: =U22/T22 -> 0.26354608

Sheet SOTP - Segment Data
B2: Segment | C2: External Rev | D2: Internal Rev | E2: Total Rev | F2: EBIT | G2: D&A | H2: EBITDA
B3: FMCG – Cigarettes | C3: 37099.65 | D3: 0 | E3: 37099.65 | F3: 21051.12 | G3: 264.06 | H3: =F3+G3 -> 21315.18
B4: FMCG – Others | C4: 24203.75 | D4: 6 | E4: 24209.75 | F4: 1802.63 | G4: 609.31 | H4: =F4+G4 -> 2411.94
B5: Agri Business | C5: 12296.48 | D5: 7999.92 | E5: 20296.4 | F5: 1496.46 | G5: 72.86 | H5: =F5+G5 -> 1569.32
B6: Paperboards & Packaging | C6: 6926.57 | D6: 1839.04 | E6: 8765.61 | F6: 796.71 | G6: 390.39 | H6: =F6+G6 -> 1187.1
B7: Others | C7: 341.04 | D7: 0.75 | E7: 341.79 | F7: -8.06 | G7: 9.53 | H7: =F7+G7 -> 1.47
C9: =SUM(C3:C7) -> 80867.49 | D9: =SUM(D3:D7) -> 9845.71 | E9: =SUM(E3:E7) -> 90713.2 | F9: =SUM(F3:F7) -> 25138.86 | G9: =SUM(G3:G7) -> 1346.15 | H9: =F9+G9 -> 26485.01

Sheet Raw Fs
B2: ="Balance Sheet"&" - "&'Data Sheet'!B1 -> Balance Sheet - ITC LTD
B3: Particulars | C3: 42064 | D3: 42430 | E3: 42795 | F3: 43160 | G3: 43525 | H3: 43891 | I3: 44256 | J3: 44621 | K3: 44986 | L3: 45352 | M3: 45717 | N3: 46082
B5: Equity Capital | C5: 802 | D5: 805 | E5: 1215 | F5: 1220 | G5: 1226 | H5: 1229 | I5: 1231 | J5: 1232 | K5: 1243 | L5: 1248 | M5: 1251 | N5: 1253
B6: Reserves | C6: 30934 | D6: 41875 | E6: 45198 | F6: 51290 | G6: 57915 | H6: 64044 | I6: 59116 | J6: 61223 | K6: 67912 | L6: 73259 | M6: 68779 | N6: 71254
B7: Borrowings -
B8: Long term Borrowings | C8: 61 | D8: 27 | E8: 18 | F8: 12 | G8: 8 | H8: 6 | I8: 6 | J8: 5 | K8: 3 | L8: 2 | M8: 0 | N8: 60
B9: Short term Borrowings | C9: 195 | D9: 44 | E9: 19 | F9: 17 | G9: 2 | H9: 1 | I9: 4 | J9: 1 | K9: 35 | L9: 10 | M9: 91 | N9: 2126
B10: Lease Liabilities | C10: 0 | D10: 0 | E10: 0 | F10: 0 | G10: 0 | H10: 268 | I10: 261 | J10: 244 | K10: 267 | L10: 292 | M10: 193 | N10: 213
B11: Other Borrowings | C11: 13 | D11: 13 | E11: 8 | F11: 7 | G11: 3 | H11: 2 | I11: 0 | J11: 0 | K11: 0 | L11: 0 | M11: 0 | N11: 0
B12: Other Liabilities -
B13: Non controlling int | C13: 225 | D13: 261 | E13: 295 | F13: 334 | G13: 343 | H13: 377 | I13: 347 | J13: 366 | K13: 384 | L13: 383 | M13: 368 | N13: 366
B14: Trade Payables | C14: 2020 | D14: 2339 | E14: 2659 | F14: 3496 | G14: 3510 | H14: 3630 | I14: 4319 | J14: 4417 | K14: 4659 | L14: 4798 | M14: 4807 | N14: 5640
B15: Advance from Customers | C15: 0 | D15: 805 | E15: 495 | F15: 461 | G15: 430 | H15: 703 | I15: 811 | J15: 1278 | K15: 1295 | L15: 886 | M15: 1264 | N15: 1342
B16: Other liability items | C16: 11702 | D16: 5483 | E16: 5991 | F16: 7404 | G16: 8301 | H16: 7050 | I16: 7666 | J16: 8429 | K16: 10032 | L16: 10877 | M16: 11249 | N16: 11384
B18: Total Liabilities | C18: 45952 | D18: 51651 | E18: 55898 | F18: 64241 | G18: 71739 | H18: 77311 | I18: 73761 | J18: 77196 | K18: 85831 | L18: 91754 | M18: 88003 | N18: 93637
B20: Fixed Assets -
B21: Land | C21: 1717 | D21: 1615 | E21: 1673 | F21: 1685 | G21: 2021 | H21: 2797 | I21: 2889 | J21: 2829 | K21: 2830 | L21: 2865 | M21: 1588 | N21: 1633
B22: Building | C22: 4860 | D22: 4219 | E22: 4716 | F22: 5331 | G22: 6996 | H22: 8161 | I22: 8387 | J22: 9100 | K22: 9789 | L22: 10944 | M22: 7550 | N22: 7791
B23: Plant Machinery | C23: 14667 | D23: 9112 | E23: 10384 | F23: 11453 | G23: 13316 | H23: 14625 | I23: 15307 | J23: 16912 | K23: 18480 | L23: 20718 | M23: 19423 | N23: 20424
B24: Equipment | C24: 46 | D24: 27 | E24: 32 | F24: 32 | G24: 34 | H24: 40 | I24: 41 | J24: 44 | K24: 44 | L24: 53 | M24: 63 | N24: 75
B25: Furniture n fittings | C25: 805 | D25: 413 | E25: 459 | F25: 497 | G25: 644 | H25: 810 | I25: 833 | J25: 907 | K25: 1000 | L25: 1068 | M25: 282 | N25: 304
B26: Railway sidings | C26: 2 | D26: 2 | E26: 2 | F26: 2 | G26: 2 | H26: 2 | I26: 2 | J26: 2 | K26: 2 | L26: 2 | M26: 2 | N26: 2
B27: Vehicles | C27: 128 | D27: 107 | E27: 128 | F27: 140 | G27: 161 | H27: 184 | I27: 180 | J27: 179 | K27: 189 | L27: 192 | M27: 141 | N27: 155
B28: Intangible Assets | C28: 678 | D28: 563 | E28: 563 | F28: 570 | G28: 684 | H28: 684 | I28: 2734 | J28: 2744 | K28: 3490 | L28: 3505 | M28: 3622 | N28: 4248
B29: Other fixed assets | C29: 458 | D29: 117 | E29: 138 | F29: 212 | G29: 234 | H29: 663 | I29: 716 | J29: 719 | K29: 786 | L29: 841 | M29: 967 | N29: 1041
B30: Gross Block | C30: 23361 | D30: 16176 | E30: 18094 | F30: 19920 | G30: 24090 | H30: 27965 | I30: 31088 | J30: 33435 | K30: 36608 | L30: 40189 | M30: 33638 | N30: 35672
B31: Accumulated Depreciation | C31: 8057 | D31: 1069 | E31: 2201 | F31: 3396 | G31: 4716 | H31: 6252 | I31: 7790 | J31: 9204 | K31: 10757 | L31: 12368 | M31: 11683 | N31: 13230
B32: Net Block | C32: =C30-C31 -> 15304 | D32: =D30-D31 -> 15107 | E32: =E30-E31 -> 15893 | F32: =F30-F31 -> 16524 | G32: =G30-G31 -> 19374 | H32: =H30-H31 -> 21713 | I32: =I30-I31 -> 23298 | J32: =J30-J31 -> 24231 | ... N32: =N30-N31 -> 22442
B34: CWIP | C34: 2700 | D34: 2560 | E34: 3730 | F34: 5508 | G34: 4136 | H34: 3256 | I34: 4011 | J34: 3226 | K34: 3003 | L34: 2861 | M34: 1091 | N34: 1602
B35: Investments | C35: 6943 | D35: 11748 | E35: 17581 | F35: 22053 | G35: 25043 | H35: 28663 | I35: 24871 | J35: 24841 | K35: 29415 | L35: 31114 | M35: 34720 | N35: 38128
B37: Other Assets -
B38: Inventories | C38: 8587 | D38: 9062 | E38: 8116 | F38: 7495 | G38: 7860 | H38: 8879 | I38: 10397 | J38: 10864 | K38: 11771 | L38: 14153 | M38: 15638 | N38: 18623
B40: Trade receivables -
B41: Receivables over 6m | C41: 118 | D41: 0 | E41: 0 | F41: 0 | G41: 0 | H41: 0 | I41: 0 | J41: 0 | K41: 0 | L41: 184 | M41: 256 | N41: 363
B42: Receivables under 6m | C42: 1938 | D42: 2013 | E42: 2595 | F42: 2816 | G42: 4188 | H42: 2737 | I42: 2696 | J42: 2659 | K42: 3154 | L42: 4030 | M42: 4640 | N42: 3749
B43: Prov for Doubtful | C43: -74 | D43: -96 | E43: -121 | F43: -134 | G43: -153 | H43: -175 | I43: -195 | J43: -197 | K43: -198 | L43: -188 | M43: -176 | N43: -189
B45: Cash Equivalents | C45: 7896 | D45: 6063 | E45: 2967 | F45: 2900 | G45: 4152 | H45: 7277 | I45: 4659 | J45: 4654 | K45: 4880 | L45: 7218 | M45: 4012 | N45: 3009
B46: Loans n Advances | C46: 150 | D46: 14 | E46: 7 | F46: 74 | G46: 67 | H46: 6 | I46: 7 | J46: 11 | K46: 13 | L46: 31 | M46: 10 | N46: 9
B47: Other asset items | C47: 2391 | D47: 5180 | E47: 5129 | F47: 7004 | G47: 7071 | H47: 4952 | I47: 4015 | J47: 6906 | K47: 7941 | L47: 4531 | M47: 5858 | N47: 5901
B49: Total Assets | C49: 45952 | D49: 51651 | E49: 55898 | F49: 64241 | G49: 71739 | H49: 77311 | I49: 73761 | J49: 77196 | K49: 85831 | L49: 91754 | M49: 88003 | N49: 93637

Sheet Cash Flows
B2: ="Cash Flow Statement of "&'Data Sheet'!B1 -> Cash Flow Statement of ITC LTD
B3: Particulars | C3: 42064 | D3: 42430 | E3: 42795 | F3: 43160 | G3: 43525 | H3: 43891 | I3: 44256 | J3: 44621 | K3: 44986 | L3: 45352 | M3: 45717 | N3: 46082
B4: Cash from Operating Activity - | C4: 9843 | D4: 9799 | E4: 10627 | F4: 13169 | G4: 12583 | H4: 14690 | I4: 12527 | J4: 15776 | K4: 18878 | L4: 17179 | M4: 17627 | N4: 18464
B5: Profit from operations | C5: 14261 | D5: 15154 | E5: 16075 | F5: 17433 | G5: 18862 | H5: 19416 | I5: 17326 | J5: 20857 | K5: 26052 | L5: 26635 | M5: 26719 | N5: 27600
B6: Receivables | C6: 558 | D6: -207 | E6: -870 | F6: -964 | G6: -755 | H6: 1411 | I6: -66 | J6: -732 | K6: -884 | L6: -934 | M6: -1023 | N6: 468
B7: Inventory | C7: -505 | D7: -693 | E7: 593 | F7: 602 | G7: -359 | H7: -508 | I7: -1460 | J7: -466 | K7: -1098 | L7: -2545 | M7: -2975 | N7: -3306
B8: Payables | C8: -23 | D8: 622 | E8: 321 | F8: 2098 | G8: 639 | H8: -607 | I8: 1112 | J8: 1099 | K8: 1058 | L8: 141 | M8: 1256 | N8: 76
B9: Working capital changes | C9: 31 | D9: -277 | E9: 44 | F9: 1736 | G9: -476 | H9: 296 | I9: -413 | J9: -100 | K9: -924 | L9: -3337 | M9: -2742 | N9: -2762
B10: Direct taxes | C10: -4449 | D10: -5078 | E10: -5492 | F10: -6000 | G10: -5803 | H10: -5023 | I10: -4387 | J10: -4982 | K10: -6250 | L10: -6120 | M10: -6350 | N10: -6374
B12: Cash from Investing Activity - | C12: -5275 | D12: -3921 | E12: -3251 | F12: -7114 | G12: -5546 | H12: -6174 | I12: 5740 | J12: -2238 | K12: -5732 | L12: 1563 | M12: -564 | N12: -2321
B13: Fixed assets purchased | C13: -3300 | D13: -2348 | E13: -3122 | F13: -2878 | G13: -3169 | H13: -2441 | I13: -1837 | J13: -2142 | K13: -2743 | L13: -3563 | M13: -2279 | N13: -2183
B14: Fixed assets sold | C14: 9 | D14: 8 | E14: 50 | F14: 80 | G14: 28 | H14: 27 | I14: 3 | J14: 133 | K14: 49 | L14: 107 | M14: 175 | N14: 50
B15: Investments purchased | C15: -98742 | D15: -154081 | E15: -85683 | F15: -98330 | G15: -94187 | H15: -79835 | I15: -57553 | J15: -69776 | K15: -80932 | L15: -75107 | M15: -66373 | N15: -68173
... B33: Net Cash Flow | C33: -93 | D33: 266 | E33: 75 | F33: -166 | G33: 169 | H33: 334 | I33: -367 | J33: -43 | K33: 139 | L33: 191 | M33: 26 | N33: -4

Sheet Daily Adjusted closings
E2: Five Year Monthly Returns | AA2: All Time Dailly Adjusted Closing of ITC VAR | AF2: All Time Dailly Adjusted Closing of ITC Monte Carlo
B3: Nifty Annual Returns | E3: Nifty | I3: ='Data Sheet'!B1 -> ITC LTD | L3: Hindustan Unilever Ltd | O3: Nestle India Ltd | R3: Britannia Industries Ltd | U3: Godrej Consumer Products Limited | X3: Dabur India Ltd | AA3: Date | AB3: Adj Close | AC3: Return | AD3: Sorted Return | AF3: Date | AG3: Adj Close | AH3: Return | AI3: Sorted Return | AJ3: Sorted Return
B4: Year | C4: Annual | I4: ITC | L4: HINDUNILVR | O4: NESTLEIND | R4: BRITANNIA | U4: GODREJCP.NS | X4: DABUR | AA4: Mar 1, 1999 | AB4: 9.48 | AC4: =(AB4/AB5)-1 -> 2.8072289 | AD4: 0.16461916 | AF4: Mar 1, 1999 | AG4: 9.48 | AH4: =(AG4/AG5)-1 -> 2.8072289 | AI4: 0.16461916 | AJ4: =_xlfn.NORM.INV(RAND(),VAR!$F$6,VAR!$F$7) -> -0.0054744278
B5: 2000 | C5: -14.65 | E5: Date | F5: Adj Close | G5: Return | I5: Adj Close | J5: Return | L5: Adj Close | M5: Return | O5: Adj Close | P5: Return | R5: Adj Close | S5: Return | U5: Adj Close | V5: Return | X5: Adj Close | Y5: Return | AA5: Feb 2, 1996 | AB5: 2.49 | AC5: =(AB5/AB6)-1 -> -0.84349466 | AD5: 0.11659193 | AF5: Feb 2, 1996 | AG5: 2.49 | AH5: =(AG5/AG6)-1 -> -0.84349466 | AI5: 0.11659193 | AJ5: =_xlfn.NORM.INV(RAND(),VAR!$F$6,VAR!$F$7) -> 0.022214082
B6: 2001 | C6: -16.18 | E6: Jun 1, 2026 | F6: 23865.75 | G6: =(F6/F7)-1 -> 0.013504475 | I6: 290.7 | J6: =(I6/I7)-1 -> 0.013245033 | L6: 2118.2 | M6: =(L6/L7)-1 -> -0.0063889071 | O6: 1405.2 | P6: =(O6/O7)-1 -> -0.01146676 | R6: 5146.5 | S6: =(R6/R7)-1 -> -0.011144202 | U6: 1010 | V6: =(U6/U7)-1 -> -0.018750607 | X6: 422.2 | Y6: =(X6/X7)-1 -> -0.047812359 | AA6: Jan 20, 2005 | AB6: 15.91 | AC6: =(AB6/AB7)-1 -> -0.58878263 | AD6: 0.11180992 | AF6: Jan 20, 2005 | AG6: 15.91 | AH6: =(AG6/AG7)-1 -> -0.58878263 | AI6: 0.11180992 | AJ6: =_xlfn.NORM.INV(RAND(),VAR!$F$6,VAR!$F$7) -> 0.0056658737
B7: 2002 | C7: 3.25 | E7: May 1, 2026 | F7: 23547.75 | G7: =(F7/F8)-1 -> -0.01874358 | I7: 286.9 | J7: =(I7/I8)-1 -> -0.064100473 | L7: 2131.82 | M7: =(L7/L8)-1 -> -0.04327182 | O7: 1421.5 | P7: =(O7/O8)-1 -> -0.025435349 | R7: 5204.5 | S7: =(R7/R8)-1 -> -0.091075795 | U7: 1029.3 | V7: =(U7/U8)-1 -> -0.03062666 | X7: 443.4 | Y7: =(X7/X8)-1 -> 0.0043035108 | AA7: May 18, 2009 | AB7: 38.69 | AC7: =(AB7/AB8)-1 -> 12.719858 | AD7: 0.11114302 | AF7: May 18, 2009 | AG7: 38.69 | AH7: =(AG7/AG8)-1 -> 12.719858 | AI7: 0.11114302 | AJ7: =_xlfn.NORM.INV(RAND(),VAR!$F$6,VAR!$F$7) -> 0.00059003771
B8: 2003 | C8: 71.9 | E8: Apr 1, 2026 | F8: 23997.55 | G8: =(F8/F9)-1 -> 0.07461019 | I8: 306.55 | J8: =(I8/I9)-1 -> 0.094547792 | L8: 2228.24 | M8: =(L8/L9)-1 -> 0.095221945 | O8: 1458.6 | P8: =(O8/O9)-1 -> 0.24157303 | R8: 5726 | S8: =(R8/R9)-1 -> 0.055873133 | U8: 1061.82 | V8: =(U8/U9)-1 -> 0.083567194 | X8: 441.5 | Y8: =(X8/X9)-1 -> 0.075648678 | AA8: Feb 8, 1996 | AB8: 2.82 | AC8: =(AB8/AB9)-1 -> -0.63984674 | AD8: 0.10588235 | AF8: Feb 8, 1996 | AG8: 2.82 | AH8: =(AG8/AG9)-1 -> -0.63984674 | AI8: 0.10588235 | AJ8: =_xlfn.NORM.INV(RAND(),VAR!$F$6,VAR!$F$7) -> -0.0055381873
B9: 2004 | C9: 10.68 | E9: Mar 1, 2026 | F9: 22331.4 | G9: =(F9/F10)-1 -> -0.11308192 | I9: 280.07 | J9: =(I9/I10)-1 -> -0.082579927 | L9: 2034.51 | M9: =(L9/L10)-1 -> -0.12099492 | O9: 1174.8 | P9: =(O9/O10)-1 -> -0.09050089 | R9: 5423 | S9: =(R9/R10)-1 -> -0.096543107 | U9: 979.93 | V9: =(U9/U10)-1 -> -0.19112986 | X9: 410.45 | Y9: =(X9/X10)-1 -> -0.20838959 | AA9: May 30, 2000 | AB9: 7.83 | AC9: =(AB9/AB10)-1 -> -0.9448475 | AD9: 0.1028169 | AF9: May 30, 2000 | AG9: 7.83 | AH9: =(AG9/AG10)-1 -> -0.9448475 | AI9: 0.1028169 | AJ9: =_xlfn.NORM.INV(RAND(),VAR!$F$6,VAR!$F$7) -> 0.028211091
B10: 2005 | C10: 36.34 | E10: Feb 1, 2026 | F10: 25178.65 | G10: =(F10/F11)-1 -> -0.0056080709 | I10: 305.28 | J10: =(I10/I11)-1 -> -0.0061529446 | L10: 2314.56 | M10: =(L10/L11)-1 -> -0.014707698 | O10: 1291.7 | P10: =(O10/O11)-1 -> -0.025308623 | R10: 6002.5 | S10: =(R10/R11)-1 -> 0.024230015 | U10: 1211.48 | V10: =(U10/U11)-1 -> 0.054937782 | X10: 518.5 | Y10: =(X10/X11)-1 -> 0.023489933 | AA10: Mar 1, 2016 | AB10: 141.97 | AC10: =(AB10/AB11)-1 -> 19.166193 | AD10: 0.10045733 | AF10: Mar 1, 2016 | AG10: 141.97 | AH10: =(AG10/AG11)-1 -> 19.166193 | AI10: 0.10045733 | AJ10: =_xlfn.NORM.INV(RAND(),VAR!$F$6,VAR!$F$7) -> 0.0061721559
B11: 2006 | C11: 39.83 | E11: Jan 1, 2026 | F11: 25320.65 | G11: =(F11/F12)-1 -> -0.030959142 | I11: 307.17 | J11: =(I11/I12)-1 -> -0.20061937 | L11: 2349.11 | M11: =(L11/L12)-1 -> 0.024657809 | O11: 1325.24 | P11: =(O11/O12)-1 -> 0.034470915 | R11: 5860.5 | S11: =(R11/R12)-1 -> -0.028270602 | U11: 1148.39 | V11: =(U11/U12)-1 -> -0.051614928 | X11: 506.6 | Y11: =(X11/X12)-1 -> 0.0059571088 | AA11: Jun 17, 1998 | AB11: 7.04 | AC11: =(AB11/AB12)-1 -> 0.16556291 | AD11: 0.098283931 | AF11: Jun 17, 1998 | AG11: 7.04 | AH11: =(AG11/AG12)-1 -> 0.16556291 | AI11: 0.098283931 | AJ11: =_xlfn.NORM.INV(RAND(),VAR!$F$6,VAR!$F$7) -> 0.017393027
B12: 2007 | C12: 54.77 | E12: Dec 1, 2025 | F12: 26129.6 | G12: =(F12/F13)-1 -> -0.0027993031 | I12: 384.26 | J12: =(I12/I13)-1 -> -0.0030873006 | L12: 2292.58 | M12: =(L12/L13)-1 -> -0.061095276 | O12: 1281.08 | P12: =(O12/O13)-1 -> 0.021326126 | R12: 6031 | S12: =(R12/R13)-1 -> 0.03164557 | U12: 1210.89 | V12: =(U12/U13)-1 -> 0.066863436 | X12: 503.6 | Y12: =(X12/X13)-1 -> -0.026671821 | AA12: Oct 29, 1997 | AB12: 6.04 | AC12: =(AB12/AB13)-1 -> -0.41015625 | AD12: 0.098181818 | AF12: Oct 29, 1997 | AG12: 6.04 | AH12: =(AG12/AG13)-1 -> -0.41015625 | AI12: 0.098181818 | AJ12: =_xlfn.NORM.INV(RAND(),VAR!$F$6,VAR!$F$7) -> -0.0062792298
B13: 2008 | C13: -51.79 | E13: Nov 1, 2025 | F13: 26202.95 | G13: =(F13/F14)-1 -> 0.018694041 | I13: 385.45 | J13: =(I13/I14)-1 -> -0.038298403 | L13: 2441.76 | M13: =(L13/L14)-1 -> 0.0083084191 | O13: 1254.33 | P13: =(O13/O14)-1 -> -0.0082544652 | R13: 5846 | S13: =(R13/R14)-1 -> 0.0016276878 | U13: 1135 | V13: =(U13/U14)-1 -> 0.028629431 | X13: 517.4 | Y13: =(X13/X14)-1 -> 0.06682612 | AA13: May 18, 2004 | AB13: 10.24 | AC13: =(AB13/AB14)-1 -> 0.15185602 | AD13: 0.095187166 | AF13: May 18, 2004 | AG13: 10.24 | AH13: =(AG13/AG14)-1 -> 0.15185602 | AI13: 0.095187166 | AJ13: =_xlfn.NORM.INV(RAND(),VAR!$F$6,VAR!$F$7) -> 0.003657435
B14: 2009 | C14: 75.76 | E14: Oct 1, 2025 | F14: 25722.1 | G14: =(F14/F15)-1 -> 0.045142233 | I14: 400.8 | J14: =(I14/I15)-1 -> 0.046803176 | L14: 2421.64 | M14: =(L14/L15)-1 -> -0.019447942 | O14: 1264.77 | P14: =(O14/O15)-1 -> 0.10295541 | R14: 5836.5 | S14: =(R14/R15)-1 -> -0.025788683 | U14: 1103.41 | V14: =(U14/U15)-1 -> -0.041396626 | X14: 484.99 | Y14: =(X14/X15)-1 -> -0.007632182 | AA14: Sep 12, 2000 | AB14: 8.89 | AC14: =(AB14/AB15)-1 -> -0.70708402 | AD14: 0.090797546 | AF14: Sep 12, 2000 | AG14: 8.89 | AH14: =(AG14/AG15)-1 -> -0.70708402 | AI14: 0.090797546 | AJ14: =_xlfn.NORM.INV(RAND(),VAR!$F$6,VAR!$F$7) -> -0.0080989434
B15: 2010 | C15: 17.95 | E15: Sep 1, 2025 | F15: 24611.1 | G15: =(F15/F16)-1 -> 0.0075429292 | I15: 382.88 | J15: =(I15/I16)-1 -> -0.020015357 | L15: 2469.67 | M15: =(L15/L16)-1 -> -0.054664533 | O15: 1146.71 | P15: =(O15/O16)-1 -> -0.0028521987 | R15: 5991 | S15: =(R15/R16)-1 -> 0.028674451 | U15: 1151.06 | V15: =(U15/U16)-1 -> -0.060918799 | X15: 488.72 | Y15: =(X15/X16)-1 -> -0.057180338 | AA15: Jul 25, 2007 | AB15: 30.35 | AC15: =(AB15/AB16)-1 -> 0.22775081 | AD15: 0.090158046 | AF15: Jul 25, 2007 | AG15: 30.35 | AH15: =(AG15/AG16)-1 -> 0.22775081 | AI15: 0.090158046 | AJ15: =_xlfn.NORM.INV(RAND(),VAR!$F$6,VAR!$F$7) -> -0.0030891977
B16: 2011 | C16: -24.62 | E16: Aug 1, 2025 | F16: 24426.85 | G16: =(F16/F17)-1 -> -0.013787757 | I16: 390.7 | J16: =(I16/I17)-1 -> -0.0053209094 | L16: 2612.48 | M16: =(L16/L17)-1 -> 0.054972035 | O16: 1149.99 | P16: =(O16/O17)-1 -> 0.028788435 | R16: 5824 | S16: =(R16/R17)-1 -> 0.022409087 | U16: 1225.73 | V16: =(U16/U17)-1 -> -0.0089024371 | X16: 518.36 | Y16: =(X16/X17)-1 -> -0.014936718 | AA16: Sep 21, 2005 | AB16: 24.72 | AC16: =(AB16/AB17)-1 -> -0.35775526 | AD16: 0.08994709 | AF16: Sep 21, 2005 | AG16: 24.72 | AH16: =(AG16/AG17)-1 -> -0.35775526 | AI16: 0.08994709 | AJ16: =_xlfn.NORM.INV(RAND(),VAR!$F$6,VAR!$F$7) -> 0.024112816
B17: 2012 | C17: 27.7 | E17: Jul 1, 2025 | F17: 24768.35 | G17: =(F17/F18)-1 -> -0.029341166 | I17: 392.79 | J17: =(I17/I18)-1 -> -0.010803868 | L17: 2476.35 | M17: =(L17/L18)-1 -> 0.098754093 | O17: 1117.81 | P17: =(O17/O18)-1 -> -0.08443771 | R17: 5696.35 | S17: =(R17/R18)-1 -> -0.013671993 | U17: 1236.74 | V17: =(U17/U18)-1 -> 0.068402502 | X17: 526.22 | Y17: =(X17/X18)-1 -> 0.10108598 | AA17: May 4, 2009 | AB17: 38.49 | AC17: =(AB17/AB18)-1 -> 0.36007067 | AD17: 0.089750849 | AF17: May 4, 2009 | AG17: 38.49 | AH17: =(AG17/AG18)-1 -> 0.36007067 | AI17: 0.089750849 | AJ17: =_xlfn.NORM.INV(RAND(),VAR!$F$6,VAR!$F$7) -> -0.003750712
... B30: 2025 | C30: 10.51 | E30: Jun 1, 2024 | F30: 24010.6 | G30: =(F30/F31)-1 -> 0.065683712 | I30: 377.11 | J30: =(I30/I31)-1 -> 0.014745849 | L30: 2376.13 | M30: =(L30/L31)-1 -> 0.07217374 | O30: 1250.2 | P30: =(O30/O31)-1 -> 0.083550009 | R30: 5335.28 | S30: =(R30/R31)-1 -> 0.057098136 | U30: 1330.6 | V30: =(U30/U31)-1 -> 0.083047771 | X30: 586.06 | Y30: =(X30/X31)-1 -> 0.10201012 | AA30: Feb 10, 2000 | AB30: 9.43 | AC30: =(AB30/AB31)-1 -> 0.24900662 | AD30: 0.080183276 | AF30: Feb 10, 2000 | AG30: 9.43 | AH30: =(AG30/AG31)-1 -> 0.24900662 | AI30: 0.080183276 | AJ30: =_xlfn.NORM.INV(RAND(),VAR!$F$6,VAR!$F$7) -> 0.0031074482
E31: May 1, 2024 | F31: 22530.7 | G31: =(F31/F32)-1 -> -0.0032802695 | I31: 371.63 | J31: =(I31/I32)-1 -> -0.02112472 | L31: 2216.18 | M31: =(L31/L32)-1 -> 0.044205507 | O31: 1153.8 | P31: =(O31/O32)-1 -> -0.060821151 | R31: 5047.1 | S31: =(R31/R32)-1 -> 0.084558192 | U31: 1228.57 | V31: =(U31/U32)-1 -> 0.049539544 | X31: 531.81 | Y31: =(X31/X32)-1 -> 0.073561176 | AA31: Dec 22, 1999 | AB31: 7.55 | AC31: =(AB31/AB32)-1 -> 0.69662921 | AD31: 0.080114449 | AF31: Dec 22, 1999 | AG31: 7.55 | AH31: =(AG31/AG32)-1 -> 0.69662921 | AI31: 0.080114449 | AJ31: =_xlfn.NORM.INV(RAND(),VAR!$F$6,VAR!$F$7) -> 0.0047186762
E32: Apr 1, 2024 | F32: 22604.85 | G32: =(F32/F33)-1 -> 0.012449108 | I32: 379.65 | J32: =(I32/I33)-1 -> 0.017037692 | L32: 2122.36 | M32: =(L32/L33)-1 -> -0.014972478 | O32: 1228.52 | P32: =(O32/O33)-1 -> -0.043834252 | R32: 4653.6 | S32: =(R32/R33)-1 -> -0.027548204 | U32: 1170.58 | V32: =(U32/U33)-1 -> -0.025807472 | X32: 495.37 | Y32: =(X32/X33)-1 -> -0.029447492 | AA32: Feb 28, 1997 | AB32: 4.45 | AC32: =(AB32/AB33)-1 -> -0.61637931 | AD32: 0.080097087 | AF32: Feb 28, 1997 | AG32: 4.45 | AH32: =(AG32/AG33)-1 -> -0.61637931 | AI32: 0.080097087 | AJ32: =_xlfn.NORM.INV(RAND(),VAR!$F$6,VAR!$F$7) -> 0.0073552446
E33: Mar 1, 2024 | F33: 22326.9 | G33: =(F33/F34)-1 -> 0.015653147 | I33: 373.29 | J33: =(I33/I34)-1 -> 0.054283051 | L33: 2154.62 | M33: =(L33/L34)-1 -> -0.061331358 | O33: 1284.84 | P33: =(O33/O34)-1 -> 0.010078458 | R33: 4785.43 | S33: =(R33/R34)-1 -> -0.01086606 | U33: 1201.59 | V33: =(U33/U34)-1 -> -0.0046883413 | X33: 510.4 | Y33: =(X33/X34)-1 -> -0.027865074 | AA33: May 6, 1999 | AB33: 11.6 | AC33: =(AB33/AB34)-1 -> 0.088180113 | AD33: 0.080074488 | AF33: May 6, 1999 | AG33: 11.6 | AH33: =(AG33/AG34)-1 -> 0.088180113 | AI33: 0.080074488 | AJ33: =_xlfn.NORM.INV(RAND(),VAR!$F$6,VAR!$F$7) -> 0.0057861595
E34: Feb 1, 2024 | F34: 21982.8 | G34: =(F34/F35)-1 -> 0.011833911 | I34: 354.07 | J34: =(I34/I35)-1 -> -0.065803013 | L34: 2295.4 | M34: =(L34/L35)-1 -> -0.027904239 | O34: 1272.02 | P34: =(O34/O35)-1 -> 0.038917974 | R34: 4838 | S34: =(R34/R35)-1 -> -0.044860747 | U34: 1207.25 | V34: =(U34/U35)-1 -> 0.080313199 | X34: 525.03 | Y34: =(X34/X35)-1 -> -0.0026973122 | AA34: Feb 15, 2000 | AB34: 10.66 | AC34: =(AB34/AB35)-1 -> 0.064935065 | AD34: 0.080040527 | AF34: Feb 15, 2000 | AG34: 10.66 | AH34: =(AG34/AG35)-1 -> 0.064935065 | AI34: 0.080040527 | AJ34: =_xlfn.NORM.INV(RAND(),VAR!$F$6,VAR!$F$7) -> 0.023961157
E35: Jan 1, 2024 | F35: 21725.7 | G35: =(F35/F36)-1 -> -0.00026229327 | I35: 379.01 | J35: =(I35/I36)-1 -> -0.044472457 | L35: 2361.29 | M35: =(L35/L36)-1 -> -0.068469535 | O35: 1224.37 | P35: =(O35/O36)-1 -> -0.057197859 | R35: 5065.23 | S35: =(R35/R36)-1 -> -0.026233782 | U35: 1117.5 | V35: =(U35/U36)-1 -> 0.029166628 | X35: 526.45 | Y35: =(X35/X36)-1 -> -0.031584563 | AA35: Apr 6, 1999 | AB35: 10.01 | AC35: =(AB35/AB36)-1 -> 0.29663212 | AD35: 0.0798274 | AF35: Apr 6, 1999 | AG35: 10.01 | AH35: =(AG35/AG36)-1 -> 0.29663212 | AI35: 0.0798274 | AJ35: =_xlfn.NORM.INV(RAND(),VAR!$F$6,VAR!$F$7) -> -0.0071822905
E36: Dec 1, 2023 | F36: 21731.4 | G36: =(F36/F37)-1 -> 0.079384001 | I36: 396.65 | J36: =(I36/I37)-1 -> 0.060363034 | L36: 2534.85 | M36: =(L36/L37)-1 -> 0.046511628 | O36: 1298.65 | P36: =(O36/O37)-1 -> 0.096721616 | R36: 5201.69 | S36: =(R36/R37)-1 -> 0.10011146 | U36: 1085.83 | V36: =(U36/U37)-1 -> 0.12200339 | X36: 543.62 | Y36: =(X36/X37)-1 -> 0.035585019 | AA36: Mar 6, 2000 | AB36: 7.72 | AC36: =(AB36/AB37)-1 -> -0.24165029 | AD36: 0.07972028 | AF36: Mar 6, 2000 | AG36: 7.72 | AH36: =(AG36/AG37)-1 -> -0.24165029 | AI36: 0.07972028 | AJ36: =_xlfn.NORM.INV(RAND(),VAR!$F$6,VAR!$F$7) -> 0.021778939
E37: Nov 1, 2023 | F37: 20133.15 | G37: =(F37/F38)-1 -> 0.055218663 | I37: 374.07 | J37: =(I37/I38)-1 -> 0.017268574 | L37: 2422.19 | M37: =(L37/L38)-1 -> 0.032296146 | O37: 1184.12 | P37: =(O37/O38)-1 -> 0.0058612664 | R37: 4728.33 | S37: =(R37/R38)-1 -> 0.096271823 | U37: 967.76 | V37: =(U37/U38)-1 -> 0.021511959 | X37: 524.94 | Y37: =(X37/X38)-1 -> 0.02255727 | AA37: Feb 11, 2000 | AB37: 10.18 | AC37: =(AB37/AB38)-1 -> 0.22650602 | AD37: 0.079533404 | AF37: Feb 11, 2000 | AG37: 10.18 | AH37: =(AG37/AG38)-1 -> 0.22650602 | AI37: 0.079533404 | AJ37: =_xlfn.NORM.INV(RAND(),VAR!$F$6,VAR!$F$7) -> -0.0090482073
E38: Oct 1, 2023 | F38: 19079.6 | G38: =(F38/F39)-1 -> -0.028449509 | I38: 367.72 | J38: =(I38/I39)-1 -> -0.035994233 | L38: 2346.41 | M38: =(L38/L39)-1 -> 0.0074623341 | O38: 1177.22 | P38: =(O38/O39)-1 -> 0.076778136 | R38: 4313.1 | S38: =(R38/R39)-1 -> -0.024388589 | U38: 947.38 | V38: =(U38/U39)-1 -> 0.00025339443 | X38: 513.36 | Y38: =(X38/X39)-1 -> -0.041147575 | AA38: Jan 6, 2000 | AB38: 8.3 | AC38: =(AB38/AB39)-1 -> 0.03362391 | AD38: 0.079323797 | AF38: Jan 6, 2000 | AG38: 8.3 | AH38: =(AG38/AG39)-1 -> 0.03362391 | AI38: 0.079323797 | AJ38: =_xlfn.NORM.INV(RAND(),VAR!$F$6,VAR!$F$7) -> 0.027466436
E39: Sep 1, 2023 | F39: 19638.3 | G39: =(F39/F40)-1 -> 0.019970084 | I39: 381.45 | J39: =(I39/I40)-1 -> 0.01067776 | L39: 2329.03 | M39: =(L39/L40)-1 -> -0.015750328 | O39: 1093.28 | P39: =(O39/O40)-1 -> 0.023670412 | R39: 4420.92 | S39: =(R39/R40)-1 -> 0.015535377 | U39: 947.14 | V39: =(U39/U40)-1 -> -0.013478043 | X39: 535.39 | Y39: =(X39/X40)-1 -> -0.002700991 | AA39: Nov 1, 2001 | AB39: 8.03 | AC39: =(AB39/AB40)-1 -> 0.070666667 | AD39: 0.079301075 | AF39: Nov 1, 2001 | AG39: 8.03 | AH39: =(AG39/AG40)-1 -> 0.070666667 | AI39: 0.079301075 | AJ39: =_xlfn.NORM.INV(RAND(),VAR!$F$6,VAR!$F$7) -> 0.015003879
E40: Aug 1, 2023 | F40: 19253.8 | G40: =(F40/F41)-1 -> -0.025311586 | I40: 377.42 | J40: =(I40/I41)-1 -> -0.055836294 | L40: 2366.3 | M40: =(L40/L41)-1 -> -0.021769686 | O40: 1068 | P40: =(O40/O41)-1 -> -0.025138288 | R40: 4353.29 | S40: =(R40/R41)-1 -> -0.068045488 | U40: 960.08 | V40: =(U40/U41)-1 -> -0.029732188 | X40: 536.84 | Y40: =(X40/X41)-1 -> -0.039092146 | AA40: Jan 3, 2000 | AB40: 7.5 | AC40: =(AB40/AB41)-1 -> 0.27768313 | AD40: 0.079136691 | AF40: Jan 3, 2000 | AG40: 7.5 | AH40: =(AG40/AG41)-1 -> 0.27768313 | AI40: 0.079136691 | AJ40: =_xlfn.NORM.INV(RAND(),VAR!$F$6,VAR!$F$7) -> -0.010285596
E41: Jul 1, 2023 | F41: 19753.8 | G41: =(F41/F42)-1 -> 0.029430847 | I41: 399.74 | J41: =(I41/I42)-1 -> 0.031241132 | L41: 2418.96 | M41: =(L41/L42)-1 -> -0.04381752 | O41: 1095.54 | P41: =(O41/O42)-1 -> -0.014890747 | R41: 4671.14 | S41: =(R41/R42)-1 -> -0.045894159 | U41: 989.5 | V41: =(U41/U42)-1 -> -0.041674334 | X41: 558.68 | Y41: =(X41/X42)-1 -> 0.0093221564 | AA41: Apr 26, 2000 | AB41: 5.87 | AC41: =(AB41/AB42)-1 -> -0.95177456 | AD41: 0.079044118 | AF41: Apr 26, 2000 | AG41: 5.87 | AH41: =(AG41/AG42)-1 -> -0.95177456 | AI41: 0.079044118 | AJ41: =_xlfn.NORM.INV(RAND(),VAR!$F$6,VAR!$F$7) -> 0.0055721383
E42: Jun 1, 2023 | F42: 19189.05 | G42: =(F42/F43)-1 -> 0.035320809 | I42: 387.63 | J42: =(I42/I43)-1 -> 0.013676778 | L42: 2529.81 | M42: =(L42/L43)-1 -> 0.012175019 | O42: 1112.1 | P42: =(O42/O43)-1 -> 0.056346055 | R42: 4895.83 | S42: =(R42/R43)-1 -> 0.078913732 | U42: 1032.53 | V42: =(U42/U43)-1 -> 0.021396775 | X42: 553.52 | Y42: =(X42/X43)-1 -> 0.031608767 | AA42: Mar 31, 2020 | AB42: 121.72 | AC42: =(AB42/AB43)-1 -> 17.358974 | AD42: 0.078504342 | AF42: Mar 31, 2020 | AG42: 121.72 | AH42: =(AG42/AG43)-1 -> 17.358974 | AI42: 0.078504342 | AJ42: =_xlfn.NORM.INV(RAND(),VAR!$F$6,VAR!$F$7) -> -0.014787233
... E64: Aug 1, 2021 | F64: 17132.2 | G64: =(F64/F65)-1 -> 0.086858191 | I64: 166.38 | J64: =(I64/I65)-1 -> 0.030982774 | L64: 2497.82 | M64: =(L64/L65)-1 -> 0.1674893 | O64: 925.3 | P64: =(O64/O65)-1 -> 0.099701691 | R64: 3764.5 | S64: =(R64/R65)-1 -> 0.16769959 | U64: 1050.01 | V64: =(U64/U65)-1 -> 0.11287639 | X64: 592.4 | Y64: =(X64/X65)-1 -> 0.03463332 | AA64: Jul 7, 2009 | AB64: 39.53 | AC64: =(AB64/AB65)-1 -> 6.0213144 | AD64: 0.068378378 | AF64: Jul 7, 2009 | AG64: 39.53 | AH64: =(AG64/AG65)-1 -> 6.0213144 | AI64: 0.068378378 | AJ64: =_xlfn.NORM.INV(RAND(),VAR!$F$6,VAR!$F$7) -> -0.025433206
E65: Jul 1, 2021 | F65: 15763.05 | I65: 161.38 | L65: 2139.48 | O65: 841.41 | R65: 3223.86 | U65: 943.51 | X65: 572.57 | AA65: Aug 1, 1997 | AB65: 5.63 | AC65: =(AB65/AB66)-1 -> -0.96901315 | AD65: 0.068311195 | AF65: Aug 1, 1997 | AG65: 5.63 | AH65: =(AG65/AG66)-1 -> -0.96901315 | AI65: 0.068311195 | AJ65: =_xlfn.NORM.INV(RAND(),VAR!$F$6,VAR!$F$7) -> 0.020828168
AA66: Sep 16, 2021 | AB66: 181.69 | AC66: =(AB66/AB67)-1 -> 21.293252 | AD66: 0.068261994 | AF66: Sep 16, 2021 | AG66: 181.69 | AH66: =(AG66/AG67)-1 -> 21.293252 | AI66: 0.068261994 | AJ66: =_xlfn.NORM.INV(RAND(),VAR!$F$6,VAR!$F$7) -> -0.0088971993
AA67: Nov 11, 1999 | AB67: 8.15 | AC67: =(AB67/AB68)-1 -> 1.3554913 | AD67: 0.068152031 | AF67: Nov 11, 1999 | AG67: 8.15 | AH67: =(AG67/AG68)-1 -> 1.3554913 | AI67: 0.068152031 | AJ67: =_xlfn.NORM.INV(RAND(),VAR!$F$6,VAR!$F$7) -> 0.021984701
AA68: Dec 26, 1996 | AB68: 3.46 | AC68: =(AB68/AB69)-1 -> -0.59389671 | AD68: 0.067901235 | AF68: Dec 26, 1996 | AG68: 3.46 | AH68: =(AG68/AG69)-1 -> -0.59389671 | AI68: 0.067901235 | AJ68: =_xlfn.NORM.INV(RAND(),VAR!$F$6,VAR!$F$7) -> 0.017719853
AA69: Mar 8, 2001 | AB69: 8.52 | AC69: =(AB69/AB70)-1 -> 0.30875576 | AD69: 0.067669173 | AF69: Mar 8, 2001 | AG69: 8.52 | AH69: =(AG69/AG70)-1 -> 0.30875576 | AI69: 0.067669173 | AJ69: =_xlfn.NORM.INV(RAND(),VAR!$F$6,VAR!$F$7) -> -0.02012093
AA70: Oct 10, 1997 | AB70: 6.51 | AC70: =(AB70/AB71)-1 -> 0.31781377 | AD70: 0.067213115 | AF70: Oct 10, 1997 | AG70: 6.51 | AH70: =(AG70/AG71)-1 -> 0.31781377 | AI70: 0.067213115 | AJ70: =_xlfn.NORM.INV(RAND(),VAR!$F$6,VAR!$F$7) -> 0.027928216
AA71: Jun 2, 1997 | AB71: 4.94 | AC71: =(AB71/AB72)-1 -> 0.235 | AD71: 0.066954644 | AF71: Jun 2, 1997 | AG71: 4.94 | AH71: =(AG71/AG72)-1 -> 0.235 | AI71: 0.066954644 | AJ71: =_xlfn.NORM.INV(RAND(),VAR!$F$6,VAR!$F$7) -> 0.03447011
AA72: Jan 14, 1997 | AB72: 4 | AC72: =(AB72/AB73)-1 -> -0.88776655 | AD72: 0.066666667 | AF72: Jan 14, 1997 | AG72: 4 | AH72: =(AG72/AG73)-1 -> -0.88776655 | AI72: 0.066666667 | AJ72: =_xlfn.NORM.INV(RAND(),VAR!$F$6,VAR!$F$7) -> 0.0011024075
AA73: Jan 23, 2008 | AB73: 35.64 | AC73: =(AB73/AB74)-1 -> 11.081356 | AD73: 0.065470852 | AF73: Jan 23, 2008 | AG73: 35.64 | AH73: =(AG73/AG74)-1 -> 11.081356 | AI73: 0.065470852 | AJ73: =_xlfn.NORM.INV(RAND(),VAR!$F$6,VAR!$F$7) -> 0.029753201
AA74: Nov 18, 1996 | AB74: 2.95 | AC74: =(AB74/AB75)-1 -> -0.72378277 | AD74: 0.064981949 | AF74: Nov 18, 1996 | AG74: 2.95 | AH74: =(AG74/AG75)-1 -> -0.72378277 | AI74: 0.064981949 | AJ74: =_xlfn.NORM.INV(RAND(),VAR!$F$6,VAR!$F$7) -> -0.0071458645
AA75: Aug 18, 1999 | AB75: 10.68 | AC75: =(AB75/AB76)-1 -> 0.35018963 | AD75: 0.064805583 | AF75: Aug 18, 1999 | AG75: 10.68 | AH75: =(AG75/AG76)-1 -> 0.35018963 | AI75: 0.064805583 | AJ75: =_xlfn.NORM.INV(RAND(),VAR!$F$6,VAR!$F$7) -> 0.0038687037
AA76: Apr 1, 1998 | AB76: 7.91 | AC76: =(AB76/AB77)-1 -> 0.16838996 | AD76: 0.064602961 | AF76: Apr 1, 1998 | AG76: 7.91 | AH76: =(AG76/AG77)-1 -> 0.16838996 | AI76: 0.064602961 | AJ76: =_xlfn.NORM.INV(RAND(),VAR!$F$6,VAR!$F$7) -> -0.019634331
AA77: Oct 20, 1997 | AB77: 6.77 | AC77: =(AB77/AB78)-1 -> -0.95802592 | AD77: 0.062794349 | AF77: Oct 20, 1997 | AG77: 6.77 | AH77: =(AG77/AG78)-1 -> -0.95802592 | AI77: 0.062794349 | AJ77: =_xlfn.NORM.INV(RAND(),VAR!$F$6,VAR!$F$7) -> -0.00021265164
... AA7658: Mar 2, 2015 | AB7658: 146.73 | AC7658: =(AB7658/AB7659)-1 -> 55.434615 | AD7658: -0.12816399 | AF7658: Mar 2, 2015 | AG7658: 146.73 | AH7658: =(AG7658/AG7659)-1 -> 55.434615 | AI7658: -0.12816399 | AJ7658: =_xlfn.NORM.INV(RAND(),VAR!$F$6,VAR!$F$7) -> 0.052938802
AA7659: Jan 1, 1996 | AB7659: 2.6 | AF7659: Jan 1, 1996 | AG7659: 2.6
